Workbook

Sheet Data Angt
A1: LAPORAN ANGGOTA
F3: 2025
A4: No. Agt | B4: Nama | C4: TP | D4: JK | E4: Tgl Lahir | F4: USIA | G4: Pekerjaan | H4: PROFESI | I4: Bidang Usaha | J4: Nama Instansi
A5: 14053.001.1000.006 | B5: A1 | C5: PBL | D5: L | E5: 17-08-1949 | F5: 76 | G5: Pensiunan | H5: Pensiunan
A6: 14053.001.1000.008 | B6: A2 | C6: PBL | D6: L | E6: 11-07-1965 | F6: 60 | G6: Guru | H6: Tenaga Pengajar | I6: PENDIDIKAN | J6: SDK MATER DEI
A7: 14053.001.1000.009 | B7: A3 | C7: PBL | D7: L | E7: 23-12-1968 | F7: 57 | G7: Guru | H7: Tenaga Pengajar | I7: PENDIDIKAN | J7: SDK MATER DEI
A8: 14053.001.1000.012 | B8: A4 | C8: PBL | D8: P | E8: 07-10-1969 | F8: 56 | G8: Karyawan Swasta | H8: Karyawan | I8: PENDIDIKAN | J8: STELLA MARIS SURABAYA
A9: 14053.001.1000.031 | B9: A5 | C9: PBL | D9: P | E9: 10-12-1967 | F9: 58 | G9: Pembantu Rumah Tangga | H9: Lain-Lain | J9: ASRAMA MATER DEI
A10: 14053.001.1000.032 | B10: A6 | C10: PBL | D10: P | E10: 18-06-1967 | F10: 58 | G10: Mengurus Rumah Tangga | H10: Mengurus Rumah Tangga | I10: RUMAH TANGGA | J10: IBU RUMAH TANGGA
A11: 14053.001.1000.033 | B11: A7 | C11: PBL | D11: P | E11: 01-07-1941 | F11: 84 | G11: Mengurus Rumah Tangga | H11: Mengurus Rumah Tangga
A12: 14053.001.1000.037 | B12: A8 | C12: PBL | D12: L | E12: 16-08-1966 | F12: 59 | G12: Pensiunan | H12: Pensiunan | I12: SDK MATER DEI | J12: SDK MATER DEI
A13: 14053.001.1000.039 | B13: A9 | C13: PBL | D13: P | E13: 10-11-1965 | F13: 60 | G13: Pensiunan | H13: Pensiunan | I13: PENDIDIKAN | J13: SDK MATER DEI
A14: 14053.001.1000.040 | B14: A10 | C14: PBL | D14: P | E14: 13-09-1960 | F14: 65 | G14: Pensiunan | H14: Pensiunan | J14: SDK MATER DEI
A15: 14053.001.1000.041 | B15: A11 | C15: PBL | D15: L | E15: 29-05-1972 | F15: 53 | G15: Guru | H15: Tenaga Pengajar | I15: PENDIDIKAN | J15: SDK MATER DEI
A16: 14053.001.1000.042 | B16: A12 | C16: PBL | D16: P | E16: 10-11-1964 | F16: 61 | G16: Wiraswasta | H16: Wiraswasta | I16: TOKO SEPATU | J16: TOKO GAYAKU
A17: 14053.001.1000.045 | B17: A13 | C17: PBL | D17: P | E17: 21-11-1963 | F17: 62 | G17: Wiraswasta | H17: Wiraswasta | I17: PERDAGANGAN | J17: TOKO KELONTONG
A18: 14053.001.1000.047 | B18: A14 | C18: PBL | D18: P | E18: 21-12-1956 | F18: 69 | G18: Pensiunan | H18: Pensiunan | I18: GURU | J18: SMPK MATER DEI
A19: 14053.001.1000.049 | B19: A15 | C19: PBL | D19: P | E19: 18-08-1970 | F19: 55 | G19: Guru | H19: Tenaga Pengajar | I19: PENDIDIKAN | J19: SMPK MATER DEI
A20: 14053.001.1000.051 | B20: A16 | C20: PBL | D20: P | E20: 25-10-1970 | F20: 55 | G20: Guru | H20: Tenaga Pengajar | I20: PENDIDIKAN | J20: SDK MATER DEI
A21: 14053.001.1000.052 | B21: A17 | C21: PBL | D21: L | E21: 28-07-1965 | F21: 60 | G21: Guru | H21: Tenaga Pengajar | I21: PENDIDIKAN | J21: SMPK MATER DEI
A22: 14053.001.1000.053 | B22: A18 | C22: PBL | D22: P | E22: 09-09-1948 | F22: 77 | G22: Pensiunan | H22: Pensiunan | J22: SMPK MATER DEI
A23: 14053.001.1000.054 | B23: A19 | C23: PBL | D23: P | E23: 17-03-1962 | F23: 63 | G23: Pensiunan | H23: Pensiunan | J23: SMPK MATER DEI
A24: 14053.001.1000.056 | B24: A20 | C24: PBL | D24: L | E24: 10-08-1952 | F24: 73 | G24: Pensiunan | H24: Pensiunan | I24: PENDIDIKAN | J24: SMAK MATER DEI
A25: 14053.001.1000.058 | B25: A21 | C25: PBL | D25: P | E25: 01-07-1963 | F25: 62 | G25: Pembantu Rumah Tangga | H25: Lain-Lain | J25: ASRAMA ST. JAN
A26: 14053.001.1000.061 | B26: A22 | C26: PBL | D26: L | E26: 24-07-1960 | F26: 65 | G26: Wiraswasta | H26: Wiraswasta | I26: PEMILIK TOKO PERACANGAN | J26: TOKO PERACANGAN
A27: 14053.001.1000.069 | B27: A23 | C27: PBL | D27: P | E27: 31-10-1972 | F27: 53 | G27: Guru | H27: Tenaga Pengajar | I27: PENDIDIKAN | J27: TK MATER DEI
A28: 14053.001.1000.070 | B28: A24 | C28: PBL | D28: P | E28: 20-11-1966 | F28: 59 | G28: Guru | H28: Tenaga Pengajar | I28: PENDIDIKAN | J28: TKK MATER DEI PROBOLINGGO
A29: 14053.001.1000.071 | B29: A25 | C29: PBL | D29: L | E29: 11-09-1959 | F29: 66 | G29: Pensiunan | H29: Pensiunan | J29: SMUK MATER DEI
A30: 14053.001.1000.082 | B30: A26 | C30: PBL | D30: P | E30: 14-12-1974 | F30: 51 | G30: Perawat | H30: Tenaga Medis | I30: KESEHATAN GIGI | J30: PERAWAT GIGI
A31: 14053.001.1000.084 | B31: A27 | C31: PBL | D31: P | E31: 10-12-1964 | F31: 61 | G31: Pensiunan | H31: Pensiunan | I31: WIRAUSAHA | J31: SMPK MATER DEI
A32: 14053.001.1000.087 | B32: A28 | C32: PBL | D32: L | E32: 14-11-1947 | F32: 78 | G32: Pensiunan | H32: Pensiunan
A33: 14053.001.1000.090 | B33: A29 | C33: PBL | D33: L | E33: 10-05-1965 | F33: 60 | G33: Pensiunan | H33: Pensiunan | J33: SMPK MATER DEI
A34: 14053.001.1000.097 | B34: A30 | C34: PBL | D34: P | E34: 30-11-1956 | F34: 69 | G34: Pensiunan | H34: Pensiunan | J34: SMPK MATER DEI
A35: 14053.001.1000.098 | B35: A31 | C35: PBL | D35: P | E35: 13-03-1966 | F35: 59 | G35: Pensiunan | H35: Tenaga Pengajar | I35: PENDIDIKAN | J35: TK MATER DEI
A36: 14053.001.1000.101 | B36: A32 | C36: PBL | D36: P | E36: 11-05-1967 | F36: 58 | G36: Guru | H36: Tenaga Pengajar | I36: PENDIDIKAN | J36: TK MATER DEI
A37: 14053.001.1000.106 | B37: A33 | C37: PBL | D37: P | E37: 11-08-1971 | F37: 54 | G37: Guru | H37: Tenaga Pengajar | I37: PENDIDIKAN | J37: SD MATER DEI
A38: 14053.001.1000.107 | B38: A34 | C38: PBL | D38: P | E38: 12-03-1963 | F38: 62 | G38: Karyawan Swasta | H38: Karyawan | I38: KESEHATAN | J38: APOTIK SUMBER BARU
A39: 14053.001.1000.110 | B39: A35 | C39: PBL | D39: L | E39: 03-10-1972 | F39: 53 | G39: Karyawan Swasta | H39: Karyawan | I39: KEBERSIHAN | J39: TK MATER DEI
A40: 14053.001.1000.116 | B40: A36 | C40: PBL | D40: P | E40: 24-10-1959 | F40: 66 | G40: Pensiunan | H40: Pensiunan | J40: SDK MATER DEI
A41: 14053.001.1000.117 | B41: A37 | C41: PBL | D41: P | E41: 14-10-1960 | F41: 65 | G41: Pensiunan | H41: Pensiunan | I41: PENDIDIKAN | J41: SMAK MATER DEI
A42: 14053.001.1000.122 | B42: A38 | C42: PBL | D42: L | E42: 02-10-1973 | F42: 52 | G42: Karyawan Swasta | H42: Karyawan | I42: TUKANG KEBUN | J42: TK MATER DEI
A43: 14053.001.1000.124 | B43: A39 | C43: PBL | D43: L | E43: 29-08-1976 | F43: 49 | G43: Karyawan Swasta | H43: Karyawan | I43: TATA USAHA | J43: TU SMAK MATER DEI
A44: 14053.001.1000.131 | B44: A40 | C44: PBL | D44: P | E44: 29-09-1968 | F44: 57 | G44: Guru | H44: Tenaga Pengajar | I44: PENDIDIKAN | J44: SDK MATER DEI
A45: 14053.001.1000.139 | B45: A41 | C45: PBL | D45: L | E45: 16-05-1969 | F45: 56 | G45: Guru | H45: Tenaga Pengajar | I45: PENDIDIKAN | J45: SMPK MATER DEI
A46: 14053.001.1000.140 | B46: A42 | C46: PBL | D46: P | E46: 05-09-1955 | F46: 70 | G46: Belum/Tidak Bekerja | H46: Mengurus Rumah Tangga | I46: MENGURUS RUMAH TANGGA
A47: 14053.001.1000.141 | B47: A43 | C47: PBL | D47: L | E47: 03-08-1956 | F47: 69 | G47: Buruh Harian Lepas | H47: Lain-Lain | I47: JASA BECAK | J47: TUKANG BECAK
A48: 14053.001.1000.163 | B48: A44 | C48: PBL | D48: P | E48: 27-08-1958 | F48: 67 | G48: Wiraswasta | H48: Wiraswasta | I48: PERDAGANGAN | J48: TOKO JAMU
A49: 14053.001.1000.172 | B49: A45 | C49: PBL | D49: L | E49: 14-06-1971 | F49: 54 | G49: Guru | H49: Tenaga Pengajar | I49: PENDIDIKAN | J49: SMAK MATER DEI
A50: 14053.001.1000.173 | B50: A46 | C50: PBL | D50: P | E50: 02-08-1957 | F50: 68 | G50: Pensiunan | H50: Pensiunan | I50: PENDIDIKAN | J50: SDN SUKABUMI 2
A51: 14053.001.1000.174 | B51: A47 | C51: PBL | D51: P | E51: 10-04-1960 | F51: 65 | G51: Pensiunan | H51: Pensiunan | J51: SMAK MATER DEI
A52: 14053.001.1000.185 | B52: A48 | C52: PBL | D52: P | E52: 11-02-1965 | F52: 60 | G52: Wiraswasta | H52: Wiraswasta | I52: CATERING | J52: CATERING BU SRI
A53: 14053.001.1000.192 | B53: A49 | C53: PBL | D53: P | E53: 21-04-1971 | F53: 54 | G53: Guru | H53: Tenaga Pengajar | I53: PENDIDIKAN | J53: SMAK MATER DEI
A54: 14053.001.1000.197 | B54: A50 | C54: PBL | D54: P | E54: 24-01-1964 | F54: 61 | G54: Biarawati | H54: Pemuka Agama | I54: BIARAWATI
A55: 14053.001.1000.198 | B55: A51 | C55: PBL | D55: P | E55: 02-11-1963 | F55: 62 | G55: Pensiunan | H55: Pensiunan | I55: PENSIUNAN GURU SDK | J55: SDK MATER DEI
A56: 14053.001.1000.205 | B56: A52 | C56: PBL | D56: L | E56: 01-07-1961 | F56: 64 | G56: Buruh Harian Lepas | H56: Lain-Lain | I56: TUKANG BECAK, WAKER | J56: TUKANG BECAK
A57: 14053.001.1000.219 | B57: A53 | C57: PBL | D57: P | E57: 20-07-1966 | F57: 59 | G57: Wiraswasta | H57: Wiraswasta | I57: PABRIK KERAMIK | J57: KERAMIK PAOLO
A58: 14053.001.1000.220 | B58: A54 | C58: PBL | D58: L | E58: 01-01-1971 | F58: 54 | G58: Buruh Nelayan/Perikanan | H58: Lain-Lain | I58: TUKANG BECAK | J58: TUKANG BECAK
A59: 14053.001.1000.221 | B59: A55 | C59: PBL | D59: L | E59: 22-01-1971 | F59: 54 | G59: Pegawai Negeri Sipil | H59: Aparatur/Pejabat Negara | I59: PNS | J59: BPPKAD
A60: 14053.001.1000.222 | B60: A56 | C60: PBL | D60: P | E60: 01-06-1978 | F60: 47 | G60: Bidan | H60: Tenaga Medis | I60: TENAGA PROFESIONAL | J60: PUSKESMAS
A61: 14053.001.1000.224 | B61: A57 | C61: PBL | D61: P | E61: 05-07-1961 | F61: 64 | G61: Mengurus Rumah Tangga | H61: Mengurus Rumah Tangga | J61: IBU RUMAH TANGGA
A62: 14053.001.1000.225 | B62: A58 | C62: PBL | D62: L | E62: 19-09-1969 | F62: 56 | G62: Guru | H62: Tenaga Pengajar | I62: PENDIDIKAN | J62: SMAK MATER DEI
A63: 14053.001.1000.237 | B63: A59 | C63: PBL | D63: P | E63: 24-02-1963 | F63: 62 | G63: Pensiunan | H63: Pensiunan | I63: PENDIDIKAN | J63: GURU SDN KANIGARAN 10
A64: 14053.001.1000.238 | B64: A60 | C64: PBL | D64: P | E64: 31-12-1966 | F64: 59 | G64: Guru | H64: Tenaga Pengajar | I64: PENDIDIKAN | J64: SMPK MATER DEI
A65: 14053.001.1000.259 | B65: A61 | C65: PBL | D65: P | E65: 11-10-1968 | F65: 57 | G65: Mengurus Rumah Tangga | H65: Mengurus Rumah Tangga | J65: IBU RUMAH TANGGA
A66: 14053.006.1000.278 | B66: A62 | C66: MGL | D66: P | E66: 07-12-1965 | F66: 60 | G66: Karyawan Swasta | H66: Karyawan | I66: ASISTEN RUMAHTANGGA | J66: SUSTERAN SPM
A67: 14053.006.1000.281 | B67: A63 | C67: MGL | D67: L | E67: 12-10-1952 | F67: 73 | G67: WIRASWASTA | H67: Karyawan
A68: 14053.006.1000.282 | B68: A64 | C68: MGL | D68: L | E68: 13-07-1959 | F68: 66 | G68: WIRASWASTA | H68: Karyawan
A69: 14053.006.1000.285 | B69: A65 | C69: MGL | D69: P | E69: 12-04-1965 | F69: 60 | G69: Karyawan Swasta | H69: Karyawan | J69: BP SANTA MARIA
A70: 14053.006.1000.287 | B70: A66 | C70: MGL | D70: P | E70: 07-09-1969 | F70: 56 | G70: Guru | H70: Tenaga Pengajar | J70: SMPK SANTA MARIA TUMPANG
A71: 14053.006.1000.288 | B71: A67 | C71: MGL | D71: L | E71: 09-12-1959 | F71: 66 | G71: Guru | H71: Pensiunan | J71: SMPK SANTA MARIA YOGYAKARTA
A72: 14053.006.1000.290 | B72: A68 | C72: MGL | D72: P | E72: 05-03-1963 | F72: 62 | G72: Dokter | H72: Tenaga Medis | I72: KESEHATAN | J72: BALAI PENGOBATAN SANTA MARIA
A73: 14053.006.1000.296 | B73: A69 | C73: MGL | D73: L | E73: 05-03-1950 | F73: 75 | G73: Karyawan Swasta | H73: Karyawan | J73: TOKO MEBEL
A74: 14053.001.1000.301 | B74: A70 | C74: PBL | D74: P | E74: 24-09-1976 | F74: 49 | G74: Karyawan Swasta | H74: Karyawan | I74: JASA KEUANGAN | J74: CU MANDIRI
A75: 14053.001.1000.302 | B75: A71 | C75: PBL | D75: P | E75: 21-01-1965 | F75: 60 | G75: Wiraswasta | H75: Wiraswasta | I75: KULINER
A76: 14053.001.1000.305 | B76: A72 | C76: PBL | D76: P | E76: 07-02-1956 | F76: 69 | G76: Pensiunan | H76: Pensiunan
A77: 14053.001.1000.308 | B77: A73 | C77: PBL | D77: P | E77: 14-06-1963 | F77: 62 | G77: Guru | H77: Pensiunan | I77: PENDIDIKAN | J77: TK KUNCUP HARAPAN
A78: 14053.001.1000.310 | B78: A74 | C78: PBL | D78: P | E78: 22-09-1972 | F78: 53 | G78: Wiraswasta | H78: Wiraswasta | I78: KULINER | J78: BAKERY
A79: 14053.001.1000.311 | B79: A75 | C79: PBL | D79: P | E79: 07-01-1965 | F79: 60 | G79: Mengurus Rumah Tangga | H79: Wiraswasta | I79: WIRASWASTA DISTRIBUTOR BENIH PADI | J79: TOKO TANI MAKMUR
A80: 14053.006.1000.312 | B80: A76 | C80: MGL | D80: L | E80: 14-09-1961 | F80: 64 | G80: SWASTA | H80: Wiraswasta | J80: JASA KONSTRUKSI
A81: 14053.001.1000.316 | B81: A77 | C81: PBL | D81: P | E81: 15-06-1965 | F81: 60 | G81: Pembantu Rumah Tangga | H81: Karyawan | J81: SUSTERAN MAGNIFICAT
A82: 14053.001.1000.318 | B82: A78 | C82: PBL | D82: L | E82: 09-04-1982 | F82: 43 | G82: Wiraswasta | H82: Wiraswasta | I82: KULINER
A83: 14053.001.1000.319 | B83: A79 | C83: PBL | D83: P | E83: 10-06-1963 | F83: 62 | G83: Mengurus Rumah Tangga | H83: Mengurus Rumah Tangga | J83: SUSTERAN
A84: 14053.006.1000.320 | B84: A80 | C84: MGL | D84: L | E84: 10-01-1973 | F84: 52 | G84: Karyawan Swasta | H84: Karyawan | J84: LAB. PRODIA
A85: 14053.006.1000.321 | B85: A81 | C85: MGL | D85: L | E85: 06-11-1967 | F85: 58 | G85: Karyawan Swasta | H85: Wiraswasta | I85: LOKET PEMBAYARAN LISTRIK | J85: DUTA ELEKTRONIK
A86: 14053.001.1000.323 | B86: A82 | C86: PBL | D86: P | E86: 17-12-1944 | F86: 81 | G86: Mengurus Rumah Tangga | H86: Mengurus Rumah Tangga | J86: IBU RUMAH TANGGA
A87: 14053.001.1000.326 | B87: A83 | C87: PBL | D87: P | E87: 26-05-1974 | F87: 51 | G87: Wiraswasta | H87: Wiraswasta | I87: KULINER | J87: MOO GEMOY
A88: 14053.006.1000.330 | B88: A84 | C88: MGL | D88: L | E88: 04-06-1978 | F88: 47 | G88: Karyawan Swasta | H88: Karyawan
A89: 14053.006.1000.331 | B89: A85 | C89: MGL | D89: P | E89: 09-02-1975 | F89: 50 | G89: WIRASWASTA | H89: Wiraswasta
A90: 14053.001.1000.332 | B90: A86 | C90: PBL | D90: P | E90: 26-09-1959 | F90: 66 | G90: Mengurus Rumah Tangga | H90: Mengurus Rumah Tangga
A91: 14053.001.1000.333 | B91: A87 | C91: PBL | D91: P | E91: 02-11-1948 | F91: 77 | G91: Pensiunan | H91: Pensiunan
A92: 14053.006.1000.334 | B92: A88 | C92: MGL | D92: P | E92: 04-02-1979 | F92: 46 | G92: Karyawan Swasta | H92: Karyawan | J92: GEREJA SANTA MARIA
A93: 14053.001.1000.338 | B93: A89 | C93: PBL | D93: P | E93: 04-04-1998 | F93: 27
A94: 14053.001.1000.340 | B94: A90 | C94: PBL | D94: P | E94: 25-08-1955 | F94: 70 | G94: Wiraswasta | H94: Wiraswasta | I94: SARANG BURUNG WALET
A95: 14053.001.1000.342 | B95: A91 | C95: PBL | D95: P | E95: 01-09-1971 | F95: 54 | G95: Pembantu Rumah Tangga | H95: Lain-Lain | I95: ASISTEN RUMAH TANGGA
A96: 14053.006.1000.346 | B96: A92 | C96: MGL | D96: L | E96: 07-11-1973 | F96: 52 | H96: Karyawan
A97: 14053.006.1000.347 | B97: A93 | C97: MGL | D97: L | E97: 30-10-1948 | F97: 77 | G97: Pensiunan | H97: Pensiunan
A98: 14053.006.1000.348 | B98: A94 | C98: MGL | D98: P | E98: 01-11-1972 | F98: 53 | G98: Pedagang | H98: Wiraswasta
A99: 14053.001.1000.349 | B99: A95 | C99: PBL | D99: L | E99: 16-05-1970 | F99: 55 | G99: Guru | H99: Tenaga Pengajar | I99: PENDIDIKAN | J99: SDK MATER DEI
A100: 14053.006.1000.350 | B100: A96 | C100: MGL | D100: P | E100: 29-03-1973 | F100: 52 | G100: SWASTA | H100: Karyawan
A101: 14053.001.1000.353 | B101: A97 | C101: PBL | D101: P | E101: 02-06-1972 | F101: 53 | G101: Buruh Tani/Perkebunan | H101: Lain-Lain
...

Sheet Rekap
B2: 1 | C2: KLASIFIKASI USIA ANGGOTA | I2: KLASIFIKASI USIA PEMINJAM | M2: KLASIFIKASI TUJUAN PINJAMAN | T2: KLASIFIKASI USIA PENABUNG
C3: Usia | D3: Jml Agt | E3: % | I3: Usia | J3: Jml Agt | K3: % | M3: Usia | N3: Jml Agt | O3: % | T3: Usia | U3: SSKA | V3: SJTA | W3: SPJ | X3: SMP
C4: < 17 | D4: =COUNTIF('Data Angt'!$F$5:$F$5710,"<17") -> 9 | E4: =D4/$D$8 -> 0.0015889831 | I4: <= 23 | J4: =COUNTIF(Pinjaman!$V$6:$V$1373,"<24") -> 30 | K4: =J4/$J$7 -> 0.021945867 | M4: KONSUMTIF | N4: =COUNTIF(Pinjaman!$W$6:$W$1373,M4) -> 312 | O4: =N4/$N$10 -> 0.22807018 | T4: <= 23 | U4: =COUNTIF(SSKA!$P$7:$P$466,"<24") -> 0 | V4: =COUNTIF(SJTA!$R$6:$R$331,"<24") -> 27 | W4: =COUNTIF(SPJ!$O$5:$O$136,"<24") -> 9 | X4: =COUNTIF(SMP!$O$6:$O$15,"<24") -> 0
C5: 17 - 23 | D5: =COUNTIF('Data Angt'!$F$5:$F$5710,"<24")-COUNTIF('Data Angt'!$F$5:$F$5710,"<17") -> 322 | E5: =D5/$D$8 -> 0.056850282 | I5: 24 - 60 | J5: =COUNTIF(Pinjaman!$V$6:$V$1373,"<=60")-COUNTIF(Pinjaman!$V$6:$V$1373,"<24") -> 1188 | K5: =J5/$J$7 -> 0.86905633 | M5: KESEJAHTERAAN | N5: =COUNTIF(Pinjaman!$W$6:$W$1373,M5) -> 234 | O5: =N5/$N$10 -> 0.17105263 | T5: 24 - 60 | U5: =COUNTIF(SSKA!$P$7:$P$466,"<=60")-COUNTIF(SSKA!$P$7:$P$466,"<24") -> 0 | V5: =COUNTIF(SJTA!$R$6:$R$331,"<=60")-COUNTIF(SJTA!$R$6:$R$331,"<24") -> 215 | W5: =COUNTIF(SPJ!$O$5:$O$136,"<=60")-COUNTIF(SPJ!$O$5:$O$136,"<24") -> 121 | X5: =COUNTIF(SMP!$O$6:$O$15,"<=60")-COUNTIF(SMP!$O$6:$O$15,"<24") -> 8
C6: 24 - 60 | D6: =COUNTIF('Data Angt'!$F$5:$F$5710,"<=60")-COUNTIF('Data Angt'!$F$5:$F$5710,"<24") -> 4469 | E6: =D6/$D$8 -> 0.78901836 | I6: > 60 | J6: =COUNTIF(Pinjaman!$V$6:$V$1373,">60") -> 149 | K6: =J6/$J$7 -> 0.10899781 | M6: PENDIDIKAN | N6: =COUNTIF(Pinjaman!$W$6:$W$1373,M6) -> 209 | O6: =N6/$N$10 -> 0.15277778 | T6: > 60 | U6: =COUNTIF(SSKA!$P$7:$P$466,">60") -> 0 | V6: =COUNTIF(SJTA!$R$6:$R$331,">60") -> 74 | W6: =COUNTIF(SPJ!$O$5:$O$136,">60") -> 2 | X6: =COUNTIF(SMP!$O$6:$O$15,">60") -> 2
C7: > 60 | D7: =COUNTIF('Data Angt'!$F$5:$F$5710,">60") -> 864 | E7: =D7/$D$8 -> 0.15254237 | I7: JML | J7: =SUM(J4:J6) -> 1367 | K7: =J7/$J$7 -> 1 | M7: PRODUKTIF | N7: =COUNTIF(Pinjaman!$W$6:$W$1373,M7) -> 529 | O7: =N7/$N$10 -> 0.38669591 | T7: JML | U7: =SUM(U4:U6) -> 0 | V7: =SUM(V4:V6) -> 316 | W7: =SUM(W4:W6) -> 132 | X7: =SUM(X4:X6) -> 10
C8: JML | D8: =SUM(D4:D7) -> 5664 | E8: =D8/$D$8 -> 1 | M8: KESEHATAN | N8: =COUNTIF(Pinjaman!$W$6:$W$1373,M8) -> 16 | O8: =N8/$N$10 -> 0.011695906
D9: =D8-COUNTIF('Data Angt'!B5:B5710,"<>0") -> -42 | M9: DATA KOSONG | N9: =COUNTIF(Pinjaman!$W$6:$W$1373,0) -> 68 | O9: =N9/$N$10 -> 0.049707602
M10: JUMLAH | N10: =SUM(N4:N9) -> 1368 | O10: =N10/$N$10 -> 1 | T10: Profesi | U10: SSKA | V10: SJTA | W10: SPJ | X10: SMP
B11: 2 | C11: KLASIFIKASI PROFESI ANGGOTA | T11: Karyawan | U11: =COUNTIF(SSKA!$Q$7:$Q$466,Rekap!$T11) -> 0 | V11: =COUNTIF(SJTA!$S$6:$S$331,T11) -> 71 | W11: =COUNTIF(SPJ!$P$5:$P$136,T11) -> 33 | X11: =COUNTIF(SMP!$P$6:$P$15,T11) -> 4
C12: Profesi | D12: Jml Agt | E12: % | T12: Wiraswasta | U12: =COUNTIF(SSKA!$Q$7:$Q$466,Rekap!$T12) -> 0 | V12: =COUNTIF(SJTA!$S$6:$S$331,T12) -> 42 | W12: =COUNTIF(SPJ!$P$5:$P$136,T12) -> 28 | X12: =COUNTIF(SMP!$P$6:$P$15,T12) -> 2
C13: Karyawan | D13: =COUNTIF('Data Angt'!$H$5:$H$5710,C13) -> 1583 | E13: =D13/$D$27 -> 0.29533582 | I13: KLASIFIKASI TUJUAN PINJAMAN BERDASAR USIA PEMINJAM | T13: Pelajar/Mahasiswa | U13: =COUNTIF(SSKA!$Q$7:$Q$466,Rekap!$T13) -> 0 | V13: =COUNTIF(SJTA!$S$6:$S$331,T13) -> 25 | W13: =COUNTIF(SPJ!$P$5:$P$136,T13) -> 12 | X13: =COUNTIF(SMP!$P$6:$P$15,T13) -> 0
C14: Wiraswasta | D14: =COUNTIF('Data Angt'!$H$5:$H$5710,C14) -> 1339 | E14: =D14/$D$27 -> 0.24981343 | I14: USIA | J14: KONSUMTIF | K14: KESEJAHTERAAN | L14: PENDIDIKAN | M14: PRODUKTIF | N14: KESEHATAN | O14: DATA KOSONG | P14: JML | T14: Mengurus Rumah Tangga | U14: =COUNTIF(SSKA!$Q$7:$Q$466,Rekap!$T14) -> 0 | V14: =COUNTIF(SJTA!$S$6:$S$331,T14) -> 39 | W14: =COUNTIF(SPJ!$P$5:$P$136,T14) -> 22 | X14: =COUNTIF(SMP!$P$6:$P$15,T14) -> 0
C15: Pelajar/Mahasiswa | D15: =COUNTIF('Data Angt'!$H$5:$H$5710,C15) -> 229 | E15: =D15/$D$27 -> 0.042723881 | I15: < 17 | J15: =COUNTIFS(Pinjaman!$W$6:$W$1373,J$14,Pinjaman!$V$6:$V$1373,"<17") -> 0 | K15: =COUNTIFS(Pinjaman!$W$6:$W$1373,K$14,Pinjaman!$V$6:$V$1373,"<17") -> 0 | L15: =COUNTIFS(Pinjaman!$W$6:$W$1373,L$14,Pinjaman!$V$6:$V$1373,"<17") -> 0 | M15: =COUNTIFS(Pinjaman!$W$6:$W$1373,M$14,Pinjaman!$V$6:$V$1373,"<17") -> 0 | N15: =COUNTIFS(Pinjaman!$W$6:$W$1373,N$14,Pinjaman!$V$6:$V$1373,"<17") -> 0 | O15: =COUNTIFS(Pinjaman!W6:W1373,0,Pinjaman!V6:V1373,"<17") -> 0 | P15: =SUM(J15:O15) -> 0 | T15: Tenaga Pengajar | U15: =COUNTIF(SSKA!$Q$7:$Q$466,Rekap!$T15) -> 0 | V15: =COUNTIF(SJTA!$S$6:$S$331,T15) -> 37 | W15: =COUNTIF(SPJ!$P$5:$P$136,T15) -> 14 | X15: =COUNTIF(SMP!$P$6:$P$15,T15) -> 1
C16: Mengurus Rumah Tangga | D16: =COUNTIF('Data Angt'!$H$5:$H$5710,C16) -> 839 | E16: =D16/$D$27 -> 0.15652985 | I16: 17 - 23 | J16: =COUNTIFS(Pinjaman!$W$6:$W$1373,J$14,Pinjaman!$V$6:$V$1373,"<24")-COUNTIFS(Pinjaman!$W$6:$W$1373,J$14,Pinjaman!$V$6:$V$1373,"<17") -> 14 | K16: =COUNTIFS(Pinjaman!$W$6:$W$1373,K$14,Pinjaman!$V$6:$V$1373,"<24")-COUNTIFS(Pinjaman!$W$6:$W$1373,K$14,Pinjaman!$V$6:$V$1373,"<17") -> 6 | L16: =COUNTIFS(Pinjaman!$W$6:$W$1373,L$14,Pinjaman!$V$6:$V$1373,"<24")-COUNTIFS(Pinjaman!$W$6:$W$1373,L$14,Pinjaman!$V$6:$V$1373,"<17") -> 3 | M16: =COUNTIFS(Pinjaman!$W$6:$W$1373,M$14,Pinjaman!$V$6:$V$1373,"<24")-COUNTIFS(Pinjaman!$W$6:$W$1373,M$14,Pinjaman!$V$6:$V$1373,"<17") -> 7 | N16: =COUNTIFS(Pinjaman!$W$6:$W$1373,N$14,Pinjaman!$V$6:$V$1373,"<24")-COUNTIFS(Pinjaman!$W$6:$W$1373,N$14,Pinjaman!$V$6:$V$1373,"<17") -> 0 | O16: =COUNTIFS(Pinjaman!W6:W1373,0,Pinjaman!V6:V1373,"<24")-COUNTIFS(Pinjaman!W6:W1373,0,Pinjaman!V6:V1373,"<17") -> 0 | P16: =SUM(J16:O16) -> 30 | T16: Lain-Lain | U16: =COUNTIF(SSKA!$Q$7:$Q$466,Rekap!$T16) -> 0 | V16: =COUNTIF(SJTA!$S$6:$S$331,T16) -> 17 | W16: =COUNTIF(SPJ!$P$5:$P$136,T16) -> 4 | X16: =COUNTIF(SMP!$P$6:$P$15,T16) -> 0
C17: Tenaga Pengajar | D17: =COUNTIF('Data Angt'!$H$5:$H$5710,C17) -> 448 | E17: =D17/$D$27 -> 0.08358209 | I17: 24 - 60 | J17: =COUNTIFS(Pinjaman!$W$6:$W$1373,J$14,Pinjaman!$V$6:$V$1373,"<=60")-COUNTIFS(Pinjaman!$W$6:$W$1373,J$14,Pinjaman!$V$6:$V$1373,"<24") -> 260 | K17: =COUNTIFS(Pinjaman!$W$6:$W$1373,K$14,Pinjaman!$V$6:$V$1373,"<=60")-COUNTIFS(Pinjaman!$W$6:$W$1373,K$14,Pinjaman!$V$6:$V$1373,"<24") -> 198 | L17: =COUNTIFS(Pinjaman!$W$6:$W$1373,L$14,Pinjaman!$V$6:$V$1373,"<=60")-COUNTIFS(Pinjaman!$W$6:$W$1373,L$14,Pinjaman!$V$6:$V$1373,"<24") -> 196 | M17: =COUNTIFS(Pinjaman!$W$6:$W$1373,M$14,Pinjaman!$V$6:$V$1373,"<=60")-COUNTIFS(Pinjaman!$W$6:$W$1373,M$14,Pinjaman!$V$6:$V$1373,"<24") -> 464 | N17: =COUNTIFS(Pinjaman!$W$6:$W$1373,N$14,Pinjaman!$V$6:$V$1373,"<=60")-COUNTIFS(Pinjaman!$W$6:$W$1373,N$14,Pinjaman!$V$6:$V$1373,"<24") -> 13 | O17: =COUNTIFS(Pinjaman!W6:W1373,0,Pinjaman!V6:V1373,"<=60")-COUNTIFS(Pinjaman!W6:W1373,0,Pinjaman!V6:V1373,"<24") -> 57 | P17: =SUM(J17:O17) -> 1188 | T17: Aparatur Negara | U17: =COUNTIF(SSKA!$Q$7:$Q$466,Rekap!$T17) -> 0 | V17: =COUNTIF(SJTA!$S$6:$S$331,T17) -> 0 | W17: =COUNTIF(SPJ!$P$5:$P$136,T17) -> 0 | X17: =COUNTIF(SMP!$P$6:$P$15,T17) -> 0
C18: Tenaga Medis | I18: > 60 | J18: =COUNTIFS(Pinjaman!$W$6:$W$1373,J$14,Pinjaman!$V$6:$V$1373,">60") -> 38 | K18: =COUNTIFS(Pinjaman!$W$6:$W$1373,K$14,Pinjaman!$V$6:$V$1373,">60") -> 30 | L18: =COUNTIFS(Pinjaman!$W$6:$W$1373,L$14,Pinjaman!$V$6:$V$1373,">60") -> 10 | M18: =COUNTIFS(Pinjaman!$W$6:$W$1373,M$14,Pinjaman!$V$6:$V$1373,">60") -> 57 | N18: =COUNTIFS(Pinjaman!$W$6:$W$1373,N$14,Pinjaman!$V$6:$V$1373,">60") -> 3 | O18: =COUNTIFS(Pinjaman!W6:W1373,0,Pinjaman!V6:V1373,">60") -> 11 | P18: =SUM(J18:O18) -> 149 | T18: Pensiunan | U18: =COUNTIF(SSKA!$Q$7:$Q$466,Rekap!$T18) -> 0 | V18: =COUNTIF(SJTA!$S$6:$S$331,T18) -> 32 | W18: =COUNTIF(SPJ!$P$5:$P$136,T18) -> 4 | X18: =COUNTIF(SMP!$P$6:$P$15,T18) -> 1
C19: Lain-Lain | D19: =COUNTIF('Data Angt'!$H$5:$H$5710,C19) -> 245 | E19: =D19/$D$27 -> 0.045708955 | I19: JML | J19: =SUM(J15:J18) -> 312 | K19: =SUM(K15:K18) -> 234 | L19: =SUM(L15:L18) -> 209 | M19: =SUM(M15:M18) -> 528 | N19: =SUM(N15:N18) -> 16 | O19: =SUM(O15:O18) -> 68 | P19: =SUM(J19:O19) -> 1367 | T19: Pemuka Agama | U19: =COUNTIF(SSKA!$Q$7:$Q$466,Rekap!$T19) -> 0 | V19: =COUNTIF(SJTA!$S$6:$S$331,T19) -> 13 | W19: =COUNTIF(SPJ!$P$5:$P$136,T19) -> 0 | X19: =COUNTIF(SMP!$P$6:$P$15,T19) -> 0
C20: Aparatur Negara | D20: =COUNTIF('Data Angt'!$H$5:$H$5710,C20) -> 0 | E20: =D20/$D$27 -> 0 | T20: Petani/Pekebun/Nelayan/Peternak | U20: =COUNTIF(SSKA!$Q$7:$Q$466,Rekap!$T20) -> 0 | V20: =COUNTIF(SJTA!$S$6:$S$331,T20) -> 0 | W20: =COUNTIF(SPJ!$P$5:$P$136,T20) -> 0 | X20: =COUNTIF(SMP!$P$6:$P$15,T20) -> 0
C21: Pensiunan | D21: =COUNTIF('Data Angt'!$H$5:$H$5710,C21) -> 221 | E21: =D21/$D$27 -> 0.041231343 | T21: Tenaga Ahli | U21: =COUNTIF(SSKA!$Q$7:$Q$466,Rekap!$T21) -> 0 | V21: =COUNTIF(SJTA!$S$6:$S$331,T21) -> 1 | W21: =COUNTIF(SPJ!$P$5:$P$136,T21) -> 0 | X21: =COUNTIF(SMP!$P$6:$P$15,T21) -> 0
C22: Pemuka Agama | D22: =COUNTIF('Data Angt'!$H$5:$H$5710,C22) -> 53 | E22: =D22/$D$27 -> 0.0098880597 | I22: KLASIFIKASI TUJUAN PINJAMAN BERDASAR PROFESI PEMINJAM | T22: Belum/Tidak bekerja | U22: =COUNTIF(SSKA!$Q$7:$Q$466,Rekap!$T22) -> 0 | V22: =COUNTIF(SJTA!$S$6:$S$331,T22) -> 5 | W22: =COUNTIF(SPJ!$P$5:$P$136,T22) -> 1 | X22: =COUNTIF(SMP!$P$6:$P$15,T22) -> 0
C23: Petani/Pekebun/Nelayan/Peternak | D23: =COUNTIF('Data Angt'!$H$5:$H$5710,C23) -> 0 | E23: =D23/$D$27 -> 0 | I23: Profesi | J23: KONSUMTIF | K23: KESEJAHTERAAN | L23: PENDIDIKAN | M23: PRODUKTIF | N23: KESEHATAN | O23: DATA KOSONG | P23: JML | T23: Data Kosong | U23: =COUNTIF(SSKA!$Q$7:$Q$466,0) -> 0 | V23: =COUNTIF(SJTA!$S$6:$S$331,0) -> 11 | W23: =COUNTIF(SPJ!$P$5:$P$136,0) -> 1 | X23: =COUNTIF(SMP!$P$6:$P$15,0) -> 0
C24: Tenaga Ahli | D24: =COUNTIF('Data Angt'!$H$5:$H$5710,C24) -> 20 | E24: =D24/$D$27 -> 0.0037313433 | I24: Karyawan | J24: =COUNTIFS(Pinjaman!$W$6:$W$1373,J$23,Pinjaman!$X$6:$X$1373,$I24) -> 110 | K24: =COUNTIFS(Pinjaman!$W$6:$W$1373,K$23,Pinjaman!$X$6:$X$1373,$I24) -> 100 | L24: =COUNTIFS(Pinjaman!$W$6:$W$1373,L$23,Pinjaman!$X$6:$X$1373,$I24) -> 58 | M24: =COUNTIFS(Pinjaman!$W$6:$W$1373,M$23,Pinjaman!$X$6:$X$1373,$I24) -> 102 | N24: =COUNTIFS(Pinjaman!$W$6:$W$1373,N$23,Pinjaman!$X$6:$X$1373,$I24) -> 5 | O24: =COUNTIFS(Pinjaman!$W$6:$W$1373,0,Pinjaman!$X$6:$X$1373,$I24) -> 15 | P24: =SUM(J24:O24) -> 390 | T24: JUMLAH | U24: =SUM(U11:U23) -> 0 | V24: =SUM(V11:V23) -> 293 | W24: =SUM(W11:W23) -> 119 | X24: =SUM(X11:X23) -> 8
C25: Belum/Tidak bekerja | D25: =COUNTIF('Data Angt'!$H$5:$H$5710,C25) -> 86 | E25: =D25/$D$27 -> 0.016044776 | I25: Wiraswasta | J25: =COUNTIFS(Pinjaman!$W$6:$W$1373,J$23,Pinjaman!$X$6:$X$1373,$I25) -> 56 | K25: =COUNTIFS(Pinjaman!$W$6:$W$1373,K$23,Pinjaman!$X$6:$X$1373,$I25) -> 41 | L25: =COUNTIFS(Pinjaman!$W$6:$W$1373,L$23,Pinjaman!$X$6:$X$1373,$I25) -> 45 | M25: =COUNTIFS(Pinjaman!$W$6:$W$1373,M$23,Pinjaman!$X$6:$X$1373,$I25) -> 241 | N25: =COUNTIFS(Pinjaman!$W$6:$W$1373,N$23,Pinjaman!$X$6:$X$1373,$I25) -> 4 | O25: =COUNTIFS(Pinjaman!$W$6:$W$1373,0,Pinjaman!$X$6:$X$1373,$I25) -> 27 | P25: =SUM(J25:O25) -> 414
C26: Data Kosong | D26: =COUNTIF('Data Angt'!$H$5:$H$5710,"") -> 297 | E26: =D26/$D$27 -> 0.055410448 | I26: Pelajar/Mahasiswa | J26: =COUNTIFS(Pinjaman!$W$6:$W$1373,J$23,Pinjaman!$X$6:$X$1373,$I26) -> 4 | K26: =COUNTIFS(Pinjaman!$W$6:$W$1373,K$23,Pinjaman!$X$6:$X$1373,$I26) -> 0 | L26: =COUNTIFS(Pinjaman!$W$6:$W$1373,L$23,Pinjaman!$X$6:$X$1373,$I26) -> 1 | M26: =COUNTIFS(Pinjaman!$W$6:$W$1373,M$23,Pinjaman!$X$6:$X$1373,$I26) -> 4 | N26: =COUNTIFS(Pinjaman!$W$6:$W$1373,N$23,Pinjaman!$X$6:$X$1373,$I26) -> 0 | O26: =COUNTIFS(Pinjaman!$W$6:$W$1373,0,Pinjaman!$X$6:$X$1373,$I26) -> 0 | P26: =SUM(J26:O26) -> 9 | S26: Usia | T26: Profesi | U26: SSKA | V26: SJTA | W26: SPJ | X26: SMP
C27: JUMLAH | D27: =SUM(D13:D26) -> 5360 | E27: =D27/$D$27 -> 1 | I27: Mengurus Rumah Tangga | J27: =COUNTIFS(Pinjaman!$W$6:$W$1373,J$23,Pinjaman!$X$6:$X$1373,$I27) -> 46 | K27: =COUNTIFS(Pinjaman!$W$6:$W$1373,K$23,Pinjaman!$X$6:$X$1373,$I27) -> 25 | L27: =COUNTIFS(Pinjaman!$W$6:$W$1373,L$23,Pinjaman!$X$6:$X$1373,$I27) -> 26 | M27: =COUNTIFS(Pinjaman!$W$6:$W$1373,M$23,Pinjaman!$X$6:$X$1373,$I27) -> 71 | N27: =COUNTIFS(Pinjaman!$W$6:$W$1373,N$23,Pinjaman!$X$6:$X$1373,$I27) -> 3 | O27: =COUNTIFS(Pinjaman!$W$6:$W$1373,0,Pinjaman!$X$6:$X$1373,$I27) -> 13 | P27: =SUM(J27:O27) -> 184 | S27: <= 23 | T27: Karyawan | U27: =COUNTIFS(SSKA!$Q$7:$Q$466,Rekap!$T27,SSKA!$P$7:$P$466,"<24") -> 0 | V27: =COUNTIFS(SJTA!$S$6:$S$331,T27,SJTA!$R$6:$R$331,"<24") -> 1 | W27: =COUNTIFS(SPJ!$P$5:$P$136,T27,SPJ!O$5:O$136,"<24") -> 0 | X27: =COUNTIFS(SMP!$P$6:$P$15,T27,SMP!$O$6:$O$15,"<24") -> 0
I28: Tenaga Pengajar | J28: =COUNTIFS(Pinjaman!$W$6:$W$1373,J$23,Pinjaman!$X$6:$X$1373,$I28) -> 33 | K28: =COUNTIFS(Pinjaman!$W$6:$W$1373,K$23,Pinjaman!$X$6:$X$1373,$I28) -> 20 | L28: =COUNTIFS(Pinjaman!$W$6:$W$1373,L$23,Pinjaman!$X$6:$X$1373,$I28) -> 34 | M28: =COUNTIFS(Pinjaman!$W$6:$W$1373,M$23,Pinjaman!$X$6:$X$1373,$I28) -> 33 | N28: =COUNTIFS(Pinjaman!$W$6:$W$1373,N$23,Pinjaman!$X$6:$X$1373,$I28) -> 0 | O28: =COUNTIFS(Pinjaman!$W$6:$W$1373,0,Pinjaman!$X$6:$X$1373,$I28) -> 4 | P28: =SUM(J28:O28) -> 124 | T28: Wiraswasta | U28: =COUNTIFS(SSKA!$Q$7:$Q$466,Rekap!$T28,SSKA!$P$7:$P$466,"<24") -> 0 | V28: =COUNTIFS(SJTA!$S$6:$S$331,T28,SJTA!$R$6:$R$331,"<24") -> 0 | W28: =COUNTIFS(SPJ!$P$5:$P$136,T28,SPJ!O$5:O$136,"<24") -> 0 | X28: =COUNTIFS(SMP!$P$6:$P$15,T28,SMP!$O$6:$O$15,"<24") -> 0
B29: KLASIFIKASI PROFESI & USIA ANGGOTA | I29: Lain-Lain | J29: =COUNTIFS(Pinjaman!$W$6:$W$1373,J$23,Pinjaman!$X$6:$X$1373,$I29) -> 22 | K29: =COUNTIFS(Pinjaman!$W$6:$W$1373,K$23,Pinjaman!$X$6:$X$1373,$I29) -> 19 | L29: =COUNTIFS(Pinjaman!$W$6:$W$1373,L$23,Pinjaman!$X$6:$X$1373,$I29) -> 15 | M29: =COUNTIFS(Pinjaman!$W$6:$W$1373,M$23,Pinjaman!$X$6:$X$1373,$I29) -> 25 | N29: =COUNTIFS(Pinjaman!$W$6:$W$1373,N$23,Pinjaman!$X$6:$X$1373,$I29) -> 2 | O29: =COUNTIFS(Pinjaman!$W$6:$W$1373,0,Pinjaman!$X$6:$X$1373,$I29) -> 3 | P29: =SUM(J29:O29) -> 86 | T29: Pelajar/Mahasiswa | U29: =COUNTIFS(SSKA!$Q$7:$Q$466,Rekap!$T29,SSKA!$P$7:$P$466,"<24") -> 0 | V29: =COUNTIFS(SJTA!$S$6:$S$331,T29,SJTA!$R$6:$R$331,"<24") -> 22 | W29: =COUNTIFS(SPJ!$P$5:$P$136,T29,SPJ!O$5:O$136,"<24") -> 9 | X29: =COUNTIFS(SMP!$P$6:$P$15,T29,SMP!$O$6:$O$15,"<24") -> 0
B30: USIA | C30: Profesi | D30: Jml Agt | E30: % | I30: Aparatur Negara | J30: =COUNTIFS(Pinjaman!$W$6:$W$1373,J$23,Pinjaman!$X$6:$X$1373,$I30) -> 0 | K30: =COUNTIFS(Pinjaman!$W$6:$W$1373,K$23,Pinjaman!$X$6:$X$1373,$I30) -> 0 | L30: =COUNTIFS(Pinjaman!$W$6:$W$1373,L$23,Pinjaman!$X$6:$X$1373,$I30) -> 0 | M30: =COUNTIFS(Pinjaman!$W$6:$W$1373,M$23,Pinjaman!$X$6:$X$1373,$I30) -> 0 | N30: =COUNTIFS(Pinjaman!$W$6:$W$1373,N$23,Pinjaman!$X$6:$X$1373,$I30) -> 0 | O30: =COUNTIFS(Pinjaman!$W$6:$W$1373,0,Pinjaman!$X$6:$X$1373,$I30) -> 0 | P30: =SUM(J30:O30) -> 0 | T30: Mengurus Rumah Tangga | U30: =COUNTIFS(SSKA!$Q$7:$Q$466,Rekap!$T30,SSKA!$P$7:$P$466,"<24") -> 0 | V30: =COUNTIFS(SJTA!$S$6:$S$331,T30,SJTA!$R$6:$R$331,"<24") -> 0 | W30: =COUNTIFS(SPJ!$P$5:$P$136,T30,SPJ!O$5:O$136,"<24") -> 0 | X30: =COUNTIFS(SMP!$P$6:$P$15,T30,SMP!$O$6:$O$15,"<24") -> 0
B31: < 17 | C31: Karyawan | D31: =COUNTIFS('Data Angt'!$H$5:$H$5710,C31,'Data Angt'!$F$5:$F$5710,"<17") -> 1 | E31: =D31/$D$27 -> 0.00018656716 | I31: Pensiunan | J31: =COUNTIFS(Pinjaman!$W$6:$W$1373,J$23,Pinjaman!$X$6:$X$1373,$I31) -> 19 | K31: =COUNTIFS(Pinjaman!$W$6:$W$1373,K$23,Pinjaman!$X$6:$X$1373,$I31) -> 10 | L31: =COUNTIFS(Pinjaman!$W$6:$W$1373,L$23,Pinjaman!$X$6:$X$1373,$I31) -> 6 | M31: =COUNTIFS(Pinjaman!$W$6:$W$1373,M$23,Pinjaman!$X$6:$X$1373,$I31) -> 13 | N31: =COUNTIFS(Pinjaman!$W$6:$W$1373,N$23,Pinjaman!$X$6:$X$1373,$I31) -> 2 | O31: =COUNTIFS(Pinjaman!$W$6:$W$1373,0,Pinjaman!$X$6:$X$1373,$I31) -> 1 | P31: =SUM(J31:O31) -> 51 | T31: Tenaga Pengajar | U31: =COUNTIFS(SSKA!$Q$7:$Q$466,Rekap!$T31,SSKA!$P$7:$P$466,"<24") -> 0 | V31: =COUNTIFS(SJTA!$S$6:$S$331,T31,SJTA!$R$6:$R$331,"<24") -> 0 | W31: =COUNTIFS(SPJ!$P$5:$P$136,T31,SPJ!O$5:O$136,"<24") -> 0 | X31: =COUNTIFS(SMP!$P$6:$P$15,T31,SMP!$O$6:$O$15,"<24") -> 0
C32: Wiraswasta | D32: =COUNTIFS('Data Angt'!$H$5:$H$5710,C32,'Data Angt'!$F$5:$F$5710,"<17") -> 0 | E32: =D32/$D$27 -> 0 | H32: USIA | I32: Pemuka Agama | J32: =COUNTIFS(Pinjaman!$W$6:$W$1373,J$23,Pinjaman!$X$6:$X$1373,$I32) -> 0 | K32: =COUNTIFS(Pinjaman!$W$6:$W$1373,K$23,Pinjaman!$X$6:$X$1373,$I32) -> 0 | L32: =COUNTIFS(Pinjaman!$W$6:$W$1373,L$23,Pinjaman!$X$6:$X$1373,$I32) -> 0 | M32: =COUNTIFS(Pinjaman!$W$6:$W$1373,M$23,Pinjaman!$X$6:$X$1373,$I32) -> 1 | N32: =COUNTIFS(Pinjaman!$W$6:$W$1373,N$23,Pinjaman!$X$6:$X$1373,$I32) -> 0 | O32: =COUNTIFS(Pinjaman!$W$6:$W$1373,0,Pinjaman!$X$6:$X$1373,$I32) -> 0 | P32: =SUM(J32:O32) -> 1 | T32: Lain-Lain | U32: =COUNTIFS(SSKA!$Q$7:$Q$466,Rekap!$T32,SSKA!$P$7:$P$466,"<24") -> 0 | V32: =COUNTIFS(SJTA!$S$6:$S$331,T32,SJTA!$R$6:$R$331,"<24") -> 0 | W32: =COUNTIFS(SPJ!$P$5:$P$136,T32,SPJ!O$5:O$136,"<24") -> 0 | X32: =COUNTIFS(SMP!$P$6:$P$15,T32,SMP!$O$6:$O$15,"<24") -> 0
C33: Pelajar/Mahasiswa | D33: =COUNTIFS('Data Angt'!$H$5:$H$5710,C33,'Data Angt'!$F$5:$F$5710,"<17") -> 8 | E33: =D33/$D$27 -> 0.0014925373 | H33: < =23 | I33: Petani/Pekebun/Nelayan/Peternak | J33: =COUNTIFS(Pinjaman!$W$6:$W$1373,J$23,Pinjaman!$X$6:$X$1373,$I33) -> 0 | K33: =COUNTIFS(Pinjaman!$W$6:$W$1373,K$23,Pinjaman!$X$6:$X$1373,$I33) -> 0 | L33: =COUNTIFS(Pinjaman!$W$6:$W$1373,L$23,Pinjaman!$X$6:$X$1373,$I33) -> 0 | M33: =COUNTIFS(Pinjaman!$W$6:$W$1373,M$23,Pinjaman!$X$6:$X$1373,$I33) -> 0 | N33: =COUNTIFS(Pinjaman!$W$6:$W$1373,N$23,Pinjaman!$X$6:$X$1373,$I33) -> 0 | O33: =COUNTIFS(Pinjaman!$W$6:$W$1373,0,Pinjaman!$X$6:$X$1373,$I33) -> 0 | P33: =SUM(J33:O33) -> 0 | T33: Aparatur Negara | U33: =COUNTIFS(SSKA!$Q$7:$Q$466,Rekap!$T33,SSKA!$P$7:$P$466,"<24") -> 0 | V33: =COUNTIFS(SJTA!$S$6:$S$331,T33,SJTA!$R$6:$R$331,"<24") -> 0 | W33: =COUNTIFS(SPJ!$P$5:$P$136,T33,SPJ!O$5:O$136,"<24") -> 0 | X33: =COUNTIFS(SMP!$P$6:$P$15,T33,SMP!$O$6:$O$15,"<24") -> 0
C34: Mengurus Rumah Tangga | D34: =COUNTIFS('Data Angt'!$H$5:$H$5710,C34,'Data Angt'!$F$5:$F$5710,"<17") -> 0 | E34: =D34/$D$27 -> 0 | I34: Tenaga Ahli | J34: =COUNTIFS(Pinjaman!$W$6:$W$1373,J$23,Pinjaman!$X$6:$X$1373,$I34) -> 1 | K34: =COUNTIFS(Pinjaman!$W$6:$W$1373,K$23,Pinjaman!$X$6:$X$1373,$I34) -> 1 | L34: =COUNTIFS(Pinjaman!$W$6:$W$1373,L$23,Pinjaman!$X$6:$X$1373,$I34) -> 0 | M34: =COUNTIFS(Pinjaman!$W$6:$W$1373,M$23,Pinjaman!$X$6:$X$1373,$I34) -> 2 | N34: =COUNTIFS(Pinjaman!$W$6:$W$1373,N$23,Pinjaman!$X$6:$X$1373,$I34) -> 0 | O34: =COUNTIFS(Pinjaman!$W$6:$W$1373,0,Pinjaman!$X$6:$X$1373,$I34) -> 0 | P34: =SUM(J34:O34) -> 4 | T34: Pensiunan | U34: =COUNTIFS(SSKA!$Q$7:$Q$466,Rekap!$T34,SSKA!$P$7:$P$466,"<24") -> 0 | V34: =COUNTIFS(SJTA!$S$6:$S$331,T34,SJTA!$R$6:$R$331,"<24") -> 0 | W34: =COUNTIFS(SPJ!$P$5:$P$136,T34,SPJ!O$5:O$136,"<24") -> 0 | X34: =COUNTIFS(SMP!$P$6:$P$15,T34,SMP!$O$6:$O$15,"<24") -> 0
C35: Tenaga Pengajar | D35: =COUNTIFS('Data Angt'!$H$5:$H$5710,C35,'Data Angt'!$F$5:$F$5710,"<17") -> 0 | E35: =D35/$D$27 -> 0 | I35: Belum/Tidak bekerja | J35: =COUNTIFS(Pinjaman!$W$6:$W$1373,J$23,Pinjaman!$X$6:$X$1373,$I35) -> 1 | K35: =COUNTIFS(Pinjaman!$W$6:$W$1373,K$23,Pinjaman!$X$6:$X$1373,$I35) -> 0 | L35: =COUNTIFS(Pinjaman!$W$6:$W$1373,L$23,Pinjaman!$X$6:$X$1373,$I35) -> 1 | M35: =COUNTIFS(Pinjaman!$W$6:$W$1373,M$23,Pinjaman!$X$6:$X$1373,$I35) -> 3 | N35: =COUNTIFS(Pinjaman!$W$6:$W$1373,N$23,Pinjaman!$X$6:$X$1373,$I35) -> 0 | O35: =COUNTIFS(Pinjaman!$W$6:$W$1373,0,Pinjaman!$X$6:$X$1373,$I35) -> 0 | P35: =SUM(J35:O35) -> 5 | T35: Pemuka Agama | U35: =COUNTIFS(SSKA!$Q$7:$Q$466,Rekap!$T35,SSKA!$P$7:$P$466,"<24") -> 0 | V35: =COUNTIFS(SJTA!$S$6:$S$331,T35,SJTA!$R$6:$R$331,"<24") -> 0 | W35: =COUNTIFS(SPJ!$P$5:$P$136,T35,SPJ!O$5:O$136,"<24") -> 0 | X35: =COUNTIFS(SMP!$P$6:$P$15,T35,SMP!$O$6:$O$15,"<24") -> 0
C36: Lain-Lain | D36: =COUNTIFS('Data Angt'!$H$5:$H$5710,C36,'Data Angt'!$F$5:$F$5710,"<17") -> 0 | E36: =D36/$D$27 -> 0 | I36: Data Kosong | J36: =COUNTIFS(Pinjaman!$W$6:$W$1373,J$23,Pinjaman!$X$6:$X$1373,0) -> 4 | K36: =COUNTIFS(Pinjaman!$W$6:$W$1373,K$23,Pinjaman!$X$6:$X$1373,0) -> 4 | L36: =COUNTIFS(Pinjaman!$W$6:$W$1373,L$23,Pinjaman!$X$6:$X$1373,0) -> 2 | M36: =COUNTIFS(Pinjaman!$W$6:$W$1373,M$23,Pinjaman!$X$6:$X$1373,0) -> 6 | N36: =COUNTIFS(Pinjaman!$W$6:$W$1373,N$23,Pinjaman!$X$6:$X$1373,0) -> 0 | O36: =COUNTIFS(Pinjaman!$W$6:$W$1373,0,Pinjaman!$X$6:$X$1373,0) -> 1 | P36: =SUM(J36:O36) -> 17 | T36: Petani/Pekebun/Nelayan/Peternak | U36: =COUNTIFS(SSKA!$Q$7:$Q$466,Rekap!$T36,SSKA!$P$7:$P$466,"<24") -> 0 | V36: =COUNTIFS(SJTA!$S$6:$S$331,T36,SJTA!$R$6:$R$331,"<24") -> 0 | W36: =COUNTIFS(SPJ!$P$5:$P$136,T36,SPJ!O$5:O$136,"<24") -> 0 | X36: =COUNTIFS(SMP!$P$6:$P$15,T36,SMP!$O$6:$O$15,"<24") -> 0
C37: Aparatur Negara | D37: =COUNTIFS('Data Angt'!$H$5:$H$5710,C37,'Data Angt'!$F$5:$F$5710,"<17") -> 0 | E37: =D37/$D$27 -> 0 | I37: JUMLAH | J37: =SUM(J24:J36) -> 296 | K37: =SUM(K24:K36) -> 220 | L37: =SUM(L24:L36) -> 188 | M37: =SUM(M24:M36) -> 501 | N37: =SUM(N24:N36) -> 16 | O37: =SUM(O24:O36) -> 64 | P37: =SUM(P24:P36) -> 1285 | T37: Tenaga Ahli | U37: =COUNTIFS(SSKA!$Q$7:$Q$466,Rekap!$T37,SSKA!$P$7:$P$466,"<24") -> 0 | V37: =COUNTIFS(SJTA!$S$6:$S$331,T37,SJTA!$R$6:$R$331,"<24") -> 0 | W37: =COUNTIFS(SPJ!$P$5:$P$136,T37,SPJ!O$5:O$136,"<24") -> 0 | X37: =COUNTIFS(SMP!$P$6:$P$15,T37,SMP!$O$6:$O$15,"<24") -> 0
C38: Pensiunan | D38: =COUNTIFS('Data Angt'!$H$5:$H$5710,C38,'Data Angt'!$F$5:$F$5710,"<17") -> 0 | E38: =D38/$D$27 -> 0 | T38: Belum/Tidak bekerja | U38: =COUNTIFS(SSKA!$Q$7:$Q$466,Rekap!$T38,SSKA!$P$7:$P$466,"<24") -> 0 | V38: =COUNTIFS(SJTA!$S$6:$S$331,T38,SJTA!$R$6:$R$331,"<24") -> 1 | W38: =COUNTIFS(SPJ!$P$5:$P$136,T38,SPJ!O$5:O$136,"<24") -> 0 | X38: =COUNTIFS(SMP!$P$6:$P$15,T38,SMP!$O$6:$O$15,"<24") -> 0
C39: Pemuka Agama | D39: =COUNTIFS('Data Angt'!$H$5:$H$5710,C39,'Data Angt'!$F$5:$F$5710,"<17") -> 0 | E39: =D39/$D$27 -> 0 | T39: Data Kosong | U39: =COUNTIFS(SSKA!$Q$7:$Q$466,0,SSKA!$P$7:$P$466,"<24") -> 0 | V39: =COUNTIFS(SJTA!$S$6:$S$331,0,SJTA!$R$6:$R$331,"<24") -> 3 | W39: =COUNTIFS(SPJ!$P$5:$P$136,0,SPJ!O$5:O$136,"<24") -> 0 | X39: =COUNTIFS(SMP!$P$6:$P$15,0,SMP!$O$6:$O$15,"<24") -> 0
C40: Petani/Pekebun/Nelayan/Peternak | D40: =COUNTIFS('Data Angt'!$H$5:$H$5710,C40,'Data Angt'!$F$5:$F$5710,"<17") -> 0 | E40: =D40/$D$27 -> 0 | I40: Profesi | J40: KONSUMTIF | K40: KESEJAHTERAAN | L40: PENDIDIKAN | M40: PRODUKTIF | N40: KESEHATAN | O40: DATA KOSONG | P40: JML | T40: JUMLAH | U40: =SUM(U27:U39) -> 0 | V40: =SUM(V27:V39) -> 27 | W40: =SUM(W27:W39) -> 9 | X40: =SUM(X27:X39) -> 0
C41: Tenaga Ahli | D41: =COUNTIFS('Data Angt'!$H$5:$H$5710,C41,'Data Angt'!$F$5:$F$5710,"<17") -> 0 | E41: =D41/$D$27 -> 0 | I41: Karyawan | J41: =COUNTIFS(Pinjaman!$X$6:$X$1373,$I41,Pinjaman!$W$6:$W$1373,J$40,Pinjaman!$V$6:$V$1373,"<24") -> 9 | K41: =COUNTIFS(Pinjaman!$X$6:$X$1373,$I41,Pinjaman!$W$6:$W$1373,K$40,Pinjaman!$V$6:$V$1373,"<24") -> 5 | L41: =COUNTIFS(Pinjaman!$X$6:$X$1373,$I41,Pinjaman!$W$6:$W$1373,L$40,Pinjaman!$V$6:$V$1373,"<24") -> 0 | M41: =COUNTIFS(Pinjaman!$X$6:$X$1373,$I41,Pinjaman!$W$6:$W$1373,M$40,Pinjaman!$V$6:$V$1373,"<24") -> 1 | N41: =COUNTIFS(Pinjaman!$X$6:$X$1373,$I41,Pinjaman!$W$6:$W$1373,N$40,Pinjaman!$V$6:$V$1373,"<24") -> 0 | O41: =COUNTIFS(Pinjaman!$X$6:$X$1373,$I41,Pinjaman!$W$6:$W$1373,0,Pinjaman!$V$6:$V$1373,"<24") -> 0 | P41: =SUM(J41:O41) -> 15 | S41: 24 - 60 | T41: Karyawan | U41: =COUNTIFS(SSKA!$Q$7:$Q$466,Rekap!$T41,SSKA!$P$7:$P$466,"<=60")-COUNTIFS(SSKA!$Q$7:$Q$466,Rekap!$T41,SSKA!$P$7:$P$466,"<24") -> 0 | V41: =COUNTIFS(SJTA!$S$6:$S$331,T41,SJTA!$R$6:$R$331,"<=60")-COUNTIFS(SJTA!$S$6:$S$331,T41,SJTA!$R$6:$R$331,"<24") -> 66 | W41: =COUNTIFS(SPJ!$P$5:$P$136,T27,SPJ!O$5:O$136,"<=60")-COUNTIFS(SPJ!$P$5:$P$136,T27,SPJ!O$5:O$136,"<24") -> 33 | X41: =COUNTIFS(SMP!$P$6:$P$15,T41,SMP!$O$6:$O$15,"<=60")-COUNTIFS(SMP!$P$6:$P$15,T41,SMP!$O$6:$O$15,"<24") -> 4
C42: Belum/Tidak bekerja | D42: =COUNTIFS('Data Angt'!$H$5:$H$5710,C42,'Data Angt'!$F$5:$F$5710,"<17") -> 0 | E42: =D42/$D$27 -> 0 | I42: Wiraswasta | J42: =COUNTIFS(Pinjaman!$X$6:$X$1373,$I42,Pinjaman!$W$6:$W$1373,J$40,Pinjaman!$V$6:$V$1373,"<24") -> 0 | K42: =COUNTIFS(Pinjaman!$X$6:$X$1373,$I42,Pinjaman!$W$6:$W$1373,K$40,Pinjaman!$V$6:$V$1373,"<24") -> 0 | L42: =COUNTIFS(Pinjaman!$X$6:$X$1373,$I42,Pinjaman!$W$6:$W$1373,L$40,Pinjaman!$V$6:$V$1373,"<24") -> 0 | M42: =COUNTIFS(Pinjaman!$X$6:$X$1373,$I42,Pinjaman!$W$6:$W$1373,M$40,Pinjaman!$V$6:$V$1373,"<24") -> 2 | N42: =COUNTIFS(Pinjaman!$X$6:$X$1373,$I42,Pinjaman!$W$6:$W$1373,N$40,Pinjaman!$V$6:$V$1373,"<24") -> 0 | O42: =COUNTIFS(Pinjaman!$X$6:$X$1373,$I42,Pinjaman!$W$6:$W$1373,0,Pinjaman!$V$6:$V$1373,"<24") -> 0 | P42: =SUM(J42:O42) -> 2 | T42: Wiraswasta | U42: =COUNTIFS(SSKA!$Q$7:$Q$466,Rekap!$T42,SSKA!$P$7:$P$466,"<=60")-COUNTIFS(SSKA!$Q$7:$Q$466,Rekap!$T42,SSKA!$P$7:$P$466,"<24") -> 0 | V42: =COUNTIFS(SJTA!$S$6:$S$331,T42,SJTA!$R$6:$R$331,"<=60")-COUNTIFS(SJTA!$S$6:$S$331,T42,SJTA!$R$6:$R$331,"<24") -> 30 | W42: =COUNTIFS(SPJ!$P$5:$P$136,T28,SPJ!O$5:O$136,"<=60")-COUNTIFS(SPJ!$P$5:$P$136,T28,SPJ!O$5:O$136,"<24") -> 28 | X42: =COUNTIFS(SMP!$P$6:$P$15,T42,SMP!$O$6:$O$15,"<=60")-COUNTIFS(SMP!$P$6:$P$15,T42,SMP!$O$6:$O$15,"<24") -> 2
C43: Data Kosong | D43: =COUNTIFS('Data Angt'!$H$5:$H$5710,"",'Data Angt'!$F$5:$F$5710,"<17") -> 0 | E43: =D43/$D$27 -> 0 | I43: Pelajar/Mahasiswa | J43: =COUNTIFS(Pinjaman!$X$6:$X$1373,$I43,Pinjaman!$W$6:$W$1373,J$40,Pinjaman!$V$6:$V$1373,"<24") -> 3 | K43: =COUNTIFS(Pinjaman!$X$6:$X$1373,$I43,Pinjaman!$W$6:$W$1373,K$40,Pinjaman!$V$6:$V$1373,"<24") -> 0 | L43: =COUNTIFS(Pinjaman!$X$6:$X$1373,$I43,Pinjaman!$W$6:$W$1373,L$40,Pinjaman!$V$6:$V$1373,"<24") -> 1 | M43: =COUNTIFS(Pinjaman!$X$6:$X$1373,$I43,Pinjaman!$W$6:$W$1373,M$40,Pinjaman!$V$6:$V$1373,"<24") -> 3 | N43: =COUNTIFS(Pinjaman!$X$6:$X$1373,$I43,Pinjaman!$W$6:$W$1373,N$40,Pinjaman!$V$6:$V$1373,"<24") -> 0 | O43: =COUNTIFS(Pinjaman!$X$6:$X$1373,$I43,Pinjaman!$W$6:$W$1373,0,Pinjaman!$V$6:$V$1373,"<24") -> 0 | P43: =SUM(J43:O43) -> 7 | T43: Pelajar/Mahasiswa | U43: =COUNTIFS(SSKA!$Q$7:$Q$466,Rekap!$T43,SSKA!$P$7:$P$466,"<=60")-COUNTIFS(SSKA!$Q$7:$Q$466,Rekap!$T43,SSKA!$P$7:$P$466,"<24") -> 0 | V43: =COUNTIFS(SJTA!$S$6:$S$331,T43,SJTA!$R$6:$R$331,"<=60")-COUNTIFS(SJTA!$S$6:$S$331,T43,SJTA!$R$6:$R$331,"<24") -> 3 | W43: =COUNTIFS(SPJ!$P$5:$P$136,T29,SPJ!O$5:O$136,"<=60")-COUNTIFS(SPJ!$P$5:$P$136,T29,SPJ!O$5:O$136,"<24") -> 3 | X43: =COUNTIFS(SMP!$P$6:$P$15,T43,SMP!$O$6:$O$15,"<=60")-COUNTIFS(SMP!$P$6:$P$15,T43,SMP!$O$6:$O$15,"<24") -> 0
C44: JUMLAH | D44: =SUM(D31:D43) -> 9 | E44: =D44/$D$27 -> 0.0016791045 | I44: Mengurus Rumah Tangga | J44: =COUNTIFS(Pinjaman!$X$6:$X$1373,$I44,Pinjaman!$W$6:$W$1373,J$40,Pinjaman!$V$6:$V$1373,"<24") -> 0 | K44: =COUNTIFS(Pinjaman!$X$6:$X$1373,$I44,Pinjaman!$W$6:$W$1373,K$40,Pinjaman!$V$6:$V$1373,"<24") -> 0 | L44: =COUNTIFS(Pinjaman!$X$6:$X$1373,$I44,Pinjaman!$W$6:$W$1373,L$40,Pinjaman!$V$6:$V$1373,"<24") -> 1 | M44: =COUNTIFS(Pinjaman!$X$6:$X$1373,$I44,Pinjaman!$W$6:$W$1373,M$40,Pinjaman!$V$6:$V$1373,"<24") -> 0 | N44: =COUNTIFS(Pinjaman!$X$6:$X$1373,$I44,Pinjaman!$W$6:$W$1373,N$40,Pinjaman!$V$6:$V$1373,"<24") -> 0 | O44: =COUNTIFS(Pinjaman!$X$6:$X$1373,$I44,Pinjaman!$W$6:$W$1373,0,Pinjaman!$V$6:$V$1373,"<24") -> 0 | P44: =SUM(J44:O44) -> 1 | T44: Mengurus Rumah Tangga | U44: =COUNTIFS(SSKA!$Q$7:$Q$466,Rekap!$T44,SSKA!$P$7:$P$466,"<=60")-COUNTIFS(SSKA!$Q$7:$Q$466,Rekap!$T44,SSKA!$P$7:$P$466,"<24") -> 0 | V44: =COUNTIFS(SJTA!$S$6:$S$331,T44,SJTA!$R$6:$R$331,"<=60")-COUNTIFS(SJTA!$S$6:$S$331,T44,SJTA!$R$6:$R$331,"<24") -> 25 | W44: =COUNTIFS(SPJ!$P$5:$P$136,T30,SPJ!O$5:O$136,"<=60")-COUNTIFS(SPJ!$P$5:$P$136,T30,SPJ!O$5:O$136,"<24") -> 22 | X44: =COUNTIFS(SMP!$P$6:$P$15,T44,SMP!$O$6:$O$15,"<=60")-COUNTIFS(SMP!$P$6:$P$15,T44,SMP!$O$6:$O$15,"<24") -> 0
B45: 17 - 23 | C45: Karyawan | D45: =COUNTIFS('Data Angt'!$H$5:$H$5710,C45,'Data Angt'!$F$5:$F$5710,"<24")-COUNTIFS('Data Angt'!$H$5:$H$5710,C45,'Data Angt'!$F$5:$F$5710,"<17") -> 76 | E45: =D45/$D$27 -> 0.014179104 | I45: Tenaga Pengajar | J45: =COUNTIFS(Pinjaman!$X$6:$X$1373,$I45,Pinjaman!$W$6:$W$1373,J$40,Pinjaman!$V$6:$V$1373,"<24") -> 1 | K45: =COUNTIFS(Pinjaman!$X$6:$X$1373,$I45,Pinjaman!$W$6:$W$1373,K$40,Pinjaman!$V$6:$V$1373,"<24") -> 0 | L45: =COUNTIFS(Pinjaman!$X$6:$X$1373,$I45,Pinjaman!$W$6:$W$1373,L$40,Pinjaman!$V$6:$V$1373,"<24") -> 1 | M45: =COUNTIFS(Pinjaman!$X$6:$X$1373,$I45,Pinjaman!$W$6:$W$1373,M$40,Pinjaman!$V$6:$V$1373,"<24") -> 0 | N45: =COUNTIFS(Pinjaman!$X$6:$X$1373,$I45,Pinjaman!$W$6:$W$1373,N$40,Pinjaman!$V$6:$V$1373,"<24") -> 0 | O45: =COUNTIFS(Pinjaman!$X$6:$X$1373,$I45,Pinjaman!$W$6:$W$1373,0,Pinjaman!$V$6:$V$1373,"<24") -> 0 | P45: =SUM(J45:O45) -> 2 | T45: Tenaga Pengajar | U45: =COUNTIFS(SSKA!$Q$7:$Q$466,Rekap!$T45,SSKA!$P$7:$P$466,"<=60")-COUNTIFS(SSKA!$Q$7:$Q$466,Rekap!$T45,SSKA!$P$7:$P$466,"<24") -> 0 | V45: =COUNTIFS(SJTA!$S$6:$S$331,T45,SJTA!$R$6:$R$331,"<=60")-COUNTIFS(SJTA!$S$6:$S$331,T45,SJTA!$R$6:$R$331,"<24") -> 35 | W45: =COUNTIFS(SPJ!$P$5:$P$136,T31,SPJ!O$5:O$136,"<=60")-COUNTIFS(SPJ!$P$5:$P$136,T31,SPJ!O$5:O$136,"<24") -> 14 | X45: =COUNTIFS(SMP!$P$6:$P$15,T45,SMP!$O$6:$O$15,"<=60")-COUNTIFS(SMP!$P$6:$P$15,T45,SMP!$O$6:$O$15,"<24") -> 1
C46: Wiraswasta | D46: =COUNTIFS('Data Angt'!$H$5:$H$5710,C46,'Data Angt'!$F$5:$F$5710,"<24")-COUNTIFS('Data Angt'!$H$5:$H$5710,C46,'Data Angt'!$F$5:$F$5710,"<17") -> 16 | E46: =D46/$D$27 -> 0.0029850746 | I46: Lain-Lain | J46: =COUNTIFS(Pinjaman!$X$6:$X$1373,$I46,Pinjaman!$W$6:$W$1373,J$40,Pinjaman!$V$6:$V$1373,"<24") -> 0 | K46: =COUNTIFS(Pinjaman!$X$6:$X$1373,$I46,Pinjaman!$W$6:$W$1373,K$40,Pinjaman!$V$6:$V$1373,"<24") -> 0 | L46: =COUNTIFS(Pinjaman!$X$6:$X$1373,$I46,Pinjaman!$W$6:$W$1373,L$40,Pinjaman!$V$6:$V$1373,"<24") -> 0 | M46: =COUNTIFS(Pinjaman!$X$6:$X$1373,$I46,Pinjaman!$W$6:$W$1373,M$40,Pinjaman!$V$6:$V$1373,"<24") -> 0 | N46: =COUNTIFS(Pinjaman!$X$6:$X$1373,$I46,Pinjaman!$W$6:$W$1373,N$40,Pinjaman!$V$6:$V$1373,"<24") -> 0 | O46: =COUNTIFS(Pinjaman!$X$6:$X$1373,$I46,Pinjaman!$W$6:$W$1373,0,Pinjaman!$V$6:$V$1373,"<24") -> 0 | P46: =SUM(J46:O46) -> 0 | T46: Lain-Lain | U46: =COUNTIFS(SSKA!$Q$7:$Q$466,Rekap!$T46,SSKA!$P$7:$P$466,"<=60")-COUNTIFS(SSKA!$Q$7:$Q$466,Rekap!$T46,SSKA!$P$7:$P$466,"<24") -> 0 | V46: =COUNTIFS(SJTA!$S$6:$S$331,T46,SJTA!$R$6:$R$331,"<=60")-COUNTIFS(SJTA!$S$6:$S$331,T46,SJTA!$R$6:$R$331,"<24") -> 14 | W46: =COUNTIFS(SPJ!$P$5:$P$136,T32,SPJ!O$5:O$136,"<=60")-COUNTIFS(SPJ!$P$5:$P$136,T32,SPJ!O$5:O$136,"<24") -> 4 | X46: =COUNTIFS(SMP!$P$6:$P$15,T46,SMP!$O$6:$O$15,"<=60")-COUNTIFS(SMP!$P$6:$P$15,T46,SMP!$O$6:$O$15,"<24") -> 0
C47: Pelajar/Mahasiswa | D47: =COUNTIFS('Data Angt'!$H$5:$H$5710,C47,'Data Angt'!$F$5:$F$5710,"<24")-COUNTIFS('Data Angt'!$H$5:$H$5710,C47,'Data Angt'!$F$5:$F$5710,"<17") -> 167 | E47: =D47/$D$27 -> 0.031156716 | H47: 24 - 60 | I47: Aparatur Negara | J47: =COUNTIFS(Pinjaman!$X$6:$X$1373,$I47,Pinjaman!$W$6:$W$1373,J$40,Pinjaman!$V$6:$V$1373,"<24") -> 0 | K47: =COUNTIFS(Pinjaman!$X$6:$X$1373,$I47,Pinjaman!$W$6:$W$1373,K$40,Pinjaman!$V$6:$V$1373,"<24") -> 0 | L47: =COUNTIFS(Pinjaman!$X$6:$X$1373,$I47,Pinjaman!$W$6:$W$1373,L$40,Pinjaman!$V$6:$V$1373,"<24") -> 0 | M47: =COUNTIFS(Pinjaman!$X$6:$X$1373,$I47,Pinjaman!$W$6:$W$1373,M$40,Pinjaman!$V$6:$V$1373,"<24") -> 0 | N47: =COUNTIFS(Pinjaman!$X$6:$X$1373,$I47,Pinjaman!$W$6:$W$1373,N$40,Pinjaman!$V$6:$V$1373,"<24") -> 0 | O47: =COUNTIFS(Pinjaman!$X$6:$X$1373,$I47,Pinjaman!$W$6:$W$1373,0,Pinjaman!$V$6:$V$1373,"<24") -> 0 | P47: =SUM(J47:O47) -> 0 | T47: Aparatur Negara | U47: =COUNTIFS(SSKA!$Q$7:$Q$466,Rekap!$T47,SSKA!$P$7:$P$466,"<=60")-COUNTIFS(SSKA!$Q$7:$Q$466,Rekap!$T47,SSKA!$P$7:$P$466,"<24") -> 0 | V47: =COUNTIFS(SJTA!$S$6:$S$331,T47,SJTA!$R$6:$R$331,"<=60")-COUNTIFS(SJTA!$S$6:$S$331,T47,SJTA!$R$6:$R$331,"<24") -> 0 | W47: =COUNTIFS(SPJ!$P$5:$P$136,T33,SPJ!O$5:O$136,"<=60")-COUNTIFS(SPJ!$P$5:$P$136,T33,SPJ!O$5:O$136,"<24") -> 0 | X47: =COUNTIFS(SMP!$P$6:$P$15,T47,SMP!$O$6:$O$15,"<=60")-COUNTIFS(SMP!$P$6:$P$15,T47,SMP!$O$6:$O$15,"<24") -> 0
C48: Mengurus Rumah Tangga | D48: =COUNTIFS('Data Angt'!$H$5:$H$5710,C48,'Data Angt'!$F$5:$F$5710,"<24")-COUNTIFS('Data Angt'!$H$5:$H$5710,C48,'Data Angt'!$F$5:$F$5710,"<17") -> 6 | E48: =D48/$D$27 -> 0.001119403 | I48: Pensiunan | J48: =COUNTIFS(Pinjaman!$X$6:$X$1373,$I48,Pinjaman!$W$6:$W$1373,J$40,Pinjaman!$V$6:$V$1373,"<24") -> 0 | K48: =COUNTIFS(Pinjaman!$X$6:$X$1373,$I48,Pinjaman!$W$6:$W$1373,K$40,Pinjaman!$V$6:$V$1373,"<24") -> 0 | L48: =COUNTIFS(Pinjaman!$X$6:$X$1373,$I48,Pinjaman!$W$6:$W$1373,L$40,Pinjaman!$V$6:$V$1373,"<24") -> 0 | M48: =COUNTIFS(Pinjaman!$X$6:$X$1373,$I48,Pinjaman!$W$6:$W$1373,M$40,Pinjaman!$V$6:$V$1373,"<24") -> 0 | N48: =COUNTIFS(Pinjaman!$X$6:$X$1373,$I48,Pinjaman!$W$6:$W$1373,N$40,Pinjaman!$V$6:$V$1373,"<24") -> 0 | O48: =COUNTIFS(Pinjaman!$X$6:$X$1373,$I48,Pinjaman!$W$6:$W$1373,0,Pinjaman!$V$6:$V$1373,"<24") -> 0 | P48: =SUM(J48:O48) -> 0 | T48: Pensiunan | U48: =COUNTIFS(SSKA!$Q$7:$Q$466,Rekap!$T48,SSKA!$P$7:$P$466,"<=60")-COUNTIFS(SSKA!$Q$7:$Q$466,Rekap!$T48,SSKA!$P$7:$P$466,"<24") -> 0 | V48: =COUNTIFS(SJTA!$S$6:$S$331,T48,SJTA!$R$6:$R$331,"<=60")-COUNTIFS(SJTA!$S$6:$S$331,T48,SJTA!$R$6:$R$331,"<24") -> 3 | W48: =COUNTIFS(SPJ!$P$5:$P$136,T34,SPJ!O$5:O$136,"<=60")-COUNTIFS(SPJ!$P$5:$P$136,T34,SPJ!O$5:O$136,"<24") -> 2 | X48: =COUNTIFS(SMP!$P$6:$P$15,T48,SMP!$O$6:$O$15,"<=60")-COUNTIFS(SMP!$P$6:$P$15,T48,SMP!$O$6:$O$15,"<24") -> 0
C49: Tenaga Pengajar | D49: =COUNTIFS('Data Angt'!$H$5:$H$5710,C49,'Data Angt'!$F$5:$F$5710,"<24")-COUNTIFS('Data Angt'!$H$5:$H$5710,C49,'Data Angt'!$F$5:$F$5710,"<17") -> 2 | E49: =D49/$D$27 -> 0.00037313433 | I49: Pemuka Agama | J49: =COUNTIFS(Pinjaman!$X$6:$X$1373,$I49,Pinjaman!$W$6:$W$1373,J$40,Pinjaman!$V$6:$V$1373,"<24") -> 0 | K49: =COUNTIFS(Pinjaman!$X$6:$X$1373,$I49,Pinjaman!$W$6:$W$1373,K$40,Pinjaman!$V$6:$V$1373,"<24") -> 0 | L49: =COUNTIFS(Pinjaman!$X$6:$X$1373,$I49,Pinjaman!$W$6:$W$1373,L$40,Pinjaman!$V$6:$V$1373,"<24") -> 0 | M49: =COUNTIFS(Pinjaman!$X$6:$X$1373,$I49,Pinjaman!$W$6:$W$1373,M$40,Pinjaman!$V$6:$V$1373,"<24") -> 0 | N49: =COUNTIFS(Pinjaman!$X$6:$X$1373,$I49,Pinjaman!$W$6:$W$1373,N$40,Pinjaman!$V$6:$V$1373,"<24") -> 0 | O49: =COUNTIFS(Pinjaman!$X$6:$X$1373,$I49,Pinjaman!$W$6:$W$1373,0,Pinjaman!$V$6:$V$1373,"<24") -> 0 | P49: =SUM(J49:O49) -> 0 | T49: Pemuka Agama | U49: =COUNTIFS(SSKA!$Q$7:$Q$466,Rekap!$T49,SSKA!$P$7:$P$466,"<=60")-COUNTIFS(SSKA!$Q$7:$Q$466,Rekap!$T49,SSKA!$P$7:$P$466,"<24") -> 0 | V49: =COUNTIFS(SJTA!$S$6:$S$331,T49,SJTA!$R$6:$R$331,"<=60")-COUNTIFS(SJTA!$S$6:$S$331,T49,SJTA!$R$6:$R$331,"<24") -> 9 | W49: =COUNTIFS(SPJ!$P$5:$P$136,T35,SPJ!O$5:O$136,"<=60")-COUNTIFS(SPJ!$P$5:$P$136,T35,SPJ!O$5:O$136,"<24") -> 0 | X49: =COUNTIFS(SMP!$P$6:$P$15,T49,SMP!$O$6:$O$15,"<=60")-COUNTIFS(SMP!$P$6:$P$15,T49,SMP!$O$6:$O$15,"<24") -> 0
C50: Lain-Lain | D50: =COUNTIFS('Data Angt'!$H$5:$H$5710,C50,'Data Angt'!$F$5:$F$5710,"<24")-COUNTIFS('Data Angt'!$H$5:$H$5710,C50,'Data Angt'!$F$5:$F$5710,"<17") -> 3 | E50: =D50/$D$27 -> 0.00055970149 | I50: Petani/Pekebun/Nelayan/Peternak | J50: =COUNTIFS(Pinjaman!$X$6:$X$1373,$I50,Pinjaman!$W$6:$W$1373,J$40,Pinjaman!$V$6:$V$1373,"<24") -> 0 | K50: =COUNTIFS(Pinjaman!$X$6:$X$1373,$I50,Pinjaman!$W$6:$W$1373,K$40,Pinjaman!$V$6:$V$1373,"<24") -> 0 | L50: =COUNTIFS(Pinjaman!$X$6:$X$1373,$I50,Pinjaman!$W$6:$W$1373,L$40,Pinjaman!$V$6:$V$1373,"<24") -> 0 | M50: =COUNTIFS(Pinjaman!$X$6:$X$1373,$I50,Pinjaman!$W$6:$W$1373,M$40,Pinjaman!$V$6:$V$1373,"<24") -> 0 | N50: =COUNTIFS(Pinjaman!$X$6:$X$1373,$I50,Pinjaman!$W$6:$W$1373,N$40,Pinjaman!$V$6:$V$1373,"<24") -> 0 | O50: =COUNTIFS(Pinjaman!$X$6:$X$1373,$I50,Pinjaman!$W$6:$W$1373,0,Pinjaman!$V$6:$V$1373,"<24") -> 0 | P50: =SUM(J50:O50) -> 0 | T50: Petani/Pekebun/Nelayan/Peternak | U50: =COUNTIFS(SSKA!$Q$7:$Q$466,Rekap!$T50,SSKA!$P$7:$P$466,"<=60")-COUNTIFS(SSKA!$Q$7:$Q$466,Rekap!$T50,SSKA!$P$7:$P$466,"<24") -> 0 | V50: =COUNTIFS(SJTA!$S$6:$S$331,T50,SJTA!$R$6:$R$331,"<=60")-COUNTIFS(SJTA!$S$6:$S$331,T50,SJTA!$R$6:$R$331,"<24") -> 0 | W50: =COUNTIFS(SPJ!$P$5:$P$136,T36,SPJ!O$5:O$136,"<=60")-COUNTIFS(SPJ!$P$5:$P$136,T36,SPJ!O$5:O$136,"<24") -> 0 | X50: =COUNTIFS(SMP!$P$6:$P$15,T50,SMP!$O$6:$O$15,"<=60")-COUNTIFS(SMP!$P$6:$P$15,T50,SMP!$O$6:$O$15,"<24") -> 0
C51: Aparatur Negara | D51: =COUNTIFS('Data Angt'!$H$5:$H$5710,C51,'Data Angt'!$F$5:$F$5710,"<24")-COUNTIFS('Data Angt'!$H$5:$H$5710,C51,'Data Angt'!$F$5:$F$5710,"<17") -> 0 | E51: =D51/$D$27 -> 0 | I51: Tenaga Ahli | J51: =COUNTIFS(Pinjaman!$X$6:$X$1373,$I51,Pinjaman!$W$6:$W$1373,J$40,Pinjaman!$V$6:$V$1373,"<24") -> 0 | K51: =COUNTIFS(Pinjaman!$X$6:$X$1373,$I51,Pinjaman!$W$6:$W$1373,K$40,Pinjaman!$V$6:$V$1373,"<24") -> 0 | L51: =COUNTIFS(Pinjaman!$X$6:$X$1373,$I51,Pinjaman!$W$6:$W$1373,L$40,Pinjaman!$V$6:$V$1373,"<24") -> 0 | M51: =COUNTIFS(Pinjaman!$X$6:$X$1373,$I51,Pinjaman!$W$6:$W$1373,M$40,Pinjaman!$V$6:$V$1373,"<24") -> 0 | N51: =COUNTIFS(Pinjaman!$X$6:$X$1373,$I51,Pinjaman!$W$6:$W$1373,N$40,Pinjaman!$V$6:$V$1373,"<24") -> 0 | O51: =COUNTIFS(Pinjaman!$X$6:$X$1373,$I51,Pinjaman!$W$6:$W$1373,0,Pinjaman!$V$6:$V$1373,"<24") -> 0 | P51: =SUM(J51:O51) -> 0 | T51: Tenaga Ahli | U51: =COUNTIFS(SSKA!$Q$7:$Q$466,Rekap!$T51,SSKA!$P$7:$P$466,"<=60")-COUNTIFS(SSKA!$Q$7:$Q$466,Rekap!$T51,SSKA!$P$7:$P$466,"<24") -> 0 | V51: =COUNTIFS(SJTA!$S$6:$S$331,T51,SJTA!$R$6:$R$331,"<=60")-COUNTIFS(SJTA!$S$6:$S$331,T51,SJTA!$R$6:$R$331,"<24") -> 1 | W51: =COUNTIFS(SPJ!$P$5:$P$136,T37,SPJ!O$5:O$136,"<=60")-COUNTIFS(SPJ!$P$5:$P$136,T37,SPJ!O$5:O$136,"<24") -> 0 | X51: =COUNTIFS(SMP!$P$6:$P$15,T51,SMP!$O$6:$O$15,"<=60")-COUNTIFS(SMP!$P$6:$P$15,T51,SMP!$O$6:$O$15,"<24") -> 0
C52: Pensiunan | D52: =COUNTIFS('Data Angt'!$H$5:$H$5710,C52,'Data Angt'!$F$5:$F$5710,"<24")-COUNTIFS('Data Angt'!$H$5:$H$5710,C52,'Data Angt'!$F$5:$F$5710,"<17") -> 0 | E52: =D52/$D$27 -> 0 | I52: Belum/Tidak bekerja | J52: =COUNTIFS(Pinjaman!$X$6:$X$1373,$I52,Pinjaman!$W$6:$W$1373,J$40,Pinjaman!$V$6:$V$1373,"<24") -> 1 | K52: =COUNTIFS(Pinjaman!$X$6:$X$1373,$I52,Pinjaman!$W$6:$W$1373,K$40,Pinjaman!$V$6:$V$1373,"<24") -> 0 | L52: =COUNTIFS(Pinjaman!$X$6:$X$1373,$I52,Pinjaman!$W$6:$W$1373,L$40,Pinjaman!$V$6:$V$1373,"<24") -> 0 | M52: =COUNTIFS(Pinjaman!$X$6:$X$1373,$I52,Pinjaman!$W$6:$W$1373,M$40,Pinjaman!$V$6:$V$1373,"<24") -> 0 | N52: =COUNTIFS(Pinjaman!$X$6:$X$1373,$I52,Pinjaman!$W$6:$W$1373,N$40,Pinjaman!$V$6:$V$1373,"<24") -> 0 | O52: =COUNTIFS(Pinjaman!$X$6:$X$1373,$I52,Pinjaman!$W$6:$W$1373,0,Pinjaman!$V$6:$V$1373,"<24") -> 0 | P52: =SUM(J52:O52) -> 1 | T52: Belum/Tidak bekerja | U52: =COUNTIFS(SSKA!$Q$7:$Q$466,Rekap!$T52,SSKA!$P$7:$P$466,"<=60")-COUNTIFS(SSKA!$Q$7:$Q$466,Rekap!$T52,SSKA!$P$7:$P$466,"<24") -> 0 | V52: =COUNTIFS(SJTA!$S$6:$S$331,T52,SJTA!$R$6:$R$331,"<=60")-COUNTIFS(SJTA!$S$6:$S$331,T52,SJTA!$R$6:$R$331,"<24") -> 3 | W52: =COUNTIFS(SPJ!$P$5:$P$136,T38,SPJ!O$5:O$136,"<=60")-COUNTIFS(SPJ!$P$5:$P$136,T38,SPJ!O$5:O$136,"<24") -> 1 | X52: =COUNTIFS(SMP!$P$6:$P$15,T52,SMP!$O$6:$O$15,"<=60")-COUNTIFS(SMP!$P$6:$P$15,T52,SMP!$O$6:$O$15,"<24") -> 0
C53: Pemuka Agama | D53: =COUNTIFS('Data Angt'!$H$5:$H$5710,C53,'Data Angt'!$F$5:$F$5710,"<24")-COUNTIFS('Data Angt'!$H$5:$H$5710,C53,'Data Angt'!$F$5:$F$5710,"<17") -> 0 | E53: =D53/$D$27 -> 0 | I53: Data Kosong | J53: =COUNTIFS(Pinjaman!$X$6:$X$1373,0,Pinjaman!$W$6:$W$1373,J$40,Pinjaman!$V$6:$V$1373,"<24") -> 0 | K53: =COUNTIFS(Pinjaman!$X$6:$X$1373,0,Pinjaman!$W$6:$W$1373,K$40,Pinjaman!$V$6:$V$1373,"<24") -> 1 | L53: =COUNTIFS(Pinjaman!$X$6:$X$1373,0,Pinjaman!$W$6:$W$1373,L$40,Pinjaman!$V$6:$V$1373,"<24") -> 0 | M53: =COUNTIFS(Pinjaman!$X$6:$X$1373,0,Pinjaman!$W$6:$W$1373,M$40,Pinjaman!$V$6:$V$1373,"<24") -> 1 | N53: =COUNTIFS(Pinjaman!$X$6:$X$1373,0,Pinjaman!$W$6:$W$1373,N$40,Pinjaman!$V$6:$V$1373,"<24") -> 0 | O53: =COUNTIFS(Pinjaman!$X$6:$X$1373,0,Pinjaman!$W$6:$W$1373,0,Pinjaman!$V$6:$V$1373,"<24") -> 0 | P53: =SUM(J53:O53) -> 2 | T53: Data Kosong | U53: =COUNTIFS(SSKA!$Q$7:$Q$466,0,SSKA!$P$7:$P$466,"<=60")-COUNTIFS(SSKA!$Q$7:$Q$466,0,SSKA!$P$7:$P$466,"<24") -> 0 | V53: =COUNTIFS(SJTA!$S$6:$S$331,0,SJTA!$R$6:$R$331,"<=60")-COUNTIFS(SJTA!$S$6:$S$331,0,SJTA!$R$6:$R$331,"<24") -> 7 | W53: =COUNTIFS(SPJ!$P$5:$P$136,0,SPJ!O$5:O$136,"<=60")-COUNTIFS(SPJ!$P$5:$P$136,0,SPJ!O$5:O$136,"<24") -> 1 | X53: =COUNTIFS(SMP!$P$6:$P$15,0,SMP!$O$6:$O$15,"<=60")-COUNTIFS(SMP!$P$6:$P$15,0,SMP!$O$6:$O$15,"<24") -> 0
C54: Petani/Pekebun/Nelayan/Peternak | D54: =COUNTIFS('Data Angt'!$H$5:$H$5710,C54,'Data Angt'!$F$5:$F$5710,"<24")-COUNTIFS('Data Angt'!$H$5:$H$5710,C54,'Data Angt'!$F$5:$F$5710,"<17") -> 0 | E54: =D54/$D$27 -> 0 | I54: JUMLAH | J54: =SUM(J41:J53) -> 14 | K54: =SUM(K41:K53) -> 6 | L54: =SUM(L41:L53) -> 3 | M54: =SUM(M41:M53) -> 7 | N54: =SUM(N41:N53) -> 0 | O54: =SUM(O41:O53) -> 0 | P54: =SUM(P41:P53) -> 30 | T54: JUMLAH | U54: =SUM(U41:U53) -> 0 | V54: =SUM(V41:V53) -> 196 | W54: =SUM(W41:W53) -> 108 | X54: =SUM(X41:X53) -> 7
C55: Tenaga Ahli | D55: =COUNTIFS('Data Angt'!$H$5:$H$5710,C55,'Data Angt'!$F$5:$F$5710,"<24")-COUNTIFS('Data Angt'!$H$5:$H$5710,C55,'Data Angt'!$F$5:$F$5710,"<17") -> 0 | E55: =D55/$D$27 -> 0 | I55: Karyawan | J55: =COUNTIFS(Pinjaman!$X$6:$X$1373,$I55,Pinjaman!$W$6:$W$1373,J$40,Pinjaman!$V$6:$V$1373,"<=60")-COUNTIFS(Pinjaman!$X$6:$X$1373,$I55,Pinjaman!$W$6:$W$1373,J$40,Pinjaman!$V$6:$V$1373,"<24") -> 99 | K55: =COUNTIFS(Pinjaman!$X$6:$X$1373,$I55,Pinjaman!$W$6:$W$1373,K$40,Pinjaman!$V$6:$V$1373,"<=60")-COUNTIFS(Pinjaman!$X$6:$X$1373,$I55,Pinjaman!$W$6:$W$1373,K$40,Pinjaman!$V$6:$V$1373,"<24") -> 92 | L55: =COUNTIFS(Pinjaman!$X$6:$X$1373,$I55,Pinjaman!$W$6:$W$1373,L$40,Pinjaman!$V$6:$V$1373,"<=60")-COUNTIFS(Pinjaman!$X$6:$X$1373,$I55,Pinjaman!$W$6:$W$1373,L$40,Pinjaman!$V$6:$V$1373,"<24") -> 56 | M55: =COUNTIFS(Pinjaman!$X$6:$X$1373,$I55,Pinjaman!$W$6:$W$1373,M$40,Pinjaman!$V$6:$V$1373,"<=60")-COUNTIFS(Pinjaman!$X$6:$X$1373,$I55,Pinjaman!$W$6:$W$1373,M$40,Pinjaman!$V$6:$V$1373,"<24") -> 97 | N55: =COUNTIFS(Pinjaman!$X$6:$X$1373,$I55,Pinjaman!$W$6:$W$1373,N$40,Pinjaman!$V$6:$V$1373,"<=60")-COUNTIFS(Pinjaman!$X$6:$X$1373,$I55,Pinjaman!$W$6:$W$1373,N$40,Pinjaman!$V$6:$V$1373,"<24") -> 5 | O55: =COUNTIFS(Pinjaman!$X$6:$X$1373,$I55,Pinjaman!$W$6:$W$1373,0,Pinjaman!$V$6:$V$1373,"<=60")-COUNTIFS(Pinjaman!$X$6:$X$1373,$I55,Pinjaman!$W$6:$W$1373,O$40,Pinjaman!$V$6:$V$1373,"<24") -> 14 | P55: =SUM(J55:O55) -> 363 | S55: > 60 | T55: Karyawan | U55: =COUNTIFS(SSKA!$Q$7:$Q$466,T55,SSKA!$P$7:$P$466,">60") -> 0 | V55: =COUNTIFS(SJTA!$S$6:$S$331,T55,SJTA!$R$6:$R$331,">60") -> 4 | W55: =COUNTIFS(SPJ!$P$5:$P$136,T55,SPJ!O$5:O$136,">60") -> 0 | X55: =COUNTIFS(SMP!$P$6:$P$15,T55,SMP!$O$6:$O$15,">60") -> 0
C56: Belum/Tidak bekerja | D56: =COUNTIFS('Data Angt'!$H$5:$H$5710,C56,'Data Angt'!$F$5:$F$5710,"<24")-COUNTIFS('Data Angt'!$H$5:$H$5710,C56,'Data Angt'!$F$5:$F$5710,"<17") -> 16 | E56: =D56/$D$27 -> 0.0029850746 | I56: Wiraswasta | J56: =COUNTIFS(Pinjaman!$X$6:$X$1373,$I56,Pinjaman!$W$6:$W$1373,J$40,Pinjaman!$V$6:$V$1373,"<=60")-COUNTIFS(Pinjaman!$X$6:$X$1373,$I56,Pinjaman!$W$6:$W$1373,J$40,Pinjaman!$V$6:$V$1373,"<24") -> 47 | K56: =COUNTIFS(Pinjaman!$X$6:$X$1373,$I56,Pinjaman!$W$6:$W$1373,K$40,Pinjaman!$V$6:$V$1373,"<=60")-COUNTIFS(Pinjaman!$X$6:$X$1373,$I56,Pinjaman!$W$6:$W$1373,K$40,Pinjaman!$V$6:$V$1373,"<24") -> 36 | L56: =COUNTIFS(Pinjaman!$X$6:$X$1373,$I56,Pinjaman!$W$6:$W$1373,L$40,Pinjaman!$V$6:$V$1373,"<=60")-COUNTIFS(Pinjaman!$X$6:$X$1373,$I56,Pinjaman!$W$6:$W$1373,L$40,Pinjaman!$V$6:$V$1373,"<24") -> 43 | M56: =COUNTIFS(Pinjaman!$X$6:$X$1373,$I56,Pinjaman!$W$6:$W$1373,M$40,Pinjaman!$V$6:$V$1373,"<=60")-COUNTIFS(Pinjaman!$X$6:$X$1373,$I56,Pinjaman!$W$6:$W$1373,M$40,Pinjaman!$V$6:$V$1373,"<24") -> 214 | N56: =COUNTIFS(Pinjaman!$X$6:$X$1373,$I56,Pinjaman!$W$6:$W$1373,N$40,Pinjaman!$V$6:$V$1373,"<=60")-COUNTIFS(Pinjaman!$X$6:$X$1373,$I56,Pinjaman!$W$6:$W$1373,N$40,Pinjaman!$V$6:$V$1373,"<24") -> 3 | O56: =COUNTIFS(Pinjaman!$X$6:$X$1373,$I56,Pinjaman!$W$6:$W$1373,0,Pinjaman!$V$6:$V$1373,"<=60")-COUNTIFS(Pinjaman!$X$6:$X$1373,$I56,Pinjaman!$W$6:$W$1373,O$40,Pinjaman!$V$6:$V$1373,"<24") -> 20 | P56: =SUM(J56:O56) -> 363 | T56: Wiraswasta | U56: =COUNTIFS(SSKA!$Q$7:$Q$466,T56,SSKA!$P$7:$P$466,">60") -> 0 | V56: =COUNTIFS(SJTA!$S$6:$S$331,T56,SJTA!$R$6:$R$331,">60") -> 12 | W56: =COUNTIFS(SPJ!$P$5:$P$136,T56,SPJ!O$5:O$136,">60") -> 0 | X56: =COUNTIFS(SMP!$P$6:$P$15,T56,SMP!$O$6:$O$15,">60") -> 0
C57: Data Kosong | D57: =COUNTIFS('Data Angt'!$H$5:$H$5710,"",'Data Angt'!$F$5:$F$5710,"<24")-COUNTIFS('Data Angt'!$H$5:$H$5710,"",'Data Angt'!$F$5:$F$5710,"<17") -> 34 | E57: =D57/$D$27 -> 0.0063432836 | I57: Pelajar/Mahasiswa | J57: =COUNTIFS(Pinjaman!$X$6:$X$1373,$I57,Pinjaman!$W$6:$W$1373,J$40,Pinjaman!$V$6:$V$1373,"<=60")-COUNTIFS(Pinjaman!$X$6:$X$1373,$I57,Pinjaman!$W$6:$W$1373,J$40,Pinjaman!$V$6:$V$1373,"<24") -> 1 | K57: =COUNTIFS(Pinjaman!$X$6:$X$1373,$I57,Pinjaman!$W$6:$W$1373,K$40,Pinjaman!$V$6:$V$1373,"<=60")-COUNTIFS(Pinjaman!$X$6:$X$1373,$I57,Pinjaman!$W$6:$W$1373,K$40,Pinjaman!$V$6:$V$1373,"<24") -> 0 | L57: =COUNTIFS(Pinjaman!$X$6:$X$1373,$I57,Pinjaman!$W$6:$W$1373,L$40,Pinjaman!$V$6:$V$1373,"<=60")-COUNTIFS(Pinjaman!$X$6:$X$1373,$I57,Pinjaman!$W$6:$W$1373,L$40,Pinjaman!$V$6:$V$1373,"<24") -> 0 | M57: =COUNTIFS(Pinjaman!$X$6:$X$1373,$I57,Pinjaman!$W$6:$W$1373,M$40,Pinjaman!$V$6:$V$1373,"<=60")-COUNTIFS(Pinjaman!$X$6:$X$1373,$I57,Pinjaman!$W$6:$W$1373,M$40,Pinjaman!$V$6:$V$1373,"<24") -> 1 | N57: =COUNTIFS(Pinjaman!$X$6:$X$1373,$I57,Pinjaman!$W$6:$W$1373,N$40,Pinjaman!$V$6:$V$1373,"<=60")-COUNTIFS(Pinjaman!$X$6:$X$1373,$I57,Pinjaman!$W$6:$W$1373,N$40,Pinjaman!$V$6:$V$1373,"<24") -> 0 | O57: =COUNTIFS(Pinjaman!$X$6:$X$1373,$I57,Pinjaman!$W$6:$W$1373,0,Pinjaman!$V$6:$V$1373,"<=60")-COUNTIFS(Pinjaman!$X$6:$X$1373,$I57,Pinjaman!$W$6:$W$1373,O$40,Pinjaman!$V$6:$V$1373,"<24") -> 0 | P57: =SUM(J57:O57) -> 2 | T57: Pelajar/Mahasiswa | U57: =COUNTIFS(SSKA!$Q$7:$Q$466,T57,SSKA!$P$7:$P$466,">60") -> 0 | V57: =COUNTIFS(SJTA!$S$6:$S$331,T57,SJTA!$R$6:$R$331,">60") -> 0 | W57: =COUNTIFS(SPJ!$P$5:$P$136,T57,SPJ!O$5:O$136,">60") -> 0 | X57: =COUNTIFS(SMP!$P$6:$P$15,T57,SMP!$O$6:$O$15,">60") -> 0
C58: JUMLAH | D58: =SUM(D45:D57) -> 320 | E58: =D58/$D$27 -> 0.059701493 | I58: Mengurus Rumah Tangga | J58: =COUNTIFS(Pinjaman!$X$6:$X$1373,$I58,Pinjaman!$W$6:$W$1373,J$40,Pinjaman!$V$6:$V$1373,"<=60")-COUNTIFS(Pinjaman!$X$6:$X$1373,$I58,Pinjaman!$W$6:$W$1373,J$40,Pinjaman!$V$6:$V$1373,"<24") -> 42 | K58: =COUNTIFS(Pinjaman!$X$6:$X$1373,$I58,Pinjaman!$W$6:$W$1373,K$40,Pinjaman!$V$6:$V$1373,"<=60")-COUNTIFS(Pinjaman!$X$6:$X$1373,$I58,Pinjaman!$W$6:$W$1373,K$40,Pinjaman!$V$6:$V$1373,"<24") -> 18 | L58: =COUNTIFS(Pinjaman!$X$6:$X$1373,$I58,Pinjaman!$W$6:$W$1373,L$40,Pinjaman!$V$6:$V$1373,"<=60")-COUNTIFS(Pinjaman!$X$6:$X$1373,$I58,Pinjaman!$W$6:$W$1373,L$40,Pinjaman!$V$6:$V$1373,"<24") -> 24 | M58: =COUNTIFS(Pinjaman!$X$6:$X$1373,$I58,Pinjaman!$W$6:$W$1373,M$40,Pinjaman!$V$6:$V$1373,"<=60")-COUNTIFS(Pinjaman!$X$6:$X$1373,$I58,Pinjaman!$W$6:$W$1373,M$40,Pinjaman!$V$6:$V$1373,"<24") -> 63 | N58: =COUNTIFS(Pinjaman!$X$6:$X$1373,$I58,Pinjaman!$W$6:$W$1373,N$40,Pinjaman!$V$6:$V$1373,"<=60")-COUNTIFS(Pinjaman!$X$6:$X$1373,$I58,Pinjaman!$W$6:$W$1373,N$40,Pinjaman!$V$6:$V$1373,"<24") -> 3 | O58: =COUNTIFS(Pinjaman!$X$6:$X$1373,$I58,Pinjaman!$W$6:$W$1373,0,Pinjaman!$V$6:$V$1373,"<=60")-COUNTIFS(Pinjaman!$X$6:$X$1373,$I58,Pinjaman!$W$6:$W$1373,O$40,Pinjaman!$V$6:$V$1373,"<24") -> 13 | P58: =SUM(J58:O58) -> 163 | T58: Mengurus Rumah Tangga | U58: =COUNTIFS(SSKA!$Q$7:$Q$466,T58,SSKA!$P$7:$P$466,">60") -> 0 | V58: =COUNTIFS(SJTA!$S$6:$S$331,T58,SJTA!$R$6:$R$331,">60") -> 14 | W58: =COUNTIFS(SPJ!$P$5:$P$136,T58,SPJ!O$5:O$136,">60") -> 0 | X58: =COUNTIFS(SMP!$P$6:$P$15,T58,SMP!$O$6:$O$15,">60") -> 0
B59: 24 - 60 | C59: Karyawan | D59: =COUNTIFS('Data Angt'!$H$5:$H$5710,C59,'Data Angt'!$F$5:$F$5710,"<=60")-COUNTIFS('Data Angt'!$H$5:$H$5710,C59,'Data Angt'!$F$5:$F$5710,"<24") -> 1426 | E59: =D59/$D$27 -> 0.26604478 | I59: Tenaga Pengajar | J59: =COUNTIFS(Pinjaman!$X$6:$X$1373,$I59,Pinjaman!$W$6:$W$1373,J$40,Pinjaman!$V$6:$V$1373,"<=60")-COUNTIFS(Pinjaman!$X$6:$X$1373,$I59,Pinjaman!$W$6:$W$1373,J$40,Pinjaman!$V$6:$V$1373,"<24") -> 31 | K59: =COUNTIFS(Pinjaman!$X$6:$X$1373,$I59,Pinjaman!$W$6:$W$1373,K$40,Pinjaman!$V$6:$V$1373,"<=60")-COUNTIFS(Pinjaman!$X$6:$X$1373,$I59,Pinjaman!$W$6:$W$1373,K$40,Pinjaman!$V$6:$V$1373,"<24") -> 19 | L59: =COUNTIFS(Pinjaman!$X$6:$X$1373,$I59,Pinjaman!$W$6:$W$1373,L$40,Pinjaman!$V$6:$V$1373,"<=60")-COUNTIFS(Pinjaman!$X$6:$X$1373,$I59,Pinjaman!$W$6:$W$1373,L$40,Pinjaman!$V$6:$V$1373,"<24") -> 33 | M59: =COUNTIFS(Pinjaman!$X$6:$X$1373,$I59,Pinjaman!$W$6:$W$1373,M$40,Pinjaman!$V$6:$V$1373,"<=60")-COUNTIFS(Pinjaman!$X$6:$X$1373,$I59,Pinjaman!$W$6:$W$1373,M$40,Pinjaman!$V$6:$V$1373,"<24") -> 32 | N59: =COUNTIFS(Pinjaman!$X$6:$X$1373,$I59,Pinjaman!$W$6:$W$1373,N$40,Pinjaman!$V$6:$V$1373,"<=60")-COUNTIFS(Pinjaman!$X$6:$X$1373,$I59,Pinjaman!$W$6:$W$1373,N$40,Pinjaman!$V$6:$V$1373,"<24") -> 0 | O59: =COUNTIFS(Pinjaman!$X$6:$X$1373,$I59,Pinjaman!$W$6:$W$1373,0,Pinjaman!$V$6:$V$1373,"<=60")-COUNTIFS(Pinjaman!$X$6:$X$1373,$I59,Pinjaman!$W$6:$W$1373,O$40,Pinjaman!$V$6:$V$1373,"<24") -> 3 | P59: =SUM(J59:O59) -> 118 | T59: Tenaga Pengajar | U59: =COUNTIFS(SSKA!$Q$7:$Q$466,T59,SSKA!$P$7:$P$466,">60") -> 0 | V59: =COUNTIFS(SJTA!$S$6:$S$331,T59,SJTA!$R$6:$R$331,">60") -> 2 | W59: =COUNTIFS(SPJ!$P$5:$P$136,T59,SPJ!O$5:O$136,">60") -> 0 | X59: =COUNTIFS(SMP!$P$6:$P$15,T59,SMP!$O$6:$O$15,">60") -> 0
C60: Wiraswasta | D60: =COUNTIFS('Data Angt'!$H$5:$H$5710,C60,'Data Angt'!$F$5:$F$5710,"<=60")-COUNTIFS('Data Angt'!$H$5:$H$5710,C60,'Data Angt'!$F$5:$F$5710,"<24") -> 1113 | E60: =D60/$D$27 -> 0.20764925 | I60: Lain-Lain | J60: =COUNTIFS(Pinjaman!$X$6:$X$1373,$I60,Pinjaman!$W$6:$W$1373,J$40,Pinjaman!$V$6:$V$1373,"<=60")-COUNTIFS(Pinjaman!$X$6:$X$1373,$I60,Pinjaman!$W$6:$W$1373,J$40,Pinjaman!$V$6:$V$1373,"<24") -> 19 | K60: =COUNTIFS(Pinjaman!$X$6:$X$1373,$I60,Pinjaman!$W$6:$W$1373,K$40,Pinjaman!$V$6:$V$1373,"<=60")-COUNTIFS(Pinjaman!$X$6:$X$1373,$I60,Pinjaman!$W$6:$W$1373,K$40,Pinjaman!$V$6:$V$1373,"<24") -> 18 | L60: =COUNTIFS(Pinjaman!$X$6:$X$1373,$I60,Pinjaman!$W$6:$W$1373,L$40,Pinjaman!$V$6:$V$1373,"<=60")-COUNTIFS(Pinjaman!$X$6:$X$1373,$I60,Pinjaman!$W$6:$W$1373,L$40,Pinjaman!$V$6:$V$1373,"<24") -> 15 | M60: =COUNTIFS(Pinjaman!$X$6:$X$1373,$I60,Pinjaman!$W$6:$W$1373,M$40,Pinjaman!$V$6:$V$1373,"<=60")-COUNTIFS(Pinjaman!$X$6:$X$1373,$I60,Pinjaman!$W$6:$W$1373,M$40,Pinjaman!$V$6:$V$1373,"<24") -> 23 | N60: =COUNTIFS(Pinjaman!$X$6:$X$1373,$I60,Pinjaman!$W$6:$W$1373,N$40,Pinjaman!$V$6:$V$1373,"<=60")-COUNTIFS(Pinjaman!$X$6:$X$1373,$I60,Pinjaman!$W$6:$W$1373,N$40,Pinjaman!$V$6:$V$1373,"<24") -> 2 | O60: =COUNTIFS(Pinjaman!$X$6:$X$1373,$I60,Pinjaman!$W$6:$W$1373,0,Pinjaman!$V$6:$V$1373,"<=60")-COUNTIFS(Pinjaman!$X$6:$X$1373,$I60,Pinjaman!$W$6:$W$1373,O$40,Pinjaman!$V$6:$V$1373,"<24") -> 3 | P60: =SUM(J60:O60) -> 80 | T60: Lain-Lain | U60: =COUNTIFS(SSKA!$Q$7:$Q$466,T60,SSKA!$P$7:$P$466,">60") -> 0 | V60: =COUNTIFS(SJTA!$S$6:$S$331,T60,SJTA!$R$6:$R$331,">60") -> 3 | W60: =COUNTIFS(SPJ!$P$5:$P$136,T60,SPJ!O$5:O$136,">60") -> 0 | X60: =COUNTIFS(SMP!$P$6:$P$15,T60,SMP!$O$6:$O$15,">60") -> 0
C61: Pelajar/Mahasiswa | D61: =COUNTIFS('Data Angt'!$H$5:$H$5710,C61,'Data Angt'!$F$5:$F$5710,"<=60")-COUNTIFS('Data Angt'!$H$5:$H$5710,C61,'Data Angt'!$F$5:$F$5710,"<24") -> 53 | E61: =D61/$D$27 -> 0.0098880597 | H61: > 60 | I61: Aparatur Negara | J61: =COUNTIFS(Pinjaman!$X$6:$X$1373,$I61,Pinjaman!$W$6:$W$1373,J$40,Pinjaman!$V$6:$V$1373,"<=60")-COUNTIFS(Pinjaman!$X$6:$X$1373,$I61,Pinjaman!$W$6:$W$1373,J$40,Pinjaman!$V$6:$V$1373,"<24") -> 0 | K61: =COUNTIFS(Pinjaman!$X$6:$X$1373,$I61,Pinjaman!$W$6:$W$1373,K$40,Pinjaman!$V$6:$V$1373,"<=60")-COUNTIFS(Pinjaman!$X$6:$X$1373,$I61,Pinjaman!$W$6:$W$1373,K$40,Pinjaman!$V$6:$V$1373,"<24") -> 0 | L61: =COUNTIFS(Pinjaman!$X$6:$X$1373,$I61,Pinjaman!$W$6:$W$1373,L$40,Pinjaman!$V$6:$V$1373,"<=60")-COUNTIFS(Pinjaman!$X$6:$X$1373,$I61,Pinjaman!$W$6:$W$1373,L$40,Pinjaman!$V$6:$V$1373,"<24") -> 0 | M61: =COUNTIFS(Pinjaman!$X$6:$X$1373,$I61,Pinjaman!$W$6:$W$1373,M$40,Pinjaman!$V$6:$V$1373,"<=60")-COUNTIFS(Pinjaman!$X$6:$X$1373,$I61,Pinjaman!$W$6:$W$1373,M$40,Pinjaman!$V$6:$V$1373,"<24") -> 0 | N61: =COUNTIFS(Pinjaman!$X$6:$X$1373,$I61,Pinjaman!$W$6:$W$1373,N$40,Pinjaman!$V$6:$V$1373,"<=60")-COUNTIFS(Pinjaman!$X$6:$X$1373,$I61,Pinjaman!$W$6:$W$1373,N$40,Pinjaman!$V$6:$V$1373,"<24") -> 0 | O61: =COUNTIFS(Pinjaman!$X$6:$X$1373,$I61,Pinjaman!$W$6:$W$1373,0,Pinjaman!$V$6:$V$1373,"<=60")-COUNTIFS(Pinjaman!$X$6:$X$1373,$I61,Pinjaman!$W$6:$W$1373,O$40,Pinjaman!$V$6:$V$1373,"<24") -> 0 | P61: =SUM(J61:O61) -> 0 | T61: Aparatur Negara | U61: =COUNTIFS(SSKA!$Q$7:$Q$466,T61,SSKA!$P$7:$P$466,">60") -> 0 | V61: =COUNTIFS(SJTA!$S$6:$S$331,T61,SJTA!$R$6:$R$331,">60") -> 0 | W61: =COUNTIFS(SPJ!$P$5:$P$136,T61,SPJ!O$5:O$136,">60") -> 0 | X61: =COUNTIFS(SMP!$P$6:$P$15,T61,SMP!$O$6:$O$15,">60") -> 0
C62: Mengurus Rumah Tangga | D62: =COUNTIFS('Data Angt'!$H$5:$H$5710,C62,'Data Angt'!$F$5:$F$5710,"<=60")-COUNTIFS('Data Angt'!$H$5:$H$5710,C62,'Data Angt'!$F$5:$F$5710,"<24") -> 650 | E62: =D62/$D$27 -> 0.12126866 | I62: Pensiunan | J62: =COUNTIFS(Pinjaman!$X$6:$X$1373,$I62,Pinjaman!$W$6:$W$1373,J$40,Pinjaman!$V$6:$V$1373,"<=60")-COUNTIFS(Pinjaman!$X$6:$X$1373,$I62,Pinjaman!$W$6:$W$1373,J$40,Pinjaman!$V$6:$V$1373,"<24") -> 1 | K62: =COUNTIFS(Pinjaman!$X$6:$X$1373,$I62,Pinjaman!$W$6:$W$1373,K$40,Pinjaman!$V$6:$V$1373,"<=60")-COUNTIFS(Pinjaman!$X$6:$X$1373,$I62,Pinjaman!$W$6:$W$1373,K$40,Pinjaman!$V$6:$V$1373,"<24") -> 2 | L62: =COUNTIFS(Pinjaman!$X$6:$X$1373,$I62,Pinjaman!$W$6:$W$1373,L$40,Pinjaman!$V$6:$V$1373,"<=60")-COUNTIFS(Pinjaman!$X$6:$X$1373,$I62,Pinjaman!$W$6:$W$1373,L$40,Pinjaman!$V$6:$V$1373,"<24") -> 1 | M62: =COUNTIFS(Pinjaman!$X$6:$X$1373,$I62,Pinjaman!$W$6:$W$1373,M$40,Pinjaman!$V$6:$V$1373,"<=60")-COUNTIFS(Pinjaman!$X$6:$X$1373,$I62,Pinjaman!$W$6:$W$1373,M$40,Pinjaman!$V$6:$V$1373,"<24") -> 3 | N62: =COUNTIFS(Pinjaman!$X$6:$X$1373,$I62,Pinjaman!$W$6:$W$1373,N$40,Pinjaman!$V$6:$V$1373,"<=60")-COUNTIFS(Pinjaman!$X$6:$X$1373,$I62,Pinjaman!$W$6:$W$1373,N$40,Pinjaman!$V$6:$V$1373,"<24") -> 0 | O62: =COUNTIFS(Pinjaman!$X$6:$X$1373,$I62,Pinjaman!$W$6:$W$1373,0,Pinjaman!$V$6:$V$1373,"<=60")-COUNTIFS(Pinjaman!$X$6:$X$1373,$I62,Pinjaman!$W$6:$W$1373,O$40,Pinjaman!$V$6:$V$1373,"<24") -> 0 | P62: =SUM(J62:O62) -> 7 | T62: Pensiunan | U62: =COUNTIFS(SSKA!$Q$7:$Q$466,T62,SSKA!$P$7:$P$466,">60") -> 0 | V62: =COUNTIFS(SJTA!$S$6:$S$331,T62,SJTA!$R$6:$R$331,">60") -> 29 | W62: =COUNTIFS(SPJ!$P$5:$P$136,T62,SPJ!O$5:O$136,">60") -> 2 | X62: =COUNTIFS(SMP!$P$6:$P$15,T62,SMP!$O$6:$O$15,">60") -> 1
C63: Tenaga Pengajar | D63: =COUNTIFS('Data Angt'!$H$5:$H$5710,C63,'Data Angt'!$F$5:$F$5710,"<=60")-COUNTIFS('Data Angt'!$H$5:$H$5710,C63,'Data Angt'!$F$5:$F$5710,"<24") -> 414 | E63: =D63/$D$27 -> 0.077238806 | I63: Pemuka Agama | J63: =COUNTIFS(Pinjaman!$X$6:$X$1373,$I63,Pinjaman!$W$6:$W$1373,J$40,Pinjaman!$V$6:$V$1373,"<=60")-COUNTIFS(Pinjaman!$X$6:$X$1373,$I63,Pinjaman!$W$6:$W$1373,J$40,Pinjaman!$V$6:$V$1373,"<24") -> 0 | K63: =COUNTIFS(Pinjaman!$X$6:$X$1373,$I63,Pinjaman!$W$6:$W$1373,K$40,Pinjaman!$V$6:$V$1373,"<=60")-COUNTIFS(Pinjaman!$X$6:$X$1373,$I63,Pinjaman!$W$6:$W$1373,K$40,Pinjaman!$V$6:$V$1373,"<24") -> 0 | L63: =COUNTIFS(Pinjaman!$X$6:$X$1373,$I63,Pinjaman!$W$6:$W$1373,L$40,Pinjaman!$V$6:$V$1373,"<=60")-COUNTIFS(Pinjaman!$X$6:$X$1373,$I63,Pinjaman!$W$6:$W$1373,L$40,Pinjaman!$V$6:$V$1373,"<24") -> 0 | M63: =COUNTIFS(Pinjaman!$X$6:$X$1373,$I63,Pinjaman!$W$6:$W$1373,M$40,Pinjaman!$V$6:$V$1373,"<=60")-COUNTIFS(Pinjaman!$X$6:$X$1373,$I63,Pinjaman!$W$6:$W$1373,M$40,Pinjaman!$V$6:$V$1373,"<24") -> 0 | N63: =COUNTIFS(Pinjaman!$X$6:$X$1373,$I63,Pinjaman!$W$6:$W$1373,N$40,Pinjaman!$V$6:$V$1373,"<=60")-COUNTIFS(Pinjaman!$X$6:$X$1373,$I63,Pinjaman!$W$6:$W$1373,N$40,Pinjaman!$V$6:$V$1373,"<24") -> 0 | O63: =COUNTIFS(Pinjaman!$X$6:$X$1373,$I63,Pinjaman!$W$6:$W$1373,0,Pinjaman!$V$6:$V$1373,"<=60")-COUNTIFS(Pinjaman!$X$6:$X$1373,$I63,Pinjaman!$W$6:$W$1373,O$40,Pinjaman!$V$6:$V$1373,"<24") -> 0 | P63: =SUM(J63:O63) -> 0 | T63: Pemuka Agama | U63: =COUNTIFS(SSKA!$Q$7:$Q$466,T63,SSKA!$P$7:$P$466,">60") -> 0 | V63: =COUNTIFS(SJTA!$S$6:$S$331,T63,SJTA!$R$6:$R$331,">60") -> 4 | W63: =COUNTIFS(SPJ!$P$5:$P$136,T63,SPJ!O$5:O$136,">60") -> 0 | X63: =COUNTIFS(SMP!$P$6:$P$15,T63,SMP!$O$6:$O$15,">60") -> 0
C64: Lain-Lain | D64: =COUNTIFS('Data Angt'!$H$5:$H$5710,C64,'Data Angt'!$F$5:$F$5710,"<=60")-COUNTIFS('Data Angt'!$H$5:$H$5710,C64,'Data Angt'!$F$5:$F$5710,"<24") -> 208 | E64: =D64/$D$27 -> 0.03880597 | I64: Petani/Pekebun/Nelayan/Peternak | J64: =COUNTIFS(Pinjaman!$X$6:$X$1373,$I64,Pinjaman!$W$6:$W$1373,J$40,Pinjaman!$V$6:$V$1373,"<=60")-COUNTIFS(Pinjaman!$X$6:$X$1373,$I64,Pinjaman!$W$6:$W$1373,J$40,Pinjaman!$V$6:$V$1373,"<24") -> 0 | K64: =COUNTIFS(Pinjaman!$X$6:$X$1373,$I64,Pinjaman!$W$6:$W$1373,K$40,Pinjaman!$V$6:$V$1373,"<=60")-COUNTIFS(Pinjaman!$X$6:$X$1373,$I64,Pinjaman!$W$6:$W$1373,K$40,Pinjaman!$V$6:$V$1373,"<24") -> 0 | L64: =COUNTIFS(Pinjaman!$X$6:$X$1373,$I64,Pinjaman!$W$6:$W$1373,L$40,Pinjaman!$V$6:$V$1373,"<=60")-COUNTIFS(Pinjaman!$X$6:$X$1373,$I64,Pinjaman!$W$6:$W$1373,L$40,Pinjaman!$V$6:$V$1373,"<24") -> 0 | M64: =COUNTIFS(Pinjaman!$X$6:$X$1373,$I64,Pinjaman!$W$6:$W$1373,M$40,Pinjaman!$V$6:$V$1373,"<=60")-COUNTIFS(Pinjaman!$X$6:$X$1373,$I64,Pinjaman!$W$6:$W$1373,M$40,Pinjaman!$V$6:$V$1373,"<24") -> 0 | N64: =COUNTIFS(Pinjaman!$X$6:$X$1373,$I64,Pinjaman!$W$6:$W$1373,N$40,Pinjaman!$V$6:$V$1373,"<=60")-COUNTIFS(Pinjaman!$X$6:$X$1373,$I64,Pinjaman!$W$6:$W$1373,N$40,Pinjaman!$V$6:$V$1373,"<24") -> 0 | O64: =COUNTIFS(Pinjaman!$X$6:$X$1373,$I64,Pinjaman!$W$6:$W$1373,0,Pinjaman!$V$6:$V$1373,"<=60")-COUNTIFS(Pinjaman!$X$6:$X$1373,$I64,Pinjaman!$W$6:$W$1373,O$40,Pinjaman!$V$6:$V$1373,"<24") -> 0 | P64: =SUM(J64:O64) -> 0 | T64: Petani/Pekebun/Nelayan/Peternak | U64: =COUNTIFS(SSKA!$Q$7:$Q$466,T64,SSKA!$P$7:$P$466,">60") -> 0 | V64: =COUNTIFS(SJTA!$S$6:$S$331,T64,SJTA!$R$6:$R$331,">60") -> 0 | W64: =COUNTIFS(SPJ!$P$5:$P$136,T64,SPJ!O$5:O$136,">60") -> 0 | X64: =COUNTIFS(SMP!$P$6:$P$15,T64,SMP!$O$6:$O$15,">60") -> 0
C65: Aparatur Negara | D65: =COUNTIFS('Data Angt'!$H$5:$H$5710,C65,'Data Angt'!$F$5:$F$5710,"<=60")-COUNTIFS('Data Angt'!$H$5:$H$5710,C65,'Data Angt'!$F$5:$F$5710,"<24") -> 0 | E65: =D65/$D$27 -> 0 | I65: Tenaga Ahli | J65: =COUNTIFS(Pinjaman!$X$6:$X$1373,$I65,Pinjaman!$W$6:$W$1373,J$40,Pinjaman!$V$6:$V$1373,"<=60")-COUNTIFS(Pinjaman!$X$6:$X$1373,$I65,Pinjaman!$W$6:$W$1373,J$40,Pinjaman!$V$6:$V$1373,"<24") -> 1 | K65: =COUNTIFS(Pinjaman!$X$6:$X$1373,$I65,Pinjaman!$W$6:$W$1373,K$40,Pinjaman!$V$6:$V$1373,"<=60")-COUNTIFS(Pinjaman!$X$6:$X$1373,$I65,Pinjaman!$W$6:$W$1373,K$40,Pinjaman!$V$6:$V$1373,"<24") -> 1 | L65: =COUNTIFS(Pinjaman!$X$6:$X$1373,$I65,Pinjaman!$W$6:$W$1373,L$40,Pinjaman!$V$6:$V$1373,"<=60")-COUNTIFS(Pinjaman!$X$6:$X$1373,$I65,Pinjaman!$W$6:$W$1373,L$40,Pinjaman!$V$6:$V$1373,"<24") -> 0 | M65: =COUNTIFS(Pinjaman!$X$6:$X$1373,$I65,Pinjaman!$W$6:$W$1373,M$40,Pinjaman!$V$6:$V$1373,"<=60")-COUNTIFS(Pinjaman!$X$6:$X$1373,$I65,Pinjaman!$W$6:$W$1373,M$40,Pinjaman!$V$6:$V$1373,"<24") -> 2 | N65: =COUNTIFS(Pinjaman!$X$6:$X$1373,$I65,Pinjaman!$W$6:$W$1373,N$40,Pinjaman!$V$6:$V$1373,"<=60")-COUNTIFS(Pinjaman!$X$6:$X$1373,$I65,Pinjaman!$W$6:$W$1373,N$40,Pinjaman!$V$6:$V$1373,"<24") -> 0 | O65: =COUNTIFS(Pinjaman!$X$6:$X$1373,$I65,Pinjaman!$W$6:$W$1373,0,Pinjaman!$V$6:$V$1373,"<=60")-COUNTIFS(Pinjaman!$X$6:$X$1373,$I65,Pinjaman!$W$6:$W$1373,O$40,Pinjaman!$V$6:$V$1373,"<24") -> 0 | P65: =SUM(J65:O65) -> 4 | T65: Tenaga Ahli | U65: =COUNTIFS(SSKA!$Q$7:$Q$466,T65,SSKA!$P$7:$P$466,">60") -> 0 | V65: =COUNTIFS(SJTA!$S$6:$S$331,T65,SJTA!$R$6:$R$331,">60") -> 0 | W65: =COUNTIFS(SPJ!$P$5:$P$136,T65,SPJ!O$5:O$136,">60") -> 0 | X65: =COUNTIFS(SMP!$P$6:$P$15,T65,SMP!$O$6:$O$15,">60") -> 0
C66: Pensiunan | D66: =COUNTIFS('Data Angt'!$H$5:$H$5710,C66,'Data Angt'!$F$5:$F$5710,"<=60")-COUNTIFS('Data Angt'!$H$5:$H$5710,C66,'Data Angt'!$F$5:$F$5710,"<24") -> 20 | E66: =D66/$D$27 -> 0.0037313433 | I66: Belum/Tidak bekerja | J66: =COUNTIFS(Pinjaman!$X$6:$X$1373,$I66,Pinjaman!$W$6:$W$1373,J$40,Pinjaman!$V$6:$V$1373,"<=60")-COUNTIFS(Pinjaman!$X$6:$X$1373,$I66,Pinjaman!$W$6:$W$1373,J$40,Pinjaman!$V$6:$V$1373,"<24") -> 0 | K66: =COUNTIFS(Pinjaman!$X$6:$X$1373,$I66,Pinjaman!$W$6:$W$1373,K$40,Pinjaman!$V$6:$V$1373,"<=60")-COUNTIFS(Pinjaman!$X$6:$X$1373,$I66,Pinjaman!$W$6:$W$1373,K$40,Pinjaman!$V$6:$V$1373,"<24") -> 0 | L66: =COUNTIFS(Pinjaman!$X$6:$X$1373,$I66,Pinjaman!$W$6:$W$1373,L$40,Pinjaman!$V$6:$V$1373,"<=60")-COUNTIFS(Pinjaman!$X$6:$X$1373,$I66,Pinjaman!$W$6:$W$1373,L$40,Pinjaman!$V$6:$V$1373,"<24") -> 1 | M66: =COUNTIFS(Pinjaman!$X$6:$X$1373,$I66,Pinjaman!$W$6:$W$1373,M$40,Pinjaman!$V$6:$V$1373,"<=60")-COUNTIFS(Pinjaman!$X$6:$X$1373,$I66,Pinjaman!$W$6:$W$1373,M$40,Pinjaman!$V$6:$V$1373,"<24") -> 3 | N66: =COUNTIFS(Pinjaman!$X$6:$X$1373,$I66,Pinjaman!$W$6:$W$1373,N$40,Pinjaman!$V$6:$V$1373,"<=60")-COUNTIFS(Pinjaman!$X$6:$X$1373,$I66,Pinjaman!$W$6:$W$1373,N$40,Pinjaman!$V$6:$V$1373,"<24") -> 0 | O66: =COUNTIFS(Pinjaman!$X$6:$X$1373,$I66,Pinjaman!$W$6:$W$1373,0,Pinjaman!$V$6:$V$1373,"<=60")-COUNTIFS(Pinjaman!$X$6:$X$1373,$I66,Pinjaman!$W$6:$W$1373,O$40,Pinjaman!$V$6:$V$1373,"<24") -> 0 | P66: =SUM(J66:O66) -> 4 | T66: Belum/Tidak bekerja | U66: =COUNTIFS(SSKA!$Q$7:$Q$466,T66,SSKA!$P$7:$P$466,">60") -> 0 | V66: =COUNTIFS(SJTA!$S$6:$S$331,T66,SJTA!$R$6:$R$331,">60") -> 1 | W66: =COUNTIFS(SPJ!$P$5:$P$136,T66,SPJ!O$5:O$136,">60") -> 0 | X66: =COUNTIFS(SMP!$P$6:$P$15,T66,SMP!$O$6:$O$15,">60") -> 0
C67: Pemuka Agama | D67: =COUNTIFS('Data Angt'!$H$5:$H$5710,C67,'Data Angt'!$F$5:$F$5710,"<=60")-COUNTIFS('Data Angt'!$H$5:$H$5710,C67,'Data Angt'!$F$5:$F$5710,"<24") -> 40 | E67: =D67/$D$27 -> 0.0074626866 | I67: Data Kosong | J67: =COUNTIFS(Pinjaman!$X$6:$X$1373,0,Pinjaman!$W$6:$W$1373,J$40,Pinjaman!$V$6:$V$1373,"<=60")-COUNTIFS(Pinjaman!$X$6:$X$1373,0,Pinjaman!$W$6:$W$1373,J$40,Pinjaman!$V$6:$V$1373,"<24") -> 4 | K67: =COUNTIFS(Pinjaman!$X$6:$X$1373,0,Pinjaman!$W$6:$W$1373,K$40,Pinjaman!$V$6:$V$1373,"<=60")-COUNTIFS(Pinjaman!$X$6:$X$1373,0,Pinjaman!$W$6:$W$1373,K$40,Pinjaman!$V$6:$V$1373,"<24") -> 1 | L67: =COUNTIFS(Pinjaman!$X$6:$X$1373,0,Pinjaman!$W$6:$W$1373,L$40,Pinjaman!$V$6:$V$1373,"<=60")-COUNTIFS(Pinjaman!$X$6:$X$1373,0,Pinjaman!$W$6:$W$1373,L$40,Pinjaman!$V$6:$V$1373,"<24") -> 2 | M67: =COUNTIFS(Pinjaman!$X$6:$X$1373,0,Pinjaman!$W$6:$W$1373,M$40,Pinjaman!$V$6:$V$1373,"<=60")-COUNTIFS(Pinjaman!$X$6:$X$1373,0,Pinjaman!$W$6:$W$1373,M$40,Pinjaman!$V$6:$V$1373,"<24") -> 5 | N67: =COUNTIFS(Pinjaman!$X$6:$X$1373,0,Pinjaman!$W$6:$W$1373,N$40,Pinjaman!$V$6:$V$1373,"<=60")-COUNTIFS(Pinjaman!$X$6:$X$1373,0,Pinjaman!$W$6:$W$1373,N$40,Pinjaman!$V$6:$V$1373,"<24") -> 0 | O67: =COUNTIFS(Pinjaman!$X$6:$X$1373,0,Pinjaman!$W$6:$W$1373,0,Pinjaman!$V$6:$V$1373,"<=60")-COUNTIFS(Pinjaman!$X$6:$X$1373,0,Pinjaman!$W$6:$W$1373,0,Pinjaman!$V$6:$V$1373,"<24") -> 1 | P67: =SUM(J67:O67) -> 13 | T67: Data Kosong | U67: =COUNTIFS(SSKA!$Q$7:$Q$466,0,SSKA!$P$7:$P$466,">60") -> 0 | V67: =COUNTIFS(SJTA!$S$6:$S$331,0,SJTA!$R$6:$R$331,">60") -> 1 | W67: =COUNTIFS(SPJ!$P$5:$P$136,0,SPJ!O$5:O$136,">60") -> 0 | X67: =COUNTIFS(SMP!$P$6:$P$15,0,SMP!$O$6:$O$15,">60") -> 0
C68: Petani/Pekebun/Nelayan/Peternak | D68: =COUNTIFS('Data Angt'!$H$5:$H$5710,C68,'Data Angt'!$F$5:$F$5710,"<=60")-COUNTIFS('Data Angt'!$H$5:$H$5710,C68,'Data Angt'!$F$5:$F$5710,"<24") -> 0 | E68: =D68/$D$27 -> 0 | I68: JUMLAH | J68: =SUM(J55:J67) -> 245 | K68: =SUM(K55:K67) -> 187 | L68: =SUM(L55:L67) -> 175 | M68: =SUM(M55:M67) -> 443 | N68: =SUM(N55:N67) -> 13 | O68: =SUM(O55:O67) -> 54 | P68: =SUM(P55:P67) -> 1117 | T68: JUMLAH | U68: =SUM(U55:U67) -> 0 | V68: =SUM(V55:V67) -> 70 | W68: =SUM(W55:W67) -> 2 | X68: =SUM(X55:X67) -> 1
C69: Tenaga Ahli | D69: =COUNTIFS('Data Angt'!$H$5:$H$5710,C69,'Data Angt'!$F$5:$F$5710,"<=60")-COUNTIFS('Data Angt'!$H$5:$H$5710,C69,'Data Angt'!$F$5:$F$5710,"<24") -> 17 | E69: =D69/$D$27 -> 0.0031716418 | I69: Karyawan | J69: =COUNTIFS(Pinjaman!$X$6:$X$1373,$I69,Pinjaman!$W$6:$W$1373,J$40,Pinjaman!$V$6:$V$1373,">60") -> 2 | K69: =COUNTIFS(Pinjaman!$X$6:$X$1373,$I69,Pinjaman!$W$6:$W$1373,K$40,Pinjaman!$V$6:$V$1373,">60") -> 3 | L69: =COUNTIFS(Pinjaman!$X$6:$X$1373,$I69,Pinjaman!$W$6:$W$1373,L$40,Pinjaman!$V$6:$V$1373,">60") -> 2 | M69: =COUNTIFS(Pinjaman!$X$6:$X$1373,$I69,Pinjaman!$W$6:$W$1373,M$40,Pinjaman!$V$6:$V$1373,">60") -> 4 | N69: =COUNTIFS(Pinjaman!$X$6:$X$1373,$I69,Pinjaman!$W$6:$W$1373,N$40,Pinjaman!$V$6:$V$1373,">60") -> 0 | O69: =COUNTIFS(Pinjaman!$X$6:$X$1373,$I69,Pinjaman!$W$6:$W$1373,0,Pinjaman!$V$6:$V$1373,">60") -> 1 | P69: =SUM(J69:O69) -> 12
C70: Belum/Tidak bekerja | D70: =COUNTIFS('Data Angt'!$H$5:$H$5710,C70,'Data Angt'!$F$5:$F$5710,"<=60")-COUNTIFS('Data Angt'!$H$5:$H$5710,C70,'Data Angt'!$F$5:$F$5710,"<24") -> 57 | E70: =D70/$D$27 -> 0.010634328 | I70: Wiraswasta | J70: =COUNTIFS(Pinjaman!$X$6:$X$1373,$I70,Pinjaman!$W$6:$W$1373,J$40,Pinjaman!$V$6:$V$1373,">60") -> 9 | K70: =COUNTIFS(Pinjaman!$X$6:$X$1373,$I70,Pinjaman!$W$6:$W$1373,K$40,Pinjaman!$V$6:$V$1373,">60") -> 5 | L70: =COUNTIFS(Pinjaman!$X$6:$X$1373,$I70,Pinjaman!$W$6:$W$1373,L$40,Pinjaman!$V$6:$V$1373,">60") -> 2 | M70: =COUNTIFS(Pinjaman!$X$6:$X$1373,$I70,Pinjaman!$W$6:$W$1373,M$40,Pinjaman!$V$6:$V$1373,">60") -> 25 | N70: =COUNTIFS(Pinjaman!$X$6:$X$1373,$I70,Pinjaman!$W$6:$W$1373,N$40,Pinjaman!$V$6:$V$1373,">60") -> 1 | O70: =COUNTIFS(Pinjaman!$X$6:$X$1373,$I70,Pinjaman!$W$6:$W$1373,0,Pinjaman!$V$6:$V$1373,">60") -> 7 | P70: =SUM(J70:O70) -> 49
C71: Data Kosong | D71: =COUNTIFS('Data Angt'!$H$5:$H$5710,"",'Data Angt'!$F$5:$F$5710,"<=60")-COUNTIFS('Data Angt'!$H$5:$H$5710,"",'Data Angt'!$F$5:$F$5710,"<24") -> 186 | E71: =D71/$D$27 -> 0.034701493 | I71: Pelajar/Mahasiswa | J71: =COUNTIFS(Pinjaman!$X$6:$X$1373,$I71,Pinjaman!$W$6:$W$1373,J$40,Pinjaman!$V$6:$V$1373,">60") -> 0 | K71: =COUNTIFS(Pinjaman!$X$6:$X$1373,$I71,Pinjaman!$W$6:$W$1373,K$40,Pinjaman!$V$6:$V$1373,">60") -> 0 | L71: =COUNTIFS(Pinjaman!$X$6:$X$1373,$I71,Pinjaman!$W$6:$W$1373,L$40,Pinjaman!$V$6:$V$1373,">60") -> 0 | M71: =COUNTIFS(Pinjaman!$X$6:$X$1373,$I71,Pinjaman!$W$6:$W$1373,M$40,Pinjaman!$V$6:$V$1373,">60") -> 0 | N71: =COUNTIFS(Pinjaman!$X$6:$X$1373,$I71,Pinjaman!$W$6:$W$1373,N$40,Pinjaman!$V$6:$V$1373,">60") -> 0 | O71: =COUNTIFS(Pinjaman!$X$6:$X$1373,$I71,Pinjaman!$W$6:$W$1373,0,Pinjaman!$V$6:$V$1373,">60") -> 0 | P71: =SUM(J71:O71) -> 0
C72: JUMLAH | D72: =SUM(D59:D71) -> 4184 | E72: =D72/$D$27 -> 0.78059701 | I72: Mengurus Rumah Tangga | J72: =COUNTIFS(Pinjaman!$X$6:$X$1373,$I72,Pinjaman!$W$6:$W$1373,J$40,Pinjaman!$V$6:$V$1373,">60") -> 4 | K72: =COUNTIFS(Pinjaman!$X$6:$X$1373,$I72,Pinjaman!$W$6:$W$1373,K$40,Pinjaman!$V$6:$V$1373,">60") -> 7 | L72: =COUNTIFS(Pinjaman!$X$6:$X$1373,$I72,Pinjaman!$W$6:$W$1373,L$40,Pinjaman!$V$6:$V$1373,">60") -> 1 | M72: =COUNTIFS(Pinjaman!$X$6:$X$1373,$I72,Pinjaman!$W$6:$W$1373,M$40,Pinjaman!$V$6:$V$1373,">60") -> 8 | N72: =COUNTIFS(Pinjaman!$X$6:$X$1373,$I72,Pinjaman!$W$6:$W$1373,N$40,Pinjaman!$V$6:$V$1373,">60") -> 0 | O72: =COUNTIFS(Pinjaman!$X$6:$X$1373,$I72,Pinjaman!$W$6:$W$1373,0,Pinjaman!$V$6:$V$1373,">60") -> 0 | P72: =SUM(J72:O72) -> 20
B73: > 60 | C73: Karyawan | D73: =COUNTIFS('Data Angt'!$H$5:$H$5710,C73,'Data Angt'!$F$5:$F$5710,">60") -> 76 | E73: =D73/$D$27 -> 0.014179104 | I73: Tenaga Pengajar | J73: =COUNTIFS(Pinjaman!$X$6:$X$1373,$I73,Pinjaman!$W$6:$W$1373,J$40,Pinjaman!$V$6:$V$1373,">60") -> 1 | K73: =COUNTIFS(Pinjaman!$X$6:$X$1373,$I73,Pinjaman!$W$6:$W$1373,K$40,Pinjaman!$V$6:$V$1373,">60") -> 1 | L73: =COUNTIFS(Pinjaman!$X$6:$X$1373,$I73,Pinjaman!$W$6:$W$1373,L$40,Pinjaman!$V$6:$V$1373,">60") -> 0 | M73: =COUNTIFS(Pinjaman!$X$6:$X$1373,$I73,Pinjaman!$W$6:$W$1373,M$40,Pinjaman!$V$6:$V$1373,">60") -> 1 | N73: =COUNTIFS(Pinjaman!$X$6:$X$1373,$I73,Pinjaman!$W$6:$W$1373,N$40,Pinjaman!$V$6:$V$1373,">60") -> 0 | O73: =COUNTIFS(Pinjaman!$X$6:$X$1373,$I73,Pinjaman!$W$6:$W$1373,0,Pinjaman!$V$6:$V$1373,">60") -> 1 | P73: =SUM(J73:O73) -> 4
C74: Wiraswasta | D74: =COUNTIFS('Data Angt'!$H$5:$H$5710,C74,'Data Angt'!$F$5:$F$5710,">60") -> 210 | E74: =D74/$D$27 -> 0.039179104 | I74: Lain-Lain | J74: =COUNTIFS(Pinjaman!$X$6:$X$1373,$I74,Pinjaman!$W$6:$W$1373,J$40,Pinjaman!$V$6:$V$1373,">60") -> 3 | K74: =COUNTIFS(Pinjaman!$X$6:$X$1373,$I74,Pinjaman!$W$6:$W$1373,K$40,Pinjaman!$V$6:$V$1373,">60") -> 1 | L74: =COUNTIFS(Pinjaman!$X$6:$X$1373,$I74,Pinjaman!$W$6:$W$1373,L$40,Pinjaman!$V$6:$V$1373,">60") -> 0 | M74: =COUNTIFS(Pinjaman!$X$6:$X$1373,$I74,Pinjaman!$W$6:$W$1373,M$40,Pinjaman!$V$6:$V$1373,">60") -> 2 | N74: =COUNTIFS(Pinjaman!$X$6:$X$1373,$I74,Pinjaman!$W$6:$W$1373,N$40,Pinjaman!$V$6:$V$1373,">60") -> 0 | O74: =COUNTIFS(Pinjaman!$X$6:$X$1373,$I74,Pinjaman!$W$6:$W$1373,0,Pinjaman!$V$6:$V$1373,">60") -> 0 | P74: =SUM(J74:O74) -> 6
C75: Pelajar/Mahasiswa | D75: =COUNTIFS('Data Angt'!$H$5:$H$5710,C75,'Data Angt'!$F$5:$F$5710,">60") -> 1 | E75: =D75/$D$27 -> 0.00018656716 | I75: Aparatur Negara | J75: =COUNTIFS(Pinjaman!$X$6:$X$1373,$I75,Pinjaman!$W$6:$W$1373,J$40,Pinjaman!$V$6:$V$1373,">60") -> 0 | K75: =COUNTIFS(Pinjaman!$X$6:$X$1373,$I75,Pinjaman!$W$6:$W$1373,K$40,Pinjaman!$V$6:$V$1373,">60") -> 0 | L75: =COUNTIFS(Pinjaman!$X$6:$X$1373,$I75,Pinjaman!$W$6:$W$1373,L$40,Pinjaman!$V$6:$V$1373,">60") -> 0 | M75: =COUNTIFS(Pinjaman!$X$6:$X$1373,$I75,Pinjaman!$W$6:$W$1373,M$40,Pinjaman!$V$6:$V$1373,">60") -> 0 | N75: =COUNTIFS(Pinjaman!$X$6:$X$1373,$I75,Pinjaman!$W$6:$W$1373,N$40,Pinjaman!$V$6:$V$1373,">60") -> 0 | O75: =COUNTIFS(Pinjaman!$X$6:$X$1373,$I75,Pinjaman!$W$6:$W$1373,0,Pinjaman!$V$6:$V$1373,">60") -> 0 | P75: =SUM(J75:O75) -> 0
C76: Mengurus Rumah Tangga | D76: =COUNTIFS('Data Angt'!$H$5:$H$5710,C76,'Data Angt'!$F$5:$F$5710,">60") -> 182 | E76: =D76/$D$27 -> 0.033955224 | I76: Pensiunan | J76: =COUNTIFS(Pinjaman!$X$6:$X$1373,$I76,Pinjaman!$W$6:$W$1373,J$40,Pinjaman!$V$6:$V$1373,">60") -> 18 | K76: =COUNTIFS(Pinjaman!$X$6:$X$1373,$I76,Pinjaman!$W$6:$W$1373,K$40,Pinjaman!$V$6:$V$1373,">60") -> 8 | L76: =COUNTIFS(Pinjaman!$X$6:$X$1373,$I76,Pinjaman!$W$6:$W$1373,L$40,Pinjaman!$V$6:$V$1373,">60") -> 5 | M76: =COUNTIFS(Pinjaman!$X$6:$X$1373,$I76,Pinjaman!$W$6:$W$1373,M$40,Pinjaman!$V$6:$V$1373,">60") -> 10 | N76: =COUNTIFS(Pinjaman!$X$6:$X$1373,$I76,Pinjaman!$W$6:$W$1373,N$40,Pinjaman!$V$6:$V$1373,">60") -> 2 | O76: =COUNTIFS(Pinjaman!$X$6:$X$1373,$I76,Pinjaman!$W$6:$W$1373,0,Pinjaman!$V$6:$V$1373,">60") -> 1 | P76: =SUM(J76:O76) -> 44
C77: Tenaga Pengajar | D77: =COUNTIFS('Data Angt'!$H$5:$H$5710,C77,'Data Angt'!$F$5:$F$5710,">60") -> 32 | E77: =D77/$D$27 -> 0.0059701493 | I77: Pemuka Agama | J77: =COUNTIFS(Pinjaman!$X$6:$X$1373,$I77,Pinjaman!$W$6:$W$1373,J$40,Pinjaman!$V$6:$V$1373,">60") -> 0 | K77: =COUNTIFS(Pinjaman!$X$6:$X$1373,$I77,Pinjaman!$W$6:$W$1373,K$40,Pinjaman!$V$6:$V$1373,">60") -> 0 | L77: =COUNTIFS(Pinjaman!$X$6:$X$1373,$I77,Pinjaman!$W$6:$W$1373,L$40,Pinjaman!$V$6:$V$1373,">60") -> 0 | M77: =COUNTIFS(Pinjaman!$X$6:$X$1373,$I77,Pinjaman!$W$6:$W$1373,M$40,Pinjaman!$V$6:$V$1373,">60") -> 1 | N77: =COUNTIFS(Pinjaman!$X$6:$X$1373,$I77,Pinjaman!$W$6:$W$1373,N$40,Pinjaman!$V$6:$V$1373,">60") -> 0 | O77: =COUNTIFS(Pinjaman!$X$6:$X$1373,$I77,Pinjaman!$W$6:$W$1373,0,Pinjaman!$V$6:$V$1373,">60") -> 0 | P77: =SUM(J77:O77) -> 1
C78: Lain-Lain | D78: =COUNTIFS('Data Angt'!$H$5:$H$5710,C78,'Data Angt'!$F$5:$F$5710,">60") -> 34 | E78: =D78/$D$27 -> 0.0063432836 | I78: Petani/Pekebun/Nelayan/Peternak | J78: =COUNTIFS(Pinjaman!$X$6:$X$1373,$I78,Pinjaman!$W$6:$W$1373,J$40,Pinjaman!$V$6:$V$1373,">60") -> 0 | K78: =COUNTIFS(Pinjaman!$X$6:$X$1373,$I78,Pinjaman!$W$6:$W$1373,K$40,Pinjaman!$V$6:$V$1373,">60") -> 0 | L78: =COUNTIFS(Pinjaman!$X$6:$X$1373,$I78,Pinjaman!$W$6:$W$1373,L$40,Pinjaman!$V$6:$V$1373,">60") -> 0 | M78: =COUNTIFS(Pinjaman!$X$6:$X$1373,$I78,Pinjaman!$W$6:$W$1373,M$40,Pinjaman!$V$6:$V$1373,">60") -> 0 | N78: =COUNTIFS(Pinjaman!$X$6:$X$1373,$I78,Pinjaman!$W$6:$W$1373,N$40,Pinjaman!$V$6:$V$1373,">60") -> 0 | O78: =COUNTIFS(Pinjaman!$X$6:$X$1373,$I78,Pinjaman!$W$6:$W$1373,0,Pinjaman!$V$6:$V$1373,">60") -> 0 | P78: =SUM(J78:O78) -> 0
C79: Aparatur Negara | D79: =COUNTIFS('Data Angt'!$H$5:$H$5710,C79,'Data Angt'!$F$5:$F$5710,">60") -> 0 | E79: =D79/$D$27 -> 0 | I79: Tenaga Ahli | J79: =COUNTIFS(Pinjaman!$X$6:$X$1373,$I79,Pinjaman!$W$6:$W$1373,J$40,Pinjaman!$V$6:$V$1373,">60") -> 0 | K79: =COUNTIFS(Pinjaman!$X$6:$X$1373,$I79,Pinjaman!$W$6:$W$1373,K$40,Pinjaman!$V$6:$V$1373,">60") -> 0 | L79: =COUNTIFS(Pinjaman!$X$6:$X$1373,$I79,Pinjaman!$W$6:$W$1373,L$40,Pinjaman!$V$6:$V$1373,">60") -> 0 | M79: =COUNTIFS(Pinjaman!$X$6:$X$1373,$I79,Pinjaman!$W$6:$W$1373,M$40,Pinjaman!$V$6:$V$1373,">60") -> 0 | N79: =COUNTIFS(Pinjaman!$X$6:$X$1373,$I79,Pinjaman!$W$6:$W$1373,N$40,Pinjaman!$V$6:$V$1373,">60") -> 0 | O79: =COUNTIFS(Pinjaman!$X$6:$X$1373,$I79,Pinjaman!$W$6:$W$1373,0,Pinjaman!$V$6:$V$1373,">60") -> 0 | P79: =SUM(J79:O79) -> 0
C80: Pensiunan | D80: =COUNTIFS('Data Angt'!$H$5:$H$5710,C80,'Data Angt'!$F$5:$F$5710,">60") -> 201 | E80: =D80/$D$27 -> 0.0375 | I80: Belum/Tidak bekerja | J80: =COUNTIFS(Pinjaman!$X$6:$X$1373,$I80,Pinjaman!$W$6:$W$1373,J$40,Pinjaman!$V$6:$V$1373,">60") -> 0 | K80: =COUNTIFS(Pinjaman!$X$6:$X$1373,$I80,Pinjaman!$W$6:$W$1373,K$40,Pinjaman!$V$6:$V$1373,">60") -> 0 | L80: =COUNTIFS(Pinjaman!$X$6:$X$1373,$I80,Pinjaman!$W$6:$W$1373,L$40,Pinjaman!$V$6:$V$1373,">60") -> 0 | M80: =COUNTIFS(Pinjaman!$X$6:$X$1373,$I80,Pinjaman!$W$6:$W$1373,M$40,Pinjaman!$V$6:$V$1373,">60") -> 0 | N80: =COUNTIFS(Pinjaman!$X$6:$X$1373,$I80,Pinjaman!$W$6:$W$1373,N$40,Pinjaman!$V$6:$V$1373,">60") -> 0 | O80: =COUNTIFS(Pinjaman!$X$6:$X$1373,$I80,Pinjaman!$W$6:$W$1373,0,Pinjaman!$V$6:$V$1373,">60") -> 0 | P80: =SUM(J80:O80) -> 0
C81: Pemuka Agama | D81: =COUNTIFS('Data Angt'!$H$5:$H$5710,C81,'Data Angt'!$F$5:$F$5710,">60") -> 13 | E81: =D81/$D$27 -> 0.0024253731 | I81: Data Kosong | J81: =COUNTIFS(Pinjaman!$X$6:$X$1373,0,Pinjaman!$W$6:$W$1373,J$40,Pinjaman!$V$6:$V$1373,">60") -> 0 | K81: =COUNTIFS(Pinjaman!$X$6:$X$1373,0,Pinjaman!$W$6:$W$1373,K$40,Pinjaman!$V$6:$V$1373,">60") -> 2 | L81: =COUNTIFS(Pinjaman!$X$6:$X$1373,0,Pinjaman!$W$6:$W$1373,L$40,Pinjaman!$V$6:$V$1373,">60") -> 0 | M81: =COUNTIFS(Pinjaman!$X$6:$X$1373,0,Pinjaman!$W$6:$W$1373,M$40,Pinjaman!$V$6:$V$1373,">60") -> 0 | N81: =COUNTIFS(Pinjaman!$X$6:$X$1373,0,Pinjaman!$W$6:$W$1373,N$40,Pinjaman!$V$6:$V$1373,">60") -> 0 | O81: =COUNTIFS(Pinjaman!$X$6:$X$1373,0,Pinjaman!$W$6:$W$1373,0,Pinjaman!$V$6:$V$1373,">60") -> 0 | P81: =SUM(J81:O81) -> 2
C82: Petani/Pekebun/Nelayan/Peternak | D82: =COUNTIFS('Data Angt'!$H$5:$H$5710,C82,'Data Angt'!$F$5:$F$5710,">60") -> 0 | E82: =D82/$D$27 -> 0 | I82: JUMLAH | J82: =SUM(J69:J81) -> 37 | K82: =SUM(K69:K81) -> 27 | L82: =SUM(L69:L81) -> 10 | M82: =SUM(M69:M81) -> 51 | N82: =SUM(N69:N81) -> 3 | O82: =SUM(O69:O81) -> 10 | P82: =SUM(P69:P81) -> 138
C83: Tenaga Ahli | D83: =COUNTIFS('Data Angt'!$H$5:$H$5710,C83,'Data Angt'!$F$5:$F$5710,">60") -> 3 | E83: =D83/$D$27 -> 0.00055970149
C84: Belum/Tidak bekerja | D84: =COUNTIFS('Data Angt'!$H$5:$H$5710,C84,'Data Angt'!$F$5:$F$5710,">60") -> 13 | E84: =D84/$D$27 -> 0.0024253731
C85: Data Kosong | D85: =COUNTIFS('Data Angt'!$H$5:$H$5710,"",'Data Angt'!$F$5:$F$5710,">60") -> 40 | E85: =D85/$D$27 -> 0.0074626866
C86: JUMLAH | D86: =SUM(D73:D85) -> 805 | E86: =D86/$D$27 -> 0.15018657

Sheet ANALISA
A2: 1 | B2: KLASIFIKASI USIA KESELURUHAN ANGGOTA | M2: ANGGOTA BARU 2025
M3: USIA | N3: GAB | P3: PBL | R3: KRK | T3: JBR | V3: BWI | X3: MJK | Z3: MGL
B4: USIA | C4: JUMLAH | D4: % | E4: PBL | F4: KRK | G4: JBR | H4: BWI | I4: MJK | J4: MGL | K4: PML | M4: <24 th | N4: =COUNTIF('2025'!$I$3:$I$649,"<24") -> 82 | O4: =N4/$N$9 -> 0.12673879 | P4: =COUNTIFS('2025'!$F$3:$F$649,"001",'2025'!$I$3:$I$649,"<24") -> 48 | Q4: =P4/P$9 -> 0.17977528 | R4: =COUNTIFS('2025'!$F$3:$F$649,"002",'2025'!$I$3:$I$649,"<24") -> 4 | S4: =R4/R$9 -> 0.042553191 | T4: =COUNTIFS('2025'!$F$3:$F$649,"003",'2025'!$I$3:$I$649,"<24") -> 6 | U4: =T4/T$9 -> 0.068181818 | V4: =COUNTIFS('2025'!$F$3:$F$649,"004",'2025'!$I$3:$I$649,"<24") -> 12 | W4: =V4/V$9 -> 0.14457831 | X4: =COUNTIFS('2025'!$F$3:$F$649,"005",'2025'!$I$3:$I$649,"<24") -> 7 | Y4: =X4/X$9 -> 0.1 | Z4: =COUNTIFS('2025'!$F$3:$F$649,"006",'2025'!$I$3:$I$649,"<24") -> 5 | AA4: =Z4/Z$9 -> 0.11111111
B5: <24 th | C5: =COUNTIF('Data Angt'!$F$5:$F$5809,"<24") -> 342 | D5: =C5/$C$11 -> 0.058914729 | E5: =COUNTIFS('Data Angt'!$C$5:$C$5809,E$4,'Data Angt'!$F$5:$F$5809,"<24") -> 166 | F5: =COUNTIFS('Data Angt'!$C$5:$C$5809,F$4,'Data Angt'!$F$5:$F$5809,"<24") -> 27 | G5: =COUNTIFS('Data Angt'!$C$5:$C$5809,G$4,'Data Angt'!$F$5:$F$5809,"<24") -> 50 | H5: =COUNTIFS('Data Angt'!$C$5:$C$5809,H$4,'Data Angt'!$F$5:$F$5809,"<24") -> 39 | I5: =COUNTIFS('Data Angt'!$C$5:$C$5809,I$4,'Data Angt'!$F$5:$F$5809,"<24") -> 34 | J5: =COUNTIFS('Data Angt'!$C$5:$C$5809,J$4,'Data Angt'!$F$5:$F$5809,"<24") -> 26 | K5: =COUNTIFS('Data Angt'!$C$5:$C$5809,K$4,'Data Angt'!$F$5:$F$5809,"<24") -> 0 | M5: 24 - 35 th | N5: =COUNTIF('2025'!$I$3:$I$649,"<=35")-COUNTIF('2025'!$I$3:$I$649,"<24") -> 159 | O5: =N5/$N$9 -> 0.24574961 | P5: =COUNTIFS('2025'!$F$3:$F$649,"001",'2025'!$I$3:$I$649,"<=35")-COUNTIFS('2025'!$F$3:$F$649,"001",'2025'!$I$3:$I$649,"<24") -> 81 | Q5: =P5/P$9 -> 0.30337079 | R5: =COUNTIFS('2025'!$F$3:$F$649,"002",'2025'!$I$3:$I$649,"<=35")-COUNTIFS('2025'!$F$3:$F$649,"002",'2025'!$I$3:$I$649,"<24") -> 15 | S5: =R5/R$9 -> 0.15957447 | T5: =COUNTIFS('2025'!$F$3:$F$649,"003",'2025'!$I$3:$I$649,"<=35")-COUNTIFS('2025'!$F$3:$F$649,"003",'2025'!$I$3:$I$649,"<24") -> 22 | U5: =T5/T$9 -> 0.25 | V5: =COUNTIFS('2025'!$F$3:$F$649,"004",'2025'!$I$3:$I$649,"<=35")-COUNTIFS('2025'!$F$3:$F$649,"004",'2025'!$I$3:$I$649,"<24") -> 27 | W5: =V5/V$9 -> 0.3253012 | X5: =COUNTIFS('2025'!$F$3:$F$649,"005",'2025'!$I$3:$I$649,"<=35")-COUNTIFS('2025'!$F$3:$F$649,"005",'2025'!$I$3:$I$649,"<24") -> 4 | Y5: =X5/X$9 -> 0.057142857 | Z5: =COUNTIFS('2025'!$F$3:$F$649,"006",'2025'!$I$3:$I$649,"<=35")-COUNTIFS('2025'!$F$3:$F$649,"006",'2025'!$I$3:$I$649,"<24") -> 10 | AA5: =Z5/Z$9 -> 0.22222222
B6: 24 - 35 th | C6: =COUNTIF('Data Angt'!$F$5:$F$5809,"<=35")-COUNTIF('Data Angt'!$F$5:$F$5809,"<24") -> 1006 | D6: =C6/$C$11 -> 0.17329888 | E6: =COUNTIFS('Data Angt'!$C$5:$C$5809,E$4,'Data Angt'!$F$5:$F$5809,"<=35")-COUNTIFS('Data Angt'!$C$5:$C$5809,E$4,'Data Angt'!$F$5:$F$5809,"<24") -> 513 | F6: =COUNTIFS('Data Angt'!$C$5:$C$5809,F$4,'Data Angt'!$F$5:$F$5809,"<=35")-COUNTIFS('Data Angt'!$C$5:$C$5809,F$4,'Data Angt'!$F$5:$F$5809,"<24") -> 105 | G6: =COUNTIFS('Data Angt'!$C$5:$C$5809,G$4,'Data Angt'!$F$5:$F$5809,"<=35")-COUNTIFS('Data Angt'!$C$5:$C$5809,G$4,'Data Angt'!$F$5:$F$5809,"<24") -> 164 | H6: =COUNTIFS('Data Angt'!$C$5:$C$5809,H$4,'Data Angt'!$F$5:$F$5809,"<=35")-COUNTIFS('Data Angt'!$C$5:$C$5809,H$4,'Data Angt'!$F$5:$F$5809,"<24") -> 112 | I6: =COUNTIFS('Data Angt'!$C$5:$C$5809,I$4,'Data Angt'!$F$5:$F$5809,"<=35")-COUNTIFS('Data Angt'!$C$5:$C$5809,I$4,'Data Angt'!$F$5:$F$5809,"<24") -> 46 | J6: =COUNTIFS('Data Angt'!$C$5:$C$5809,J$4,'Data Angt'!$F$5:$F$5809,"<=35")-COUNTIFS('Data Angt'!$C$5:$C$5809,J$4,'Data Angt'!$F$5:$F$5809,"<24") -> 62 | K6: =COUNTIFS('Data Angt'!$C$5:$C$5809,K$4,'Data Angt'!$F$5:$F$5809,"<=35")-COUNTIFS('Data Angt'!$C$5:$C$5809,K$4,'Data Angt'!$F$5:$F$5809,"<24") -> 4 | M6: 36 - 45 th | N6: =COUNTIF('2025'!$I$3:$I$649,"<=45")-COUNTIF('2025'!$I$3:$I$649,"<=35") -> 160 | O6: =N6/$N$9 -> 0.24729521 | P6: =COUNTIFS('2025'!$F$3:$F$649,"001",'2025'!$I$3:$I$649,"<=45")-COUNTIFS('2025'!$F$3:$F$649,"001",'2025'!$I$3:$I$649,"<36") -> 51 | Q6: =P6/P$9 -> 0.19101124 | R6: =COUNTIFS('2025'!$F$3:$F$649,"002",'2025'!$I$3:$I$649,"<=45")-COUNTIFS('2025'!$F$3:$F$649,"002",'2025'!$I$3:$I$649,"<36") -> 34 | S6: =R6/R$9 -> 0.36170213 | T6: =COUNTIFS('2025'!$F$3:$F$649,"003",'2025'!$I$3:$I$649,"<=45")-COUNTIFS('2025'!$F$3:$F$649,"003",'2025'!$I$3:$I$649,"<36") -> 23 | U6: =T6/T$9 -> 0.26136364 | V6: =COUNTIFS('2025'!$F$3:$F$649,"004",'2025'!$I$3:$I$649,"<=45")-COUNTIFS('2025'!$F$3:$F$649,"004",'2025'!$I$3:$I$649,"<36") -> 28 | W6: =V6/V$9 -> 0.3373494 | X6: =COUNTIFS('2025'!$F$3:$F$649,"005",'2025'!$I$3:$I$649,"<=45")-COUNTIFS('2025'!$F$3:$F$649,"005",'2025'!$I$3:$I$649,"<36") -> 13 | Y6: =X6/X$9 -> 0.18571429 | Z6: =COUNTIFS('2025'!$F$3:$F$649,"006",'2025'!$I$3:$I$649,"<=45")-COUNTIFS('2025'!$F$3:$F$649,"006",'2025'!$I$3:$I$649,"<36") -> 11 | AA6: =Z6/Z$9 -> 0.24444444
B7: 36 - 45 th | C7: =COUNTIF('Data Angt'!$F$5:$F$5809,"<=45")-COUNTIF('Data Angt'!$F$5:$F$5809,"<=35") -> 1448 | D7: =C7/$C$11 -> 0.24944014 | E7: =COUNTIFS('Data Angt'!$C$5:$C$5809,E$4,'Data Angt'!$F$5:$F$5809,"<=45")-COUNTIFS('Data Angt'!$C$5:$C$5809,E$4,'Data Angt'!$F$5:$F$5809,"<36") -> 653 | F7: =COUNTIFS('Data Angt'!$C$5:$C$5809,F$4,'Data Angt'!$F$5:$F$5809,"<=45")-COUNTIFS('Data Angt'!$C$5:$C$5809,F$4,'Data Angt'!$F$5:$F$5809,"<36") -> 198 | G7: =COUNTIFS('Data Angt'!$C$5:$C$5809,G$4,'Data Angt'!$F$5:$F$5809,"<=45")-COUNTIFS('Data Angt'!$C$5:$C$5809,G$4,'Data Angt'!$F$5:$F$5809,"<36") -> 211 | H7: =COUNTIFS('Data Angt'!$C$5:$C$5809,H$4,'Data Angt'!$F$5:$F$5809,"<=45")-COUNTIFS('Data Angt'!$C$5:$C$5809,H$4,'Data Angt'!$F$5:$F$5809,"<36") -> 113 | I7: =COUNTIFS('Data Angt'!$C$5:$C$5809,I$4,'Data Angt'!$F$5:$F$5809,"<=45")-COUNTIFS('Data Angt'!$C$5:$C$5809,I$4,'Data Angt'!$F$5:$F$5809,"<36") -> 82 | J7: =COUNTIFS('Data Angt'!$C$5:$C$5809,J$4,'Data Angt'!$F$5:$F$5809,"<=45")-COUNTIFS('Data Angt'!$C$5:$C$5809,J$4,'Data Angt'!$F$5:$F$5809,"<36") -> 100 | K7: =COUNTIFS('Data Angt'!$C$5:$C$5809,K$4,'Data Angt'!$F$5:$F$5809,"<=45")-COUNTIFS('Data Angt'!$C$5:$C$5809,K$4,'Data Angt'!$F$5:$F$5809,"<36") -> 91 | M7: 46 - 60 th | N7: =COUNTIF('2025'!$I$3:$I$649,"<=60")-COUNTIF('2025'!$I$3:$I$649,"<=45") -> 206 | O7: =N7/$N$9 -> 0.31839258 | P7: =COUNTIFS('2025'!$F$3:$F$649,"001",'2025'!$I$3:$I$649,"<=60")-COUNTIFS('2025'!$F$3:$F$649,"001",'2025'!$I$3:$I$649,"<46") -> 72 | Q7: =P7/P$9 -> 0.26966292 | R7: =COUNTIFS('2025'!$F$3:$F$649,"002",'2025'!$I$3:$I$649,"<=60")-COUNTIFS('2025'!$F$3:$F$649,"002",'2025'!$I$3:$I$649,"<46") -> 35 | S7: =R7/R$9 -> 0.37234043 | T7: =COUNTIFS('2025'!$F$3:$F$649,"003",'2025'!$I$3:$I$649,"<=60")-COUNTIFS('2025'!$F$3:$F$649,"003",'2025'!$I$3:$I$649,"<46") -> 33 | U7: =T7/T$9 -> 0.375 | V7: =COUNTIFS('2025'!$F$3:$F$649,"004",'2025'!$I$3:$I$649,"<=60")-COUNTIFS('2025'!$F$3:$F$649,"004",'2025'!$I$3:$I$649,"<46") -> 13 | W7: =V7/V$9 -> 0.15662651 | X7: =COUNTIFS('2025'!$F$3:$F$649,"005",'2025'!$I$3:$I$649,"<=60")-COUNTIFS('2025'!$F$3:$F$649,"005",'2025'!$I$3:$I$649,"<46") -> 36 | Y7: =X7/X$9 -> 0.51428571 | Z7: =COUNTIFS('2025'!$F$3:$F$649,"006",'2025'!$I$3:$I$649,"<=60")-COUNTIFS('2025'!$F$3:$F$649,"006",'2025'!$I$3:$I$649,"<46") -> 17 | AA7: =Z7/Z$9 -> 0.37777778
B8: 46 - 60 th | C8: =COUNTIF('Data Angt'!$F$5:$F$5809,"<=60")-COUNTIF('Data Angt'!$F$5:$F$5809,"<=45") -> 2097 | D8: =C8/$C$11 -> 0.36124031 | E8: =COUNTIFS('Data Angt'!$C$5:$C$5809,E$4,'Data Angt'!$F$5:$F$5809,"<=60")-COUNTIFS('Data Angt'!$C$5:$C$5809,E$4,'Data Angt'!$F$5:$F$5809,"<46") -> 874 | F8: =COUNTIFS('Data Angt'!$C$5:$C$5809,F$4,'Data Angt'!$F$5:$F$5809,"<=60")-COUNTIFS('Data Angt'!$C$5:$C$5809,F$4,'Data Angt'!$F$5:$F$5809,"<46") -> 262 | G8: =COUNTIFS('Data Angt'!$C$5:$C$5809,G$4,'Data Angt'!$F$5:$F$5809,"<=60")-COUNTIFS('Data Angt'!$C$5:$C$5809,G$4,'Data Angt'!$F$5:$F$5809,"<46") -> 371 | H8: =COUNTIFS('Data Angt'!$C$5:$C$5809,H$4,'Data Angt'!$F$5:$F$5809,"<=60")-COUNTIFS('Data Angt'!$C$5:$C$5809,H$4,'Data Angt'!$F$5:$F$5809,"<46") -> 155 | I8: =COUNTIFS('Data Angt'!$C$5:$C$5809,I$4,'Data Angt'!$F$5:$F$5809,"<=60")-COUNTIFS('Data Angt'!$C$5:$C$5809,I$4,'Data Angt'!$F$5:$F$5809,"<46") -> 156 | J8: =COUNTIFS('Data Angt'!$C$5:$C$5809,J$4,'Data Angt'!$F$5:$F$5809,"<=60")-COUNTIFS('Data Angt'!$C$5:$C$5809,J$4,'Data Angt'!$F$5:$F$5809,"<46") -> 228 | K8: =COUNTIFS('Data Angt'!$C$5:$C$5809,K$4,'Data Angt'!$F$5:$F$5809,"<=60")-COUNTIFS('Data Angt'!$C$5:$C$5809,K$4,'Data Angt'!$F$5:$F$5809,"<46") -> 51 | M8: > 60 th | N8: =COUNTIF('2025'!$I$3:$I$649,">60") -> 40 | O8: =N8/$N$9 -> 0.061823802 | P8: =COUNTIFS('2025'!$F$3:$F$649,"001",'2025'!$I$3:$I$649,">60") -> 15 | Q8: =P8/P$9 -> 0.056179775 | R8: =COUNTIFS('2025'!$F$3:$F$649,"002",'2025'!$I$3:$I$649,">60") -> 6 | S8: =R8/R$9 -> 0.063829787 | T8: =COUNTIFS('2025'!$F$3:$F$649,"003",'2025'!$I$3:$I$649,">60") -> 4 | U8: =T8/T$9 -> 0.045454545 | V8: =COUNTIFS('2025'!$F$3:$F$649,"004",'2025'!$I$3:$I$649,">60") -> 3 | W8: =V8/V$9 -> 0.036144578 | X8: =COUNTIFS('2025'!$F$3:$F$649,"005",'2025'!$I$3:$I$649,">60") -> 10 | Y8: =X8/X$9 -> 0.14285714 | Z8: =COUNTIFS('2025'!$F$3:$F$649,"006",'2025'!$I$3:$I$649,">60") -> 2 | AA8: =Z8/Z$9 -> 0.044444444
B9: > 60 th | C9: =COUNTIF('Data Angt'!$F$5:$F$5809,">60") -> 870 | D9: =C9/$C$11 -> 0.1498708 | E9: =COUNTIFS('Data Angt'!$C$5:$C$5809,E$4,'Data Angt'!$F$5:$F$5809,">60") -> 410 | F9: =COUNTIFS('Data Angt'!$C$5:$C$5809,F$4,'Data Angt'!$F$5:$F$5809,">60") -> 105 | G9: =COUNTIFS('Data Angt'!$C$5:$C$5809,G$4,'Data Angt'!$F$5:$F$5809,">60") -> 148 | H9: =COUNTIFS('Data Angt'!$C$5:$C$5809,H$4,'Data Angt'!$F$5:$F$5809,">60") -> 61 | I9: =COUNTIFS('Data Angt'!$C$5:$C$5809,I$4,'Data Angt'!$F$5:$F$5809,">60") -> 38 | J9: =COUNTIFS('Data Angt'!$C$5:$C$5809,J$4,'Data Angt'!$F$5:$F$5809,">60") -> 106 | K9: =COUNTIFS('Data Angt'!$C$5:$C$5809,K$4,'Data Angt'!$F$5:$F$5809,">60") -> 2 | M9: TOTAL | N9: =SUM(N4:N8) -> 647 | P9: =SUM(P4:P8) -> 267 | R9: =SUM(R4:R8) -> 94 | T9: =SUM(T4:T8) -> 88 | V9: =SUM(V4:V8) -> 83 | X9: =SUM(X4:X8) -> 70 | Z9: =SUM(Z4:Z8) -> 45
B10: Tidak Valid | C10: =COUNTIF('Data Angt'!$F$5:$F$5809,"#VALUE!") -> 42 | D10: =C10/$C$11 -> 0.0072351421 | E10: =COUNTIFS('Data Angt'!$C$5:$C$5809,E$4,'Data Angt'!$F$5:$F$5809,"#VALUE!") -> 0 | F10: =COUNTIFS('Data Angt'!$C$5:$C$5809,F$4,'Data Angt'!$F$5:$F$5809,"#VALUE!") -> 0 | G10: =COUNTIFS('Data Angt'!$C$5:$C$5809,G$4,'Data Angt'!$F$5:$F$5809,"#VALUE!") -> 0 | H10: =COUNTIFS('Data Angt'!$C$5:$C$5809,H$4,'Data Angt'!$F$5:$F$5809,"#VALUE!") -> 0 | I10: =COUNTIFS('Data Angt'!$C$5:$C$5809,I$4,'Data Angt'!$F$5:$F$5809,"#VALUE!") -> 0 | J10: =COUNTIFS('Data Angt'!$C$5:$C$5809,J$4,'Data Angt'!$F$5:$F$5809,"#VALUE!") -> 0 | K10: =COUNTIFS('Data Angt'!$C$5:$C$5809,K$4,'Data Angt'!$F$5:$F$5809,"#VALUE!") -> 42
B11: TOTAL | C11: =SUM(C5:C10) -> 5805 | E11: =SUM(E5:E10) -> 2616 | F11: =SUM(F5:F10) -> 697 | G11: =SUM(G5:G10) -> 944 | H11: =SUM(H5:H10) -> 480 | I11: =SUM(I5:I10) -> 356 | J11: =SUM(J5:J10) -> 522 | K11: =SUM(K5:K10) -> 190
M12: ANGGOTA BARU 2024
M13: USIA | N13: GAB | P13: PBL | R13: KRK | T13: JBR | V13: BWI | X13: MJK | Z13: MGL | AB13: PM
M14: <24 th | N14: =COUNTIF('2024'!$K$5:$K$908,"<24") -> 83 | O14: =N14/N$20 -> 0.091814159 | P14: =COUNTIFS('2024'!$L$3:$L$908,"001",'2024'!$K$3:$K$908,"<24") -> 44 | Q14: =P14/P$20 -> 0.15068493 | R14: =COUNTIFS('2024'!$L$3:$L$908,"002",'2024'!$K$3:$K$908,"<24") -> 8 | S14: =R14/R$20 -> 0.081632653 | T14: =COUNTIFS('2024'!$L$3:$L$908,"003",'2024'!$K$3:$K$908,"<24") -> 5 | U14: =T14/T$20 -> 0.045454545 | V14: =COUNTIFS('2024'!$L$3:$L$908,"004",'2024'!$K$3:$K$908,"<24") -> 16 | W14: =V14/V$20 -> 0.14953271 | X14: =COUNTIFS('2024'!$L$3:$L$908,"005",'2024'!$K$3:$K$908,"<24") -> 4 | Y14: =X14/X$20 -> 0.072727273 | Z14: =COUNTIFS('2024'!$L$3:$L$908,"006",'2024'!$K$3:$K$908,"<24") -> 6 | AA14: =Z14/Z$20 -> 0.12 | AB14: =COUNTIFS('2024'!$L$3:$L$908,"007",'2024'!$K$3:$K$908,"<24") -> 0 | AC14: =AB14/AB$20 -> 0
M15: 24 - 35 th | N15: =COUNTIF('2024'!$K$5:$K$908,"<=35")-COUNTIF('2024'!$K$5:$K$908,"<24") -> 199 | O15: =N15/N$20 -> 0.22013274 | P15: =COUNTIFS('2024'!$L$3:$L$908,"001",'2024'!$K$3:$K$908,"<=35")-COUNTIFS('2024'!$L$3:$L$908,"001",'2024'!$K$3:$K$908,"<24") -> 89 | Q15: =P15/P$20 -> 0.30479452 | R15: =COUNTIFS('2024'!$L$3:$L$908,"002",'2024'!$K$3:$K$908,"<=35")-COUNTIFS('2024'!$L$3:$L$908,"002",'2024'!$K$3:$K$908,"<24") -> 24 | S15: =R15/R$20 -> 0.24489796 | T15: =COUNTIFS('2024'!$L$3:$L$908,"003",'2024'!$K$3:$K$908,"<=35")-COUNTIFS('2024'!$L$3:$L$908,"003",'2024'!$K$3:$K$908,"<24") -> 28 | U15: =T15/T$20 -> 0.25454545 | V15: =COUNTIFS('2024'!$L$3:$L$908,"004",'2024'!$K$3:$K$908,"<=35")-COUNTIFS('2024'!$L$3:$L$908,"004",'2024'!$K$3:$K$908,"<24") -> 28 | W15: =V15/V$20 -> 0.26168224 | X15: =COUNTIFS('2024'!$L$3:$L$908,"005",'2024'!$K$3:$K$908,"<=35")-COUNTIFS('2024'!$L$3:$L$908,"005",'2024'!$K$3:$K$908,"<24") -> 15 | Y15: =X15/X$20 -> 0.27272727 | Z15: =COUNTIFS('2024'!$L$3:$L$908,"006",'2024'!$K$3:$K$908,"<=35")-COUNTIFS('2024'!$L$3:$L$908,"006",'2024'!$K$3:$K$908,"<24") -> 10 | AA15: =Z15/Z$20 -> 0.2 | AB15: =COUNTIFS('2024'!$L$3:$L$908,"007",'2024'!$K$3:$K$908,"<=35")-COUNTIFS('2024'!$L$3:$L$908,"007",'2024'!$K$3:$K$908,"<24") -> 5 | AC15: =AB15/AB$20 -> 0.026041667
M16: 36 - 45 th | N16: =COUNTIF('2024'!$K$5:$K$908,"<=45")-COUNTIF('2024'!$K$5:$K$908,"<=35") -> 274 | O16: =N16/N$20 -> 0.30309735 | P16: =COUNTIFS('2024'!$L$3:$L$908,"001",'2024'!$K$3:$K$908,"<=45")-COUNTIFS('2024'!$L$3:$L$908,"001",'2024'!$K$3:$K$908,"<36") -> 64 | Q16: =P16/P$20 -> 0.21917808 | R16: =COUNTIFS('2024'!$L$3:$L$908,"002",'2024'!$K$3:$K$908,"<=45")-COUNTIFS('2024'!$L$3:$L$908,"002",'2024'!$K$3:$K$908,"<36") -> 33 | S16: =R16/R$20 -> 0.33673469 | T16: =COUNTIFS('2024'!$L$3:$L$908,"003",'2024'!$K$3:$K$908,"<=45")-COUNTIFS('2024'!$L$3:$L$908,"003",'2024'!$K$3:$K$908,"<36") -> 26 | U16: =T16/T$20 -> 0.23636364 | V16: =COUNTIFS('2024'!$L$3:$L$908,"004",'2024'!$K$3:$K$908,"<=45")-COUNTIFS('2024'!$L$3:$L$908,"004",'2024'!$K$3:$K$908,"<36") -> 26 | W16: =V16/V$20 -> 0.24299065 | X16: =COUNTIFS('2024'!$L$3:$L$908,"005",'2024'!$K$3:$K$908,"<=45")-COUNTIFS('2024'!$L$3:$L$908,"005",'2024'!$K$3:$K$908,"<36") -> 13 | Y16: =X16/X$20 -> 0.23636364 | Z16: =COUNTIFS('2024'!$L$3:$L$908,"006",'2024'!$K$3:$K$908,"<=45")-COUNTIFS('2024'!$L$3:$L$908,"006",'2024'!$K$3:$K$908,"<36") -> 12 | AA16: =Z16/Z$20 -> 0.24 | AB16: =COUNTIFS('2024'!$L$3:$L$908,"007",'2024'!$K$3:$K$908,"<=45")-COUNTIFS('2024'!$L$3:$L$908,"007",'2024'!$K$3:$K$908,"<36") -> 100 | AC16: =AB16/AB$20 -> 0.52083333
M17: 46 - 60 th | N17: =COUNTIF('2024'!$K$5:$K$908,"<=60")-COUNTIF('2024'!$K$5:$K$908,"<=45") -> 260 | O17: =N17/N$20 -> 0.28761062 | P17: =COUNTIFS('2024'!$L$3:$L$908,"001",'2024'!$K$3:$K$908,"<=60")-COUNTIFS('2024'!$L$3:$L$908,"001",'2024'!$K$3:$K$908,"<46") -> 76 | Q17: =P17/P$20 -> 0.26027397 | R17: =COUNTIFS('2024'!$L$3:$L$908,"002",'2024'!$K$3:$K$908,"<=60")-COUNTIFS('2024'!$L$3:$L$908,"002",'2024'!$K$3:$K$908,"<46") -> 29 | S17: =R17/R$20 -> 0.29591837 | T17: =COUNTIFS('2024'!$L$3:$L$908,"003",'2024'!$K$3:$K$908,"<=60")-COUNTIFS('2024'!$L$3:$L$908,"003",'2024'!$K$3:$K$908,"<46") -> 41 | U17: =T17/T$20 -> 0.37272727 | V17: =COUNTIFS('2024'!$L$3:$L$908,"004",'2024'!$K$3:$K$908,"<=60")-COUNTIFS('2024'!$L$3:$L$908,"004",'2024'!$K$3:$K$908,"<46") -> 32 | W17: =V17/V$20 -> 0.29906542 | X17: =COUNTIFS('2024'!$L$3:$L$908,"005",'2024'!$K$3:$K$908,"<=60")-COUNTIFS('2024'!$L$3:$L$908,"005",'2024'!$K$3:$K$908,"<46") -> 21 | Y17: =X17/X$20 -> 0.38181818 | Z17: =COUNTIFS('2024'!$L$3:$L$908,"006",'2024'!$K$3:$K$908,"<=60")-COUNTIFS('2024'!$L$3:$L$908,"006",'2024'!$K$3:$K$908,"<46") -> 19 | AA17: =Z17/Z$20 -> 0.38 | AB17: =COUNTIFS('2024'!$L$3:$L$908,"007",'2024'!$K$3:$K$908,"<=60")-COUNTIFS('2024'!$L$3:$L$908,"007",'2024'!$K$3:$K$908,"<46") -> 42 | AC17: =AB17/AB$20 -> 0.21875
M18: > 60 th | N18: =COUNTIF('2024'!$K$5:$K$908,">60") -> 45 | O18: =N18/N$20 -> 0.049778761 | P18: =COUNTIFS('2024'!$L$3:$L$908,"001",'2024'!$K$3:$K$908,">60") -> 19 | Q18: =P18/P$20 -> 0.065068493 | R18: =COUNTIFS('2024'!$L$3:$L$908,"002",'2024'!$K$3:$K$908,">60") -> 4 | S18: =R18/R$20 -> 0.040816327 | T18: =COUNTIFS('2024'!$L$3:$L$908,"003",'2024'!$K$3:$K$908,">60") -> 10 | U18: =T18/T$20 -> 0.090909091 | V18: =COUNTIFS('2024'!$L$3:$L$908,"004",'2024'!$K$3:$K$908,">60") -> 5 | W18: =V18/V$20 -> 0.046728972 | X18: =COUNTIFS('2024'!$L$3:$L$908,"005",'2024'!$K$3:$K$908,">60") -> 2 | Y18: =X18/X$20 -> 0.036363636 | Z18: =COUNTIFS('2024'!$L$3:$L$908,"006",'2024'!$K$3:$K$908,">60") -> 3 | AA18: =Z18/Z$20 -> 0.06 | AB18: =COUNTIFS('2024'!$L$3:$L$908,"007",'2024'!$K$3:$K$908,">60") -> 2 | AC18: =AB18/AB$20 -> 0.010416667
M19: Tidak Valid | N19: =COUNTIF('2024'!$K$5:$K$908,"/") -> 43 | O19: =N19/N$20 -> 0.047566372 | P19: =COUNTIFS('2024'!$L$3:$L$908,"001",'2024'!$K$3:$K$908,"/") -> 0 | Q19: =P19/P$20 -> 0 | R19: =COUNTIFS('2024'!$L$3:$L$908,"002",'2024'!$K$3:$K$908,"/") -> 0 | S19: =R19/R$20 -> 0 | T19: =COUNTIFS('2024'!$L$3:$L$908,"003",'2024'!$K$3:$K$908,"/") -> 0 | U19: =T19/T$20 -> 0 | V19: =COUNTIFS('2024'!$L$3:$L$908,"004",'2024'!$K$3:$K$908,"/") -> 0 | W19: =V19/V$20 -> 0 | X19: =COUNTIFS('2024'!$L$3:$L$908,"005",'2024'!$K$3:$K$908,"/") -> 0 | Y19: =X19/X$20 -> 0 | Z19: =COUNTIFS('2024'!$L$3:$L$908,"006",'2024'!$K$3:$K$908,"/") -> 0 | AA19: =Z19/Z$20 -> 0 | AB19: =COUNTIFS('2024'!$L$3:$L$908,"007",'2024'!$K$3:$K$908,"/") -> 43 | AC19: =AB19/AB$20 -> 0.22395833
M20: TOTAL | N20: =SUM(N14:N19) -> 904 | P20: =SUM(P14:P19) -> 292 | R20: =SUM(R14:R19) -> 98 | T20: =SUM(T14:T19) -> 110 | V20: =SUM(V14:V19) -> 107 | X20: =SUM(X14:X19) -> 55 | Z20: =SUM(Z14:Z19) -> 50 | AB20: =SUM(AB14:AB19) -> 192
A25: 2 | B25: KLASIFIKASI ANGGOTA BERDASARKAN PROFESI
B27: PROFESI | C27: JUMLAH | D27: % | E27: PBL | F27: KRK | G27: JBR | H27: BWI | I27: MJK | J27: MGL | K27: PML
B28: Wiraswasta | C28: =COUNTIF('Data Angt'!$H$5:$H$5809,B28) -> 1369 | D28: =C28/$C$42 -> 0.23583118 | E28: =COUNTIFS('Data Angt'!$C$5:$C$5809,E$27,'Data Angt'!$H$5:$H$5809,$B28) -> 544 | F28: =COUNTIFS('Data Angt'!$C$5:$C$5809,F$27,'Data Angt'!$H$5:$H$5809,$B28) -> 186 | G28: =COUNTIFS('Data Angt'!$C$5:$C$5809,G$27,'Data Angt'!$H$5:$H$5809,$B28) -> 204 | H28: =COUNTIFS('Data Angt'!$C$5:$C$5809,H$27,'Data Angt'!$H$5:$H$5809,$B28) -> 165 | I28: =COUNTIFS('Data Angt'!$C$5:$C$5809,I$27,'Data Angt'!$H$5:$H$5809,$B28) -> 114 | J28: =COUNTIFS('Data Angt'!$C$5:$C$5809,J$27,'Data Angt'!$H$5:$H$5809,$B28) -> 149 | K28: =COUNTIFS('Data Angt'!$C$5:$C$5809,K$27,'Data Angt'!$H$5:$H$5809,$B28) -> 7
B29: Karyawan | C29: =COUNTIF('Data Angt'!$H$5:$H$5809,B29) -> 1623 | D29: =C29/$C$42 -> 0.27958656 | E29: =COUNTIFS('Data Angt'!$C$5:$C$5809,E$27,'Data Angt'!$H$5:$H$5809,$B29) -> 728 | F29: =COUNTIFS('Data Angt'!$C$5:$C$5809,F$27,'Data Angt'!$H$5:$H$5809,$B29) -> 174 | G29: =COUNTIFS('Data Angt'!$C$5:$C$5809,G$27,'Data Angt'!$H$5:$H$5809,$B29) -> 264 | H29: =COUNTIFS('Data Angt'!$C$5:$C$5809,H$27,'Data Angt'!$H$5:$H$5809,$B29) -> 145 | I29: =COUNTIFS('Data Angt'!$C$5:$C$5809,I$27,'Data Angt'!$H$5:$H$5809,$B29) -> 80 | J29: =COUNTIFS('Data Angt'!$C$5:$C$5809,J$27,'Data Angt'!$H$5:$H$5809,$B29) -> 156 | K29: =COUNTIFS('Data Angt'!$C$5:$C$5809,K$27,'Data Angt'!$H$5:$H$5809,$B29) -> 76
B30: Tenaga Pengajar | C30: =COUNTIF('Data Angt'!$H$5:$H$5809,B30) -> 452 | D30: =C30/$C$42 -> 0.07786391 | E30: =COUNTIFS('Data Angt'!$C$5:$C$5809,E$27,'Data Angt'!$H$5:$H$5809,$B30) -> 177 | F30: =COUNTIFS('Data Angt'!$C$5:$C$5809,F$27,'Data Angt'!$H$5:$H$5809,$B30) -> 76 | G30: =COUNTIFS('Data Angt'!$C$5:$C$5809,G$27,'Data Angt'!$H$5:$H$5809,$B30) -> 101 | H30: =COUNTIFS('Data Angt'!$C$5:$C$5809,H$27,'Data Angt'!$H$5:$H$5809,$B30) -> 40 | I30: =COUNTIFS('Data Angt'!$C$5:$C$5809,I$27,'Data Angt'!$H$5:$H$5809,$B30) -> 29 | J30: =COUNTIFS('Data Angt'!$C$5:$C$5809,J$27,'Data Angt'!$H$5:$H$5809,$B30) -> 25 | K30: =COUNTIFS('Data Angt'!$C$5:$C$5809,K$27,'Data Angt'!$H$5:$H$5809,$B30) -> 4
B31: Aparatur/Pejabat Negara | C31: =COUNTIF('Data Angt'!$H$5:$H$5809,B31) -> 243 | D31: =C31/$C$42 -> 0.041860465 | E31: =COUNTIFS('Data Angt'!$C$5:$C$5809,E$27,'Data Angt'!$H$5:$H$5809,$B31) -> 160 | F31: =COUNTIFS('Data Angt'!$C$5:$C$5809,F$27,'Data Angt'!$H$5:$H$5809,$B31) -> 30 | G31: =COUNTIFS('Data Angt'!$C$5:$C$5809,G$27,'Data Angt'!$H$5:$H$5809,$B31) -> 16 | H31: =COUNTIFS('Data Angt'!$C$5:$C$5809,H$27,'Data Angt'!$H$5:$H$5809,$B31) -> 15 | I31: =COUNTIFS('Data Angt'!$C$5:$C$5809,I$27,'Data Angt'!$H$5:$H$5809,$B31) -> 7 | J31: =COUNTIFS('Data Angt'!$C$5:$C$5809,J$27,'Data Angt'!$H$5:$H$5809,$B31) -> 9 | K31: =COUNTIFS('Data Angt'!$C$5:$C$5809,K$27,'Data Angt'!$H$5:$H$5809,$B31) -> 6
B32: Pelajar/Mahasiswa | C32: =COUNTIF('Data Angt'!$H$5:$H$5809,B32) -> 235 | D32: =C32/$C$42 -> 0.040482343 | E32: =COUNTIFS('Data Angt'!$C$5:$C$5809,E$27,'Data Angt'!$H$5:$H$5809,$B32) -> 96 | F32: =COUNTIFS('Data Angt'!$C$5:$C$5809,F$27,'Data Angt'!$H$5:$H$5809,$B32) -> 18 | G32: =COUNTIFS('Data Angt'!$C$5:$C$5809,G$27,'Data Angt'!$H$5:$H$5809,$B32) -> 59 | H32: =COUNTIFS('Data Angt'!$C$5:$C$5809,H$27,'Data Angt'!$H$5:$H$5809,$B32) -> 14 | I32: =COUNTIFS('Data Angt'!$C$5:$C$5809,I$27,'Data Angt'!$H$5:$H$5809,$B32) -> 30 | J32: =COUNTIFS('Data Angt'!$C$5:$C$5809,J$27,'Data Angt'!$H$5:$H$5809,$B32) -> 18 | K32: =COUNTIFS('Data Angt'!$C$5:$C$5809,K$27,'Data Angt'!$H$5:$H$5809,$B32) -> 0
B33: Pemuka Agama | C33: =COUNTIF('Data Angt'!$H$5:$H$5809,B33) -> 53 | D33: =C33/$C$42 -> 0.0091300603 | E33: =COUNTIFS('Data Angt'!$C$5:$C$5809,E$27,'Data Angt'!$H$5:$H$5809,$B33) -> 33 | F33: =COUNTIFS('Data Angt'!$C$5:$C$5809,F$27,'Data Angt'!$H$5:$H$5809,$B33) -> 0 | G33: =COUNTIFS('Data Angt'!$C$5:$C$5809,G$27,'Data Angt'!$H$5:$H$5809,$B33) -> 10 | H33: =COUNTIFS('Data Angt'!$C$5:$C$5809,H$27,'Data Angt'!$H$5:$H$5809,$B33) -> 2 | I33: =COUNTIFS('Data Angt'!$C$5:$C$5809,I$27,'Data Angt'!$H$5:$H$5809,$B33) -> 1 | J33: =COUNTIFS('Data Angt'!$C$5:$C$5809,J$27,'Data Angt'!$H$5:$H$5809,$B33) -> 6 | K33: =COUNTIFS('Data Angt'!$C$5:$C$5809,K$27,'Data Angt'!$H$5:$H$5809,$B33) -> 1
B34: Mengurus Rumah Tangga | C34: =COUNTIF('Data Angt'!$H$5:$H$5809,B34) -> 848 | D34: =C34/$C$42 -> 0.14608096 | E34: =COUNTIFS('Data Angt'!$C$5:$C$5809,E$27,'Data Angt'!$H$5:$H$5809,$B34) -> 361 | F34: =COUNTIFS('Data Angt'!$C$5:$C$5809,F$27,'Data Angt'!$H$5:$H$5809,$B34) -> 71 | G34: =COUNTIFS('Data Angt'!$C$5:$C$5809,G$27,'Data Angt'!$H$5:$H$5809,$B34) -> 206 | H34: =COUNTIFS('Data Angt'!$C$5:$C$5809,H$27,'Data Angt'!$H$5:$H$5809,$B34) -> 50 | I34: =COUNTIFS('Data Angt'!$C$5:$C$5809,I$27,'Data Angt'!$H$5:$H$5809,$B34) -> 41 | J34: =COUNTIFS('Data Angt'!$C$5:$C$5809,J$27,'Data Angt'!$H$5:$H$5809,$B34) -> 66 | K34: =COUNTIFS('Data Angt'!$C$5:$C$5809,K$27,'Data Angt'!$H$5:$H$5809,$B34) -> 53
B35: Tenaga Ahli | C35: =COUNTIF('Data Angt'!$H$5:$H$5809,B35) -> 20 | D35: =C35/$C$42 -> 0.0034453058 | E35: =COUNTIFS('Data Angt'!$C$5:$C$5809,E$27,'Data Angt'!$H$5:$H$5809,$B35) -> 13 | F35: =COUNTIFS('Data Angt'!$C$5:$C$5809,F$27,'Data Angt'!$H$5:$H$5809,$B35) -> 3 | G35: =COUNTIFS('Data Angt'!$C$5:$C$5809,G$27,'Data Angt'!$H$5:$H$5809,$B35) -> 3 | H35: =COUNTIFS('Data Angt'!$C$5:$C$5809,H$27,'Data Angt'!$H$5:$H$5809,$B35) -> 1 | I35: =COUNTIFS('Data Angt'!$C$5:$C$5809,I$27,'Data Angt'!$H$5:$H$5809,$B35) -> 0 | J35: =COUNTIFS('Data Angt'!$C$5:$C$5809,J$27,'Data Angt'!$H$5:$H$5809,$B35) -> 0 | K35: =COUNTIFS('Data Angt'!$C$5:$C$5809,K$27,'Data Angt'!$H$5:$H$5809,$B35) -> 0
B36: Tenaga Medis | C36: =COUNTIF('Data Angt'!$H$5:$H$5809,B36) -> 56 | D36: =C36/$C$42 -> 0.0096468562 | E36: =COUNTIFS('Data Angt'!$C$5:$C$5809,E$27,'Data Angt'!$H$5:$H$5809,$B36) -> 20 | F36: =COUNTIFS('Data Angt'!$C$5:$C$5809,F$27,'Data Angt'!$H$5:$H$5809,$B36) -> 5 | G36: =COUNTIFS('Data Angt'!$C$5:$C$5809,G$27,'Data Angt'!$H$5:$H$5809,$B36) -> 15 | H36: =COUNTIFS('Data Angt'!$C$5:$C$5809,H$27,'Data Angt'!$H$5:$H$5809,$B36) -> 3 | I36: =COUNTIFS('Data Angt'!$C$5:$C$5809,I$27,'Data Angt'!$H$5:$H$5809,$B36) -> 7 | J36: =COUNTIFS('Data Angt'!$C$5:$C$5809,J$27,'Data Angt'!$H$5:$H$5809,$B36) -> 5 | K36: =COUNTIFS('Data Angt'!$C$5:$C$5809,K$27,'Data Angt'!$H$5:$H$5809,$B36) -> 1
B37: Petani/Pekebun/Nelayan | C37: =COUNTIF('Data Angt'!$H$5:$H$5809,B37) -> 52 | D37: =C37/$C$42 -> 0.008957795 | E37: =COUNTIFS('Data Angt'!$C$5:$C$5809,E$27,'Data Angt'!$H$5:$H$5809,$B37) -> 6 | F37: =COUNTIFS('Data Angt'!$C$5:$C$5809,F$27,'Data Angt'!$H$5:$H$5809,$B37) -> 24 | G37: =COUNTIFS('Data Angt'!$C$5:$C$5809,G$27,'Data Angt'!$H$5:$H$5809,$B37) -> 8 | H37: =COUNTIFS('Data Angt'!$C$5:$C$5809,H$27,'Data Angt'!$H$5:$H$5809,$B37) -> 4 | I37: =COUNTIFS('Data Angt'!$C$5:$C$5809,I$27,'Data Angt'!$H$5:$H$5809,$B37) -> 0 | J37: =COUNTIFS('Data Angt'!$C$5:$C$5809,J$27,'Data Angt'!$H$5:$H$5809,$B37) -> 10 | K37: =COUNTIFS('Data Angt'!$C$5:$C$5809,K$27,'Data Angt'!$H$5:$H$5809,$B37) -> 0
B38: Pensiunan | C38: =COUNTIF('Data Angt'!$H$5:$H$5809,B38) -> 224 | D38: =C38/$C$42 -> 0.038587425 | E38: =COUNTIFS('Data Angt'!$C$5:$C$5809,E$27,'Data Angt'!$H$5:$H$5809,$B38) -> 104 | F38: =COUNTIFS('Data Angt'!$C$5:$C$5809,F$27,'Data Angt'!$H$5:$H$5809,$B38) -> 28 | G38: =COUNTIFS('Data Angt'!$C$5:$C$5809,G$27,'Data Angt'!$H$5:$H$5809,$B38) -> 38 | H38: =COUNTIFS('Data Angt'!$C$5:$C$5809,H$27,'Data Angt'!$H$5:$H$5809,$B38) -> 19 | I38: =COUNTIFS('Data Angt'!$C$5:$C$5809,I$27,'Data Angt'!$H$5:$H$5809,$B38) -> 17 | J38: =COUNTIFS('Data Angt'!$C$5:$C$5809,J$27,'Data Angt'!$H$5:$H$5809,$B38) -> 18 | K38: =COUNTIFS('Data Angt'!$C$5:$C$5809,K$27,'Data Angt'!$H$5:$H$5809,$B38) -> 0
B39: Belum/Tidak Bekerja | C39: =COUNTIF('Data Angt'!$H$5:$H$5809,B39) -> 86 | D39: =C39/$C$42 -> 0.014814815 | E39: =COUNTIFS('Data Angt'!$C$5:$C$5809,E$27,'Data Angt'!$H$5:$H$5809,$B39) -> 33 | F39: =COUNTIFS('Data Angt'!$C$5:$C$5809,F$27,'Data Angt'!$H$5:$H$5809,$B39) -> 11 | G39: =COUNTIFS('Data Angt'!$C$5:$C$5809,G$27,'Data Angt'!$H$5:$H$5809,$B39) -> 3 | H39: =COUNTIFS('Data Angt'!$C$5:$C$5809,H$27,'Data Angt'!$H$5:$H$5809,$B39) -> 8 | I39: =COUNTIFS('Data Angt'!$C$5:$C$5809,I$27,'Data Angt'!$H$5:$H$5809,$B39) -> 17 | J39: =COUNTIFS('Data Angt'!$C$5:$C$5809,J$27,'Data Angt'!$H$5:$H$5809,$B39) -> 14 | K39: =COUNTIFS('Data Angt'!$C$5:$C$5809,K$27,'Data Angt'!$H$5:$H$5809,$B39) -> 0
B40: Lain-lain | C40: =COUNTIF('Data Angt'!$H$5:$H$5809,B40) -> 246 | D40: =C40/$C$42 -> 0.042377261 | E40: =COUNTIFS('Data Angt'!$C$5:$C$5809,E$27,'Data Angt'!$H$5:$H$5809,$B40) -> 146 | F40: =COUNTIFS('Data Angt'!$C$5:$C$5809,F$27,'Data Angt'!$H$5:$H$5809,$B40) -> 22 | G40: =COUNTIFS('Data Angt'!$C$5:$C$5809,G$27,'Data Angt'!$H$5:$H$5809,$B40) -> 16 | H40: =COUNTIFS('Data Angt'!$C$5:$C$5809,H$27,'Data Angt'!$H$5:$H$5809,$B40) -> 13 | I40: =COUNTIFS('Data Angt'!$C$5:$C$5809,I$27,'Data Angt'!$H$5:$H$5809,$B40) -> 12 | J40: =COUNTIFS('Data Angt'!$C$5:$C$5809,J$27,'Data Angt'!$H$5:$H$5809,$B40) -> 37 | K40: =COUNTIFS('Data Angt'!$C$5:$C$5809,K$27,'Data Angt'!$H$5:$H$5809,$B40) -> 0
B41: Kosong | C41: =COUNTIF('Data Angt'!$H$5:$H$5809,"") -> 298 | D41: =C41/$C$42 -> 0.051335056 | E41: =COUNTIFS('Data Angt'!$C$5:$C$5809,E$27,'Data Angt'!$H$5:$H$5809,"") -> 195 | F41: =COUNTIFS('Data Angt'!$C$5:$C$5809,F$27,'Data Angt'!$H$5:$H$5809,"") -> 49 | G41: =COUNTIFS('Data Angt'!$C$5:$C$5809,G$27,'Data Angt'!$H$5:$H$5809,"") -> 1 | H41: =COUNTIFS('Data Angt'!$C$5:$C$5809,H$27,'Data Angt'!$H$5:$H$5809,"") -> 1 | I41: =COUNTIFS('Data Angt'!$C$5:$C$5809,I$27,'Data Angt'!$H$5:$H$5809,"") -> 1 | J41: =COUNTIFS('Data Angt'!$C$5:$C$5809,J$27,'Data Angt'!$H$5:$H$5809,"") -> 9 | K41: =COUNTIFS('Data Angt'!$C$5:$C$5809,K$27,'Data Angt'!$H$5:$H$5809,"") -> 42
B42: JUMLAH | C42: =SUM(C28:C41) -> 5805 | D42: =C42/$C$42 -> 1 | E42: =SUM(E28:E41) -> 2616 | F42: =SUM(F28:F41) -> 697 | G42: =SUM(G28:G41) -> 944 | H42: =SUM(H28:H41) -> 480 | I42: =SUM(I28:I41) -> 356 | J42: =SUM(J28:J41) -> 522 | K42: =SUM(K28:K41) -> 190
A44: 3 | B44: KLASIFIKASI PROFESI DAN USIA ANGGOTA
B46: Usia | C46: Profesi | D46: Jumlah | E46: % | F46: PBL | G46: KRK | H46: JBR | I46: BWI | J46: MJK | K46: MGL | L46: PML
B47: <24 Th | C47: Wiraswasta | D47: =COUNTIFS('Data Angt'!$F$5:$F$5809,"<24",'Data Angt'!$H$5:$H$5809,C47) -> 18 | E47: =D47/$C$42 -> 0.0031007752 | F47: =COUNTIFS('Data Angt'!$C$5:$C$5809,F$46,'Data Angt'!$F$5:$F$5809,"<24",'Data Angt'!$H$5:$H$5809,$C47) -> 3 | G47: =COUNTIFS('Data Angt'!$C$5:$C$5809,G$46,'Data Angt'!$F$5:$F$5809,"<24",'Data Angt'!$H$5:$H$5809,$C47) -> 2 | H47: =COUNTIFS('Data Angt'!$C$5:$C$5809,H$46,'Data Angt'!$F$5:$F$5809,"<24",'Data Angt'!$H$5:$H$5809,$C47) -> 3 | I47: =COUNTIFS('Data Angt'!$C$5:$C$5809,I$46,'Data Angt'!$F$5:$F$5809,"<24",'Data Angt'!$H$5:$H$5809,$C47) -> 8 | J47: =COUNTIFS('Data Angt'!$C$5:$C$5809,J$46,'Data Angt'!$F$5:$F$5809,"<24",'Data Angt'!$H$5:$H$5809,$C47) -> 0 | K47: =COUNTIFS('Data Angt'!$C$5:$C$5809,K$46,'Data Angt'!$F$5:$F$5809,"<24",'Data Angt'!$H$5:$H$5809,$C47) -> 2 | L47: =COUNTIFS('Data Angt'!$C$5:$C$5809,L$46,'Data Angt'!$F$5:$F$5809,"<24",'Data Angt'!$H$5:$H$5809,$C47) -> 0
C48: Karyawan | D48: =COUNTIFS('Data Angt'!$F$5:$F$5809,"<24",'Data Angt'!$H$5:$H$5809,C48) -> 81 | E48: =D48/$C$42 -> 0.013953488 | F48: =COUNTIFS('Data Angt'!$C$5:$C$5809,F$46,'Data Angt'!$F$5:$F$5809,"<24",'Data Angt'!$H$5:$H$5809,$C48) -> 57 | G48: =COUNTIFS('Data Angt'!$C$5:$C$5809,G$46,'Data Angt'!$F$5:$F$5809,"<24",'Data Angt'!$H$5:$H$5809,$C48) -> 3 | H48: =COUNTIFS('Data Angt'!$C$5:$C$5809,H$46,'Data Angt'!$F$5:$F$5809,"<24",'Data Angt'!$H$5:$H$5809,$C48) -> 2 | I48: =COUNTIFS('Data Angt'!$C$5:$C$5809,I$46,'Data Angt'!$F$5:$F$5809,"<24",'Data Angt'!$H$5:$H$5809,$C48) -> 11 | J48: =COUNTIFS('Data Angt'!$C$5:$C$5809,J$46,'Data Angt'!$F$5:$F$5809,"<24",'Data Angt'!$H$5:$H$5809,$C48) -> 4 | K48: =COUNTIFS('Data Angt'!$C$5:$C$5809,K$46,'Data Angt'!$F$5:$F$5809,"<24",'Data Angt'!$H$5:$H$5809,$C48) -> 4 | L48: =COUNTIFS('Data Angt'!$C$5:$C$5809,L$46,'Data Angt'!$F$5:$F$5809,"<24",'Data Angt'!$H$5:$H$5809,$C48) -> 0
C49: Tenaga Pengajar | D49: =COUNTIFS('Data Angt'!$F$5:$F$5809,"<24",'Data Angt'!$H$5:$H$5809,C49) -> 2 | E49: =D49/$C$42 -> 0.00034453058 | F49: =COUNTIFS('Data Angt'!$C$5:$C$5809,F$46,'Data Angt'!$F$5:$F$5809,"<24",'Data Angt'!$H$5:$H$5809,$C49) -> 1 | G49: =COUNTIFS('Data Angt'!$C$5:$C$5809,G$46,'Data Angt'!$F$5:$F$5809,"<24",'Data Angt'!$H$5:$H$5809,$C49) -> 0 | H49: =COUNTIFS('Data Angt'!$C$5:$C$5809,H$46,'Data Angt'!$F$5:$F$5809,"<24",'Data Angt'!$H$5:$H$5809,$C49) -> 0 | I49: =COUNTIFS('Data Angt'!$C$5:$C$5809,I$46,'Data Angt'!$F$5:$F$5809,"<24",'Data Angt'!$H$5:$H$5809,$C49) -> 1 | J49: =COUNTIFS('Data Angt'!$C$5:$C$5809,J$46,'Data Angt'!$F$5:$F$5809,"<24",'Data Angt'!$H$5:$H$5809,$C49) -> 0 | K49: =COUNTIFS('Data Angt'!$C$5:$C$5809,K$46,'Data Angt'!$F$5:$F$5809,"<24",'Data Angt'!$H$5:$H$5809,$C49) -> 0 | L49: =COUNTIFS('Data Angt'!$C$5:$C$5809,L$46,'Data Angt'!$F$5:$F$5809,"<24",'Data Angt'!$H$5:$H$5809,$C49) -> 0
C50: Aparatur/Pejabat Negara | D50: =COUNTIFS('Data Angt'!$F$5:$F$5809,"<24",'Data Angt'!$H$5:$H$5809,C50) -> 0 | E50: =D50/$C$42 -> 0 | F50: =COUNTIFS('Data Angt'!$C$5:$C$5809,F$46,'Data Angt'!$F$5:$F$5809,"<24",'Data Angt'!$H$5:$H$5809,$C50) -> 0 | G50: =COUNTIFS('Data Angt'!$C$5:$C$5809,G$46,'Data Angt'!$F$5:$F$5809,"<24",'Data Angt'!$H$5:$H$5809,$C50) -> 0 | H50: =COUNTIFS('Data Angt'!$C$5:$C$5809,H$46,'Data Angt'!$F$5:$F$5809,"<24",'Data Angt'!$H$5:$H$5809,$C50) -> 0 | I50: =COUNTIFS('Data Angt'!$C$5:$C$5809,I$46,'Data Angt'!$F$5:$F$5809,"<24",'Data Angt'!$H$5:$H$5809,$C50) -> 0 | J50: =COUNTIFS('Data Angt'!$C$5:$C$5809,J$46,'Data Angt'!$F$5:$F$5809,"<24",'Data Angt'!$H$5:$H$5809,$C50) -> 0 | K50: =COUNTIFS('Data Angt'!$C$5:$C$5809,K$46,'Data Angt'!$F$5:$F$5809,"<24",'Data Angt'!$H$5:$H$5809,$C50) -> 0 | L50: =COUNTIFS('Data Angt'!$C$5:$C$5809,L$46,'Data Angt'!$F$5:$F$5809,"<24",'Data Angt'!$H$5:$H$5809,$C50) -> 0
C51: Pelajar/Mahasiswa | D51: =COUNTIFS('Data Angt'!$F$5:$F$5809,"<24",'Data Angt'!$H$5:$H$5809,C51) -> 180 | E51: =D51/$C$42 -> 0.031007752 | F51: =COUNTIFS('Data Angt'!$C$5:$C$5809,F$46,'Data Angt'!$F$5:$F$5809,"<24",'Data Angt'!$H$5:$H$5809,$C51) -> 70 | G51: =COUNTIFS('Data Angt'!$C$5:$C$5809,G$46,'Data Angt'!$F$5:$F$5809,"<24",'Data Angt'!$H$5:$H$5809,$C51) -> 14 | H51: =COUNTIFS('Data Angt'!$C$5:$C$5809,H$46,'Data Angt'!$F$5:$F$5809,"<24",'Data Angt'!$H$5:$H$5809,$C51) -> 44 | I51: =COUNTIFS('Data Angt'!$C$5:$C$5809,I$46,'Data Angt'!$F$5:$F$5809,"<24",'Data Angt'!$H$5:$H$5809,$C51) -> 12 | J51: =COUNTIFS('Data Angt'!$C$5:$C$5809,J$46,'Data Angt'!$F$5:$F$5809,"<24",'Data Angt'!$H$5:$H$5809,$C51) -> 27 | K51: =COUNTIFS('Data Angt'!$C$5:$C$5809,K$46,'Data Angt'!$F$5:$F$5809,"<24",'Data Angt'!$H$5:$H$5809,$C51) -> 13 | L51: =COUNTIFS('Data Angt'!$C$5:$C$5809,L$46,'Data Angt'!$F$5:$F$5809,"<24",'Data Angt'!$H$5:$H$5809,$C51) -> 0
C52: Pemuka Agama | D52: =COUNTIFS('Data Angt'!$F$5:$F$5809,"<24",'Data Angt'!$H$5:$H$5809,C52) -> 0 | E52: =D52/$C$42 -> 0 | F52: =COUNTIFS('Data Angt'!$C$5:$C$5809,F$46,'Data Angt'!$F$5:$F$5809,"<24",'Data Angt'!$H$5:$H$5809,$C52) -> 0 | G52: =COUNTIFS('Data Angt'!$C$5:$C$5809,G$46,'Data Angt'!$F$5:$F$5809,"<24",'Data Angt'!$H$5:$H$5809,$C52) -> 0 | H52: =COUNTIFS('Data Angt'!$C$5:$C$5809,H$46,'Data Angt'!$F$5:$F$5809,"<24",'Data Angt'!$H$5:$H$5809,$C52) -> 0 | I52: =COUNTIFS('Data Angt'!$C$5:$C$5809,I$46,'Data Angt'!$F$5:$F$5809,"<24",'Data Angt'!$H$5:$H$5809,$C52) -> 0 | J52: =COUNTIFS('Data Angt'!$C$5:$C$5809,J$46,'Data Angt'!$F$5:$F$5809,"<24",'Data Angt'!$H$5:$H$5809,$C52) -> 0 | K52: =COUNTIFS('Data Angt'!$C$5:$C$5809,K$46,'Data Angt'!$F$5:$F$5809,"<24",'Data Angt'!$H$5:$H$5809,$C52) -> 0 | L52: =COUNTIFS('Data Angt'!$C$5:$C$5809,L$46,'Data Angt'!$F$5:$F$5809,"<24",'Data Angt'!$H$5:$H$5809,$C52) -> 0
C53: Mengurus Rumah Tangga | D53: =COUNTIFS('Data Angt'!$F$5:$F$5809,"<24",'Data Angt'!$H$5:$H$5809,C53) -> 6 | E53: =D53/$C$42 -> 0.0010335917 | F53: =COUNTIFS('Data Angt'!$C$5:$C$5809,F$46,'Data Angt'!$F$5:$F$5809,"<24",'Data Angt'!$H$5:$H$5809,$C53) -> 1 | G53: =COUNTIFS('Data Angt'!$C$5:$C$5809,G$46,'Data Angt'!$F$5:$F$5809,"<24",'Data Angt'!$H$5:$H$5809,$C53) -> 2 | H53: =COUNTIFS('Data Angt'!$C$5:$C$5809,H$46,'Data Angt'!$F$5:$F$5809,"<24",'Data Angt'!$H$5:$H$5809,$C53) -> 0 | I53: =COUNTIFS('Data Angt'!$C$5:$C$5809,I$46,'Data Angt'!$F$5:$F$5809,"<24",'Data Angt'!$H$5:$H$5809,$C53) -> 1 | J53: =COUNTIFS('Data Angt'!$C$5:$C$5809,J$46,'Data Angt'!$F$5:$F$5809,"<24",'Data Angt'!$H$5:$H$5809,$C53) -> 1 | K53: =COUNTIFS('Data Angt'!$C$5:$C$5809,K$46,'Data Angt'!$F$5:$F$5809,"<24",'Data Angt'!$H$5:$H$5809,$C53) -> 1 | L53: =COUNTIFS('Data Angt'!$C$5:$C$5809,L$46,'Data Angt'!$F$5:$F$5809,"<24",'Data Angt'!$H$5:$H$5809,$C53) -> 0
C54: Tenaga Ahli | D54: =COUNTIFS('Data Angt'!$F$5:$F$5809,"<24",'Data Angt'!$H$5:$H$5809,C54) -> 0 | E54: =D54/$C$42 -> 0 | F54: =COUNTIFS('Data Angt'!$C$5:$C$5809,F$46,'Data Angt'!$F$5:$F$5809,"<24",'Data Angt'!$H$5:$H$5809,$C54) -> 0 | G54: =COUNTIFS('Data Angt'!$C$5:$C$5809,G$46,'Data Angt'!$F$5:$F$5809,"<24",'Data Angt'!$H$5:$H$5809,$C54) -> 0 | H54: =COUNTIFS('Data Angt'!$C$5:$C$5809,H$46,'Data Angt'!$F$5:$F$5809,"<24",'Data Angt'!$H$5:$H$5809,$C54) -> 0 | I54: =COUNTIFS('Data Angt'!$C$5:$C$5809,I$46,'Data Angt'!$F$5:$F$5809,"<24",'Data Angt'!$H$5:$H$5809,$C54) -> 0 | J54: =COUNTIFS('Data Angt'!$C$5:$C$5809,J$46,'Data Angt'!$F$5:$F$5809,"<24",'Data Angt'!$H$5:$H$5809,$C54) -> 0 | K54: =COUNTIFS('Data Angt'!$C$5:$C$5809,K$46,'Data Angt'!$F$5:$F$5809,"<24",'Data Angt'!$H$5:$H$5809,$C54) -> 0 | L54: =COUNTIFS('Data Angt'!$C$5:$C$5809,L$46,'Data Angt'!$F$5:$F$5809,"<24",'Data Angt'!$H$5:$H$5809,$C54) -> 0
C55: Tenaga Medis | D55: =COUNTIFS('Data Angt'!$F$5:$F$5809,"<24",'Data Angt'!$H$5:$H$5809,C55) -> 2 | E55: =D55/$C$42 -> 0.00034453058 | F55: =COUNTIFS('Data Angt'!$C$5:$C$5809,F$46,'Data Angt'!$F$5:$F$5809,"<24",'Data Angt'!$H$5:$H$5809,$C55) -> 1 | G55: =COUNTIFS('Data Angt'!$C$5:$C$5809,G$46,'Data Angt'!$F$5:$F$5809,"<24",'Data Angt'!$H$5:$H$5809,$C55) -> 0 | H55: =COUNTIFS('Data Angt'!$C$5:$C$5809,H$46,'Data Angt'!$F$5:$F$5809,"<24",'Data Angt'!$H$5:$H$5809,$C55) -> 1 | I55: =COUNTIFS('Data Angt'!$C$5:$C$5809,I$46,'Data Angt'!$F$5:$F$5809,"<24",'Data Angt'!$H$5:$H$5809,$C55) -> 0 | J55: =COUNTIFS('Data Angt'!$C$5:$C$5809,J$46,'Data Angt'!$F$5:$F$5809,"<24",'Data Angt'!$H$5:$H$5809,$C55) -> 0 | K55: =COUNTIFS('Data Angt'!$C$5:$C$5809,K$46,'Data Angt'!$F$5:$F$5809,"<24",'Data Angt'!$H$5:$H$5809,$C55) -> 0 | L55: =COUNTIFS('Data Angt'!$C$5:$C$5809,L$46,'Data Angt'!$F$5:$F$5809,"<24",'Data Angt'!$H$5:$H$5809,$C55) -> 0
C56: Petani/Pekebun/Nelayan | D56: =COUNTIFS('Data Angt'!$F$5:$F$5809,"<24",'Data Angt'!$H$5:$H$5809,C56) -> 0 | E56: =D56/$C$42 -> 0 | F56: =COUNTIFS('Data Angt'!$C$5:$C$5809,F$46,'Data Angt'!$F$5:$F$5809,"<24",'Data Angt'!$H$5:$H$5809,$C56) -> 0 | G56: =COUNTIFS('Data Angt'!$C$5:$C$5809,G$46,'Data Angt'!$F$5:$F$5809,"<24",'Data Angt'!$H$5:$H$5809,$C56) -> 0 | H56: =COUNTIFS('Data Angt'!$C$5:$C$5809,H$46,'Data Angt'!$F$5:$F$5809,"<24",'Data Angt'!$H$5:$H$5809,$C56) -> 0 | I56: =COUNTIFS('Data Angt'!$C$5:$C$5809,I$46,'Data Angt'!$F$5:$F$5809,"<24",'Data Angt'!$H$5:$H$5809,$C56) -> 0 | J56: =COUNTIFS('Data Angt'!$C$5:$C$5809,J$46,'Data Angt'!$F$5:$F$5809,"<24",'Data Angt'!$H$5:$H$5809,$C56) -> 0 | K56: =COUNTIFS('Data Angt'!$C$5:$C$5809,K$46,'Data Angt'!$F$5:$F$5809,"<24",'Data Angt'!$H$5:$H$5809,$C56) -> 0 | L56: =COUNTIFS('Data Angt'!$C$5:$C$5809,L$46,'Data Angt'!$F$5:$F$5809,"<24",'Data Angt'!$H$5:$H$5809,$C56) -> 0
C57: Pensiunan | D57: =COUNTIFS('Data Angt'!$F$5:$F$5809,"<24",'Data Angt'!$H$5:$H$5809,C57) -> 0 | E57: =D57/$C$42 -> 0 | F57: =COUNTIFS('Data Angt'!$C$5:$C$5809,F$46,'Data Angt'!$F$5:$F$5809,"<24",'Data Angt'!$H$5:$H$5809,$C57) -> 0 | G57: =COUNTIFS('Data Angt'!$C$5:$C$5809,G$46,'Data Angt'!$F$5:$F$5809,"<24",'Data Angt'!$H$5:$H$5809,$C57) -> 0 | H57: =COUNTIFS('Data Angt'!$C$5:$C$5809,H$46,'Data Angt'!$F$5:$F$5809,"<24",'Data Angt'!$H$5:$H$5809,$C57) -> 0 | I57: =COUNTIFS('Data Angt'!$C$5:$C$5809,I$46,'Data Angt'!$F$5:$F$5809,"<24",'Data Angt'!$H$5:$H$5809,$C57) -> 0 | J57: =COUNTIFS('Data Angt'!$C$5:$C$5809,J$46,'Data Angt'!$F$5:$F$5809,"<24",'Data Angt'!$H$5:$H$5809,$C57) -> 0 | K57: =COUNTIFS('Data Angt'!$C$5:$C$5809,K$46,'Data Angt'!$F$5:$F$5809,"<24",'Data Angt'!$H$5:$H$5809,$C57) -> 0 | L57: =COUNTIFS('Data Angt'!$C$5:$C$5809,L$46,'Data Angt'!$F$5:$F$5809,"<24",'Data Angt'!$H$5:$H$5809,$C57) -> 0
C58: Belum/Tidak Bekerja | D58: =COUNTIFS('Data Angt'!$F$5:$F$5809,"<24",'Data Angt'!$H$5:$H$5809,C58) -> 16 | E58: =D58/$C$42 -> 0.0027562446 | F58: =COUNTIFS('Data Angt'!$C$5:$C$5809,F$46,'Data Angt'!$F$5:$F$5809,"<24",'Data Angt'!$H$5:$H$5809,$C58) -> 5 | G58: =COUNTIFS('Data Angt'!$C$5:$C$5809,G$46,'Data Angt'!$F$5:$F$5809,"<24",'Data Angt'!$H$5:$H$5809,$C58) -> 1 | H58: =COUNTIFS('Data Angt'!$C$5:$C$5809,H$46,'Data Angt'!$F$5:$F$5809,"<24",'Data Angt'!$H$5:$H$5809,$C58) -> 0 | I58: =COUNTIFS('Data Angt'!$C$5:$C$5809,I$46,'Data Angt'!$F$5:$F$5809,"<24",'Data Angt'!$H$5:$H$5809,$C58) -> 6 | J58: =COUNTIFS('Data Angt'!$C$5:$C$5809,J$46,'Data Angt'!$F$5:$F$5809,"<24",'Data Angt'!$H$5:$H$5809,$C58) -> 2 | K58: =COUNTIFS('Data Angt'!$C$5:$C$5809,K$46,'Data Angt'!$F$5:$F$5809,"<24",'Data Angt'!$H$5:$H$5809,$C58) -> 2 | L58: =COUNTIFS('Data Angt'!$C$5:$C$5809,L$46,'Data Angt'!$F$5:$F$5809,"<24",'Data Angt'!$H$5:$H$5809,$C58) -> 0
C59: Lain-lain | D59: =COUNTIFS('Data Angt'!$F$5:$F$5809,"<24",'Data Angt'!$H$5:$H$5809,C59) -> 3 | E59: =D59/$C$42 -> 0.00051679587 | F59: =COUNTIFS('Data Angt'!$C$5:$C$5809,F$46,'Data Angt'!$F$5:$F$5809,"<24",'Data Angt'!$H$5:$H$5809,$C59) -> 1 | G59: =COUNTIFS('Data Angt'!$C$5:$C$5809,G$46,'Data Angt'!$F$5:$F$5809,"<24",'Data Angt'!$H$5:$H$5809,$C59) -> 1 | H59: =COUNTIFS('Data Angt'!$C$5:$C$5809,H$46,'Data Angt'!$F$5:$F$5809,"<24",'Data Angt'!$H$5:$H$5809,$C59) -> 0 | I59: =COUNTIFS('Data Angt'!$C$5:$C$5809,I$46,'Data Angt'!$F$5:$F$5809,"<24",'Data Angt'!$H$5:$H$5809,$C59) -> 0 | J59: =COUNTIFS('Data Angt'!$C$5:$C$5809,J$46,'Data Angt'!$F$5:$F$5809,"<24",'Data Angt'!$H$5:$H$5809,$C59) -> 0 | K59: =COUNTIFS('Data Angt'!$C$5:$C$5809,K$46,'Data Angt'!$F$5:$F$5809,"<24",'Data Angt'!$H$5:$H$5809,$C59) -> 1 | L59: =COUNTIFS('Data Angt'!$C$5:$C$5809,L$46,'Data Angt'!$F$5:$F$5809,"<24",'Data Angt'!$H$5:$H$5809,$C59) -> 0
C60: Kosong | D60: =COUNTIFS('Data Angt'!$F$5:$F$5809,"<24",'Data Angt'!$H$5:$H$5809,"") -> 34 | E60: =D60/$C$42 -> 0.0058570198 | F60: =COUNTIFS('Data Angt'!$C$5:$C$5809,F$46,'Data Angt'!$F$5:$F$5809,"<24",'Data Angt'!$H$5:$H$5809,"") -> 27 | G60: =COUNTIFS('Data Angt'!$C$5:$C$5809,G$46,'Data Angt'!$F$5:$F$5809,"<24",'Data Angt'!$H$5:$H$5809,"") -> 4 | H60: =COUNTIFS('Data Angt'!$C$5:$C$5809,H$46,'Data Angt'!$F$5:$F$5809,"<24",'Data Angt'!$H$5:$H$5809,"") -> 0 | I60: =COUNTIFS('Data Angt'!$C$5:$C$5809,I$46,'Data Angt'!$F$5:$F$5809,"<24",'Data Angt'!$H$5:$H$5809,"") -> 0 | J60: =COUNTIFS('Data Angt'!$C$5:$C$5809,J$46,'Data Angt'!$F$5:$F$5809,"<24",'Data Angt'!$H$5:$H$5809,"") -> 0 | K60: =COUNTIFS('Data Angt'!$C$5:$C$5809,K$46,'Data Angt'!$F$5:$F$5809,"<24",'Data Angt'!$H$5:$H$5809,"") -> 3 | L60: =COUNTIFS('Data Angt'!$C$5:$C$5809,L$46,'Data Angt'!$F$5:$F$5809,"<24",'Data Angt'!$H$5:$H$5809,"") -> 0
B61: 24 - 35 Th | C61: Wiraswasta | D61: =COUNTIFS('Data Angt'!$F$5:$F$5809,"<=35",'Data Angt'!$H$5:$H$5809,C61)-COUNTIFS('Data Angt'!$F$5:$F$5809,"<24",'Data Angt'!$H$5:$H$5809,C61) -> 170 | E61: =D61/$C$42 -> 0.029285099 | F61: =COUNTIFS('Data Angt'!$C$5:$C$5809,F$46,'Data Angt'!$F$5:$F$5809,"<=35",'Data Angt'!$H$5:$H$5809,$C61)-COUNTIFS('Data Angt'!$C$5:$C$5809,F$46,'Data Angt'!$F$5:$F$5809,"<24",'Data Angt'!$H$5:$H$5809,$C61) -> 72 | G61: =COUNTIFS('Data Angt'!$C$5:$C$5809,G$46,'Data Angt'!$F$5:$F$5809,"<=35",'Data Angt'!$H$5:$H$5809,$C61)-COUNTIFS('Data Angt'!$C$5:$C$5809,G$46,'Data Angt'!$F$5:$F$5809,"<24",'Data Angt'!$H$5:$H$5809,$C61) -> 24 | H61: =COUNTIFS('Data Angt'!$C$5:$C$5809,H$46,'Data Angt'!$F$5:$F$5809,"<=35",'Data Angt'!$H$5:$H$5809,$C61)-COUNTIFS('Data Angt'!$C$5:$C$5809,H$46,'Data Angt'!$F$5:$F$5809,"<24",'Data Angt'!$H$5:$H$5809,$C61) -> 31 | I61: =COUNTIFS('Data Angt'!$C$5:$C$5809,I$46,'Data Angt'!$F$5:$F$5809,"<=35",'Data Angt'!$H$5:$H$5809,$C61)-COUNTIFS('Data Angt'!$C$5:$C$5809,I$46,'Data Angt'!$F$5:$F$5809,"<24",'Data Angt'!$H$5:$H$5809,$C61) -> 24 | J61: =COUNTIFS('Data Angt'!$C$5:$C$5809,J$46,'Data Angt'!$F$5:$F$5809,"<=35",'Data Angt'!$H$5:$H$5809,$C61)-COUNTIFS('Data Angt'!$C$5:$C$5809,J$46,'Data Angt'!$F$5:$F$5809,"<24",'Data Angt'!$H$5:$H$5809,$C61) -> 8 | K61: =COUNTIFS('Data Angt'!$C$5:$C$5809,K$46,'Data Angt'!$F$5:$F$5809,"<=35",'Data Angt'!$H$5:$H$5809,$C61)-COUNTIFS('Data Angt'!$C$5:$C$5809,K$46,'Data Angt'!$F$5:$F$5809,"<24",'Data Angt'!$H$5:$H$5809,$C61) -> 11 | L61: =COUNTIFS('Data Angt'!$C$5:$C$5809,L$46,'Data Angt'!$F$5:$F$5809,"<=35",'Data Angt'!$H$5:$H$5809,$C61)-COUNTIFS('Data Angt'!$C$5:$C$5809,L$46,'Data Angt'!$F$5:$F$5809,"<24",'Data Angt'!$H$5:$H$5809,$C61) -> 0
C62: Karyawan | D62: =COUNTIFS('Data Angt'!$F$5:$F$5809,"<=35",'Data Angt'!$H$5:$H$5809,C62)-COUNTIFS('Data Angt'!$F$5:$F$5809,"<24",'Data Angt'!$H$5:$H$5809,C62) -> 486 | E62: =D62/$C$42 -> 0.08372093 | F62: =COUNTIFS('Data Angt'!$C$5:$C$5809,F$46,'Data Angt'!$F$5:$F$5809,"<=35",'Data Angt'!$H$5:$H$5809,$C62)-COUNTIFS('Data Angt'!$C$5:$C$5809,F$46,'Data Angt'!$F$5:$F$5809,"<24",'Data Angt'!$H$5:$H$5809,$C62) -> 250 | G62: =COUNTIFS('Data Angt'!$C$5:$C$5809,G$46,'Data Angt'!$F$5:$F$5809,"<=35",'Data Angt'!$H$5:$H$5809,$C62)-COUNTIFS('Data Angt'!$C$5:$C$5809,G$46,'Data Angt'!$F$5:$F$5809,"<24",'Data Angt'!$H$5:$H$5809,$C62) -> 45 | H62: =COUNTIFS('Data Angt'!$C$5:$C$5809,H$46,'Data Angt'!$F$5:$F$5809,"<=35",'Data Angt'!$H$5:$H$5809,$C62)-COUNTIFS('Data Angt'!$C$5:$C$5809,H$46,'Data Angt'!$F$5:$F$5809,"<24",'Data Angt'!$H$5:$H$5809,$C62) -> 84 | I62: =COUNTIFS('Data Angt'!$C$5:$C$5809,I$46,'Data Angt'!$F$5:$F$5809,"<=35",'Data Angt'!$H$5:$H$5809,$C62)-COUNTIFS('Data Angt'!$C$5:$C$5809,I$46,'Data Angt'!$F$5:$F$5809,"<24",'Data Angt'!$H$5:$H$5809,$C62) -> 61 | J62: =COUNTIFS('Data Angt'!$C$5:$C$5809,J$46,'Data Angt'!$F$5:$F$5809,"<=35",'Data Angt'!$H$5:$H$5809,$C62)-COUNTIFS('Data Angt'!$C$5:$C$5809,J$46,'Data Angt'!$F$5:$F$5809,"<24",'Data Angt'!$H$5:$H$5809,$C62) -> 17 | K62: =COUNTIFS('Data Angt'!$C$5:$C$5809,K$46,'Data Angt'!$F$5:$F$5809,"<=35",'Data Angt'!$H$5:$H$5809,$C62)-COUNTIFS('Data Angt'!$C$5:$C$5809,K$46,'Data Angt'!$F$5:$F$5809,"<24",'Data Angt'!$H$5:$H$5809,$C62) -> 29 | L62: =COUNTIFS('Data Angt'!$C$5:$C$5809,L$46,'Data Angt'!$F$5:$F$5809,"<=35",'Data Angt'!$H$5:$H$5809,$C62)-COUNTIFS('Data Angt'!$C$5:$C$5809,L$46,'Data Angt'!$F$5:$F$5809,"<24",'Data Angt'!$H$5:$H$5809,$C62) -> 0
C63: Tenaga Pengajar | D63: =COUNTIFS('Data Angt'!$F$5:$F$5809,"<=35",'Data Angt'!$H$5:$H$5809,C63)-COUNTIFS('Data Angt'!$F$5:$F$5809,"<24",'Data Angt'!$H$5:$H$5809,C63) -> 68 | E63: =D63/$C$42 -> 0.01171404 | F63: =COUNTIFS('Data Angt'!$C$5:$C$5809,F$46,'Data Angt'!$F$5:$F$5809,"<=35",'Data Angt'!$H$5:$H$5809,$C63)-COUNTIFS('Data Angt'!$C$5:$C$5809,F$46,'Data Angt'!$F$5:$F$5809,"<24",'Data Angt'!$H$5:$H$5809,$C63) -> 36 | G63: =COUNTIFS('Data Angt'!$C$5:$C$5809,G$46,'Data Angt'!$F$5:$F$5809,"<=35",'Data Angt'!$H$5:$H$5809,$C63)-COUNTIFS('Data Angt'!$C$5:$C$5809,G$46,'Data Angt'!$F$5:$F$5809,"<24",'Data Angt'!$H$5:$H$5809,$C63) -> 5 | H63: =COUNTIFS('Data Angt'!$C$5:$C$5809,H$46,'Data Angt'!$F$5:$F$5809,"<=35",'Data Angt'!$H$5:$H$5809,$C63)-COUNTIFS('Data Angt'!$C$5:$C$5809,H$46,'Data Angt'!$F$5:$F$5809,"<24",'Data Angt'!$H$5:$H$5809,$C63) -> 10 | I63: =COUNTIFS('Data Angt'!$C$5:$C$5809,I$46,'Data Angt'!$F$5:$F$5809,"<=35",'Data Angt'!$H$5:$H$5809,$C63)-COUNTIFS('Data Angt'!$C$5:$C$5809,I$46,'Data Angt'!$F$5:$F$5809,"<24",'Data Angt'!$H$5:$H$5809,$C63) -> 11 | J63: =COUNTIFS('Data Angt'!$C$5:$C$5809,J$46,'Data Angt'!$F$5:$F$5809,"<=35",'Data Angt'!$H$5:$H$5809,$C63)-COUNTIFS('Data Angt'!$C$5:$C$5809,J$46,'Data Angt'!$F$5:$F$5809,"<24",'Data Angt'!$H$5:$H$5809,$C63) -> 6 | K63: =COUNTIFS('Data Angt'!$C$5:$C$5809,K$46,'Data Angt'!$F$5:$F$5809,"<=35",'Data Angt'!$H$5:$H$5809,$C63)-COUNTIFS('Data Angt'!$C$5:$C$5809,K$46,'Data Angt'!$F$5:$F$5809,"<24",'Data Angt'!$H$5:$H$5809,$C63) -> 0 | L63: =COUNTIFS('Data Angt'!$C$5:$C$5809,L$46,'Data Angt'!$F$5:$F$5809,"<=35",'Data Angt'!$H$5:$H$5809,$C63)-COUNTIFS('Data Angt'!$C$5:$C$5809,L$46,'Data Angt'!$F$5:$F$5809,"<24",'Data Angt'!$H$5:$H$5809,$C63) -> 0
C64: Aparatur/Pejabat Negara | D64: =COUNTIFS('Data Angt'!$F$5:$F$5809,"<=35",'Data Angt'!$H$5:$H$5809,C64)-COUNTIFS('Data Angt'!$F$5:$F$5809,"<24",'Data Angt'!$H$5:$H$5809,C64) -> 20 | E64: =D64/$C$42 -> 0.0034453058 | F64: =COUNTIFS('Data Angt'!$C$5:$C$5809,F$46,'Data Angt'!$F$5:$F$5809,"<=35",'Data Angt'!$H$5:$H$5809,$C64)-COUNTIFS('Data Angt'!$C$5:$C$5809,F$46,'Data Angt'!$F$5:$F$5809,"<24",'Data Angt'!$H$5:$H$5809,$C64) -> 18 | G64: =COUNTIFS('Data Angt'!$C$5:$C$5809,G$46,'Data Angt'!$F$5:$F$5809,"<=35",'Data Angt'!$H$5:$H$5809,$C64)-COUNTIFS('Data Angt'!$C$5:$C$5809,G$46,'Data Angt'!$F$5:$F$5809,"<24",'Data Angt'!$H$5:$H$5809,$C64) -> 0 | H64: =COUNTIFS('Data Angt'!$C$5:$C$5809,H$46,'Data Angt'!$F$5:$F$5809,"<=35",'Data Angt'!$H$5:$H$5809,$C64)-COUNTIFS('Data Angt'!$C$5:$C$5809,H$46,'Data Angt'!$F$5:$F$5809,"<24",'Data Angt'!$H$5:$H$5809,$C64) -> 0 | I64: =COUNTIFS('Data Angt'!$C$5:$C$5809,I$46,'Data Angt'!$F$5:$F$5809,"<=35",'Data Angt'!$H$5:$H$5809,$C64)-COUNTIFS('Data Angt'!$C$5:$C$5809,I$46,'Data Angt'!$F$5:$F$5809,"<24",'Data Angt'!$H$5:$H$5809,$C64) -> 0 | J64: =COUNTIFS('Data Angt'!$C$5:$C$5809,J$46,'Data Angt'!$F$5:$F$5809,"<=35",'Data Angt'!$H$5:$H$5809,$C64)-COUNTIFS('Data Angt'!$C$5:$C$5809,J$46,'Data Angt'!$F$5:$F$5809,"<24",'Data Angt'!$H$5:$H$5809,$C64) -> 1 | K64: =COUNTIFS('Data Angt'!$C$5:$C$5809,K$46,'Data Angt'!$F$5:$F$5809,"<=35",'Data Angt'!$H$5:$H$5809,$C64)-COUNTIFS('Data Angt'!$C$5:$C$5809,K$46,'Data Angt'!$F$5:$F$5809,"<24",'Data Angt'!$H$5:$H$5809,$C64) -> 1 | L64: =COUNTIFS('Data Angt'!$C$5:$C$5809,L$46,'Data Angt'!$F$5:$F$5809,"<=35",'Data Angt'!$H$5:$H$5809,$C64)-COUNTIFS('Data Angt'!$C$5:$C$5809,L$46,'Data Angt'!$F$5:$F$5809,"<24",'Data Angt'!$H$5:$H$5809,$C64) -> 0
C65: Pelajar/Mahasiswa | D65: =COUNTIFS('Data Angt'!$F$5:$F$5809,"<=35",'Data Angt'!$H$5:$H$5809,C65)-COUNTIFS('Data Angt'!$F$5:$F$5809,"<24",'Data Angt'!$H$5:$H$5809,C65) -> 51 | E65: =D65/$C$42 -> 0.0087855297 | F65: =COUNTIFS('Data Angt'!$C$5:$C$5809,F$46,'Data Angt'!$F$5:$F$5809,"<=35",'Data Angt'!$H$5:$H$5809,$C65)-COUNTIFS('Data Angt'!$C$5:$C$5809,F$46,'Data Angt'!$F$5:$F$5809,"<24",'Data Angt'!$H$5:$H$5809,$C65) -> 24 | G65: =COUNTIFS('Data Angt'!$C$5:$C$5809,G$46,'Data Angt'!$F$5:$F$5809,"<=35",'Data Angt'!$H$5:$H$5809,$C65)-COUNTIFS('Data Angt'!$C$5:$C$5809,G$46,'Data Angt'!$F$5:$F$5809,"<24",'Data Angt'!$H$5:$H$5809,$C65) -> 4 | H65: =COUNTIFS('Data Angt'!$C$5:$C$5809,H$46,'Data Angt'!$F$5:$F$5809,"<=35",'Data Angt'!$H$5:$H$5809,$C65)-COUNTIFS('Data Angt'!$C$5:$C$5809,H$46,'Data Angt'!$F$5:$F$5809,"<24",'Data Angt'!$H$5:$H$5809,$C65) -> 15 | I65: =COUNTIFS('Data Angt'!$C$5:$C$5809,I$46,'Data Angt'!$F$5:$F$5809,"<=35",'Data Angt'!$H$5:$H$5809,$C65)-COUNTIFS('Data Angt'!$C$5:$C$5809,I$46,'Data Angt'!$F$5:$F$5809,"<24",'Data Angt'!$H$5:$H$5809,$C65) -> 2 | J65: =COUNTIFS('Data Angt'!$C$5:$C$5809,J$46,'Data Angt'!$F$5:$F$5809,"<=35",'Data Angt'!$H$5:$H$5809,$C65)-COUNTIFS('Data Angt'!$C$5:$C$5809,J$46,'Data Angt'!$F$5:$F$5809,"<24",'Data Angt'!$H$5:$H$5809,$C65) -> 2 | K65: =COUNTIFS('Data Angt'!$C$5:$C$5809,K$46,'Data Angt'!$F$5:$F$5809,"<=35",'Data Angt'!$H$5:$H$5809,$C65)-COUNTIFS('Data Angt'!$C$5:$C$5809,K$46,'Data Angt'!$F$5:$F$5809,"<24",'Data Angt'!$H$5:$H$5809,$C65) -> 4 | L65: =COUNTIFS('Data Angt'!$C$5:$C$5809,L$46,'Data Angt'!$F$5:$F$5809,"<=35",'Data Angt'!$H$5:$H$5809,$C65)-COUNTIFS('Data Angt'!$C$5:$C$5809,L$46,'Data Angt'!$F$5:$F$5809,"<24",'Data Angt'!$H$5:$H$5809,$C65) -> 0
C66: Pemuka Agama | D66: =COUNTIFS('Data Angt'!$F$5:$F$5809,"<=35",'Data Angt'!$H$5:$H$5809,C66)-COUNTIFS('Data Angt'!$F$5:$F$5809,"<24",'Data Angt'!$H$5:$H$5809,C66) -> 3 | E66: =D66/$C$42 -> 0.00051679587 | F66: =COUNTIFS('Data Angt'!$C$5:$C$5809,F$46,'Data Angt'!$F$5:$F$5809,"<=35",'Data Angt'!$H$5:$H$5809,$C66)-COUNTIFS('Data Angt'!$C$5:$C$5809,F$46,'Data Angt'!$F$5:$F$5809,"<24",'Data Angt'!$H$5:$H$5809,$C66) -> 0 | G66: =COUNTIFS('Data Angt'!$C$5:$C$5809,G$46,'Data Angt'!$F$5:$F$5809,"<=35",'Data Angt'!$H$5:$H$5809,$C66)-COUNTIFS('Data Angt'!$C$5:$C$5809,G$46,'Data Angt'!$F$5:$F$5809,"<24",'Data Angt'!$H$5:$H$5809,$C66) -> 0 | H66: =COUNTIFS('Data Angt'!$C$5:$C$5809,H$46,'Data Angt'!$F$5:$F$5809,"<=35",'Data Angt'!$H$5:$H$5809,$C66)-COUNTIFS('Data Angt'!$C$5:$C$5809,H$46,'Data Angt'!$F$5:$F$5809,"<24",'Data Angt'!$H$5:$H$5809,$C66) -> 1 | I66: =COUNTIFS('Data Angt'!$C$5:$C$5809,I$46,'Data Angt'!$F$5:$F$5809,"<=35",'Data Angt'!$H$5:$H$5809,$C66)-COUNTIFS('Data Angt'!$C$5:$C$5809,I$46,'Data Angt'!$F$5:$F$5809,"<24",'Data Angt'!$H$5:$H$5809,$C66) -> 0 | J66: =COUNTIFS('Data Angt'!$C$5:$C$5809,J$46,'Data Angt'!$F$5:$F$5809,"<=35",'Data Angt'!$H$5:$H$5809,$C66)-COUNTIFS('Data Angt'!$C$5:$C$5809,J$46,'Data Angt'!$F$5:$F$5809,"<24",'Data Angt'!$H$5:$H$5809,$C66) -> 1 | K66: =COUNTIFS('Data Angt'!$C$5:$C$5809,K$46,'Data Angt'!$F$5:$F$5809,"<=35",'Data Angt'!$H$5:$H$5809,$C66)-COUNTIFS('Data Angt'!$C$5:$C$5809,K$46,'Data Angt'!$F$5:$F$5809,"<24",'Data Angt'!$H$5:$H$5809,$C66) -> 1 | L66: =COUNTIFS('Data Angt'!$C$5:$C$5809,L$46,'Data Angt'!$F$5:$F$5809,"<=35",'Data Angt'!$H$5:$H$5809,$C66)-COUNTIFS('Data Angt'!$C$5:$C$5809,L$46,'Data Angt'!$F$5:$F$5809,"<24",'Data Angt'!$H$5:$H$5809,$C66) -> 0
C67: Mengurus Rumah Tangga | D67: =COUNTIFS('Data Angt'!$F$5:$F$5809,"<=35",'Data Angt'!$H$5:$H$5809,C67)-COUNTIFS('Data Angt'!$F$5:$F$5809,"<24",'Data Angt'!$H$5:$H$5809,C67) -> 84 | E67: =D67/$C$42 -> 0.014470284 | F67: =COUNTIFS('Data Angt'!$C$5:$C$5809,F$46,'Data Angt'!$F$5:$F$5809,"<=35",'Data Angt'!$H$5:$H$5809,$C67)-COUNTIFS('Data Angt'!$C$5:$C$5809,F$46,'Data Angt'!$F$5:$F$5809,"<24",'Data Angt'!$H$5:$H$5809,$C67) -> 37 | G67: =COUNTIFS('Data Angt'!$C$5:$C$5809,G$46,'Data Angt'!$F$5:$F$5809,"<=35",'Data Angt'!$H$5:$H$5809,$C67)-COUNTIFS('Data Angt'!$C$5:$C$5809,G$46,'Data Angt'!$F$5:$F$5809,"<24",'Data Angt'!$H$5:$H$5809,$C67) -> 10 | H67: =COUNTIFS('Data Angt'!$C$5:$C$5809,H$46,'Data Angt'!$F$5:$F$5809,"<=35",'Data Angt'!$H$5:$H$5809,$C67)-COUNTIFS('Data Angt'!$C$5:$C$5809,H$46,'Data Angt'!$F$5:$F$5809,"<24",'Data Angt'!$H$5:$H$5809,$C67) -> 17 | I67: =COUNTIFS('Data Angt'!$C$5:$C$5809,I$46,'Data Angt'!$F$5:$F$5809,"<=35",'Data Angt'!$H$5:$H$5809,$C67)-COUNTIFS('Data Angt'!$C$5:$C$5809,I$46,'Data Angt'!$F$5:$F$5809,"<24",'Data Angt'!$H$5:$H$5809,$C67) -> 7 | J67: =COUNTIFS('Data Angt'!$C$5:$C$5809,J$46,'Data Angt'!$F$5:$F$5809,"<=35",'Data Angt'!$H$5:$H$5809,$C67)-COUNTIFS('Data Angt'!$C$5:$C$5809,J$46,'Data Angt'!$F$5:$F$5809,"<24",'Data Angt'!$H$5:$H$5809,$C67) -> 4 | K67: =COUNTIFS('Data Angt'!$C$5:$C$5809,K$46,'Data Angt'!$F$5:$F$5809,"<=35",'Data Angt'!$H$5:$H$5809,$C67)-COUNTIFS('Data Angt'!$C$5:$C$5809,K$46,'Data Angt'!$F$5:$F$5809,"<24",'Data Angt'!$H$5:$H$5809,$C67) -> 5 | L67: =COUNTIFS('Data Angt'!$C$5:$C$5809,L$46,'Data Angt'!$F$5:$F$5809,"<=35",'Data Angt'!$H$5:$H$5809,$C67)-COUNTIFS('Data Angt'!$C$5:$C$5809,L$46,'Data Angt'!$F$5:$F$5809,"<24",'Data Angt'!$H$5:$H$5809,$C67) -> 4
C68: Tenaga Ahli | D68: =COUNTIFS('Data Angt'!$F$5:$F$5809,"<=35",'Data Angt'!$H$5:$H$5809,C68)-COUNTIFS('Data Angt'!$F$5:$F$5809,"<24",'Data Angt'!$H$5:$H$5809,C68) -> 2 | E68: =D68/$C$42 -> 0.00034453058 | F68: =COUNTIFS('Data Angt'!$C$5:$C$5809,F$46,'Data Angt'!$F$5:$F$5809,"<=35",'Data Angt'!$H$5:$H$5809,$C68)-COUNTIFS('Data Angt'!$C$5:$C$5809,F$46,'Data Angt'!$F$5:$F$5809,"<24",'Data Angt'!$H$5:$H$5809,$C68) -> 2 | G68: =COUNTIFS('Data Angt'!$C$5:$C$5809,G$46,'Data Angt'!$F$5:$F$5809,"<=35",'Data Angt'!$H$5:$H$5809,$C68)-COUNTIFS('Data Angt'!$C$5:$C$5809,G$46,'Data Angt'!$F$5:$F$5809,"<24",'Data Angt'!$H$5:$H$5809,$C68) -> 0 | H68: =COUNTIFS('Data Angt'!$C$5:$C$5809,H$46,'Data Angt'!$F$5:$F$5809,"<=35",'Data Angt'!$H$5:$H$5809,$C68)-COUNTIFS('Data Angt'!$C$5:$C$5809,H$46,'Data Angt'!$F$5:$F$5809,"<24",'Data Angt'!$H$5:$H$5809,$C68) -> 0 | I68: =COUNTIFS('Data Angt'!$C$5:$C$5809,I$46,'Data Angt'!$F$5:$F$5809,"<=35",'Data Angt'!$H$5:$H$5809,$C68)-COUNTIFS('Data Angt'!$C$5:$C$5809,I$46,'Data Angt'!$F$5:$F$5809,"<24",'Data Angt'!$H$5:$H$5809,$C68) -> 0 | J68: =COUNTIFS('Data Angt'!$C$5:$C$5809,J$46,'Data Angt'!$F$5:$F$5809,"<=35",'Data Angt'!$H$5:$H$5809,$C68)-COUNTIFS('Data Angt'!$C$5:$C$5809,J$46,'Data Angt'!$F$5:$F$5809,"<24",'Data Angt'!$H$5:$H$5809,$C68) -> 0 | K68: =COUNTIFS('Data Angt'!$C$5:$C$5809,K$46,'Data Angt'!$F$5:$F$5809,"<=35",'Data Angt'!$H$5:$H$5809,$C68)-COUNTIFS('Data Angt'!$C$5:$C$5809,K$46,'Data Angt'!$F$5:$F$5809,"<24",'Data Angt'!$H$5:$H$5809,$C68) -> 0 | L68: =COUNTIFS('Data Angt'!$C$5:$C$5809,L$46,'Data Angt'!$F$5:$F$5809,"<=35",'Data Angt'!$H$5:$H$5809,$C68)-COUNTIFS('Data Angt'!$C$5:$C$5809,L$46,'Data Angt'!$F$5:$F$5809,"<24",'Data Angt'!$H$5:$H$5809,$C68) -> 0
C69: Tenaga Medis | D69: =COUNTIFS('Data Angt'!$F$5:$F$5809,"<=35",'Data Angt'!$H$5:$H$5809,C69)-COUNTIFS('Data Angt'!$F$5:$F$5809,"<24",'Data Angt'!$H$5:$H$5809,C69) -> 16 | E69: =D69/$C$42 -> 0.0027562446 | F69: =COUNTIFS('Data Angt'!$C$5:$C$5809,F$46,'Data Angt'!$F$5:$F$5809,"<=35",'Data Angt'!$H$5:$H$5809,$C69)-COUNTIFS('Data Angt'!$C$5:$C$5809,F$46,'Data Angt'!$F$5:$F$5809,"<24",'Data Angt'!$H$5:$H$5809,$C69) -> 7 | G69: =COUNTIFS('Data Angt'!$C$5:$C$5809,G$46,'Data Angt'!$F$5:$F$5809,"<=35",'Data Angt'!$H$5:$H$5809,$C69)-COUNTIFS('Data Angt'!$C$5:$C$5809,G$46,'Data Angt'!$F$5:$F$5809,"<24",'Data Angt'!$H$5:$H$5809,$C69) -> 0 | H69: =COUNTIFS('Data Angt'!$C$5:$C$5809,H$46,'Data Angt'!$F$5:$F$5809,"<=35",'Data Angt'!$H$5:$H$5809,$C69)-COUNTIFS('Data Angt'!$C$5:$C$5809,H$46,'Data Angt'!$F$5:$F$5809,"<24",'Data Angt'!$H$5:$H$5809,$C69) -> 3 | I69: =COUNTIFS('Data Angt'!$C$5:$C$5809,I$46,'Data Angt'!$F$5:$F$5809,"<=35",'Data Angt'!$H$5:$H$5809,$C69)-COUNTIFS('Data Angt'!$C$5:$C$5809,I$46,'Data Angt'!$F$5:$F$5809,"<24",'Data Angt'!$H$5:$H$5809,$C69) -> 2 | J69: =COUNTIFS('Data Angt'!$C$5:$C$5809,J$46,'Data Angt'!$F$5:$F$5809,"<=35",'Data Angt'!$H$5:$H$5809,$C69)-COUNTIFS('Data Angt'!$C$5:$C$5809,J$46,'Data Angt'!$F$5:$F$5809,"<24",'Data Angt'!$H$5:$H$5809,$C69) -> 2 | K69: =COUNTIFS('Data Angt'!$C$5:$C$5809,K$46,'Data Angt'!$F$5:$F$5809,"<=35",'Data Angt'!$H$5:$H$5809,$C69)-COUNTIFS('Data Angt'!$C$5:$C$5809,K$46,'Data Angt'!$F$5:$F$5809,"<24",'Data Angt'!$H$5:$H$5809,$C69) -> 2 | L69: =COUNTIFS('Data Angt'!$C$5:$C$5809,L$46,'Data Angt'!$F$5:$F$5809,"<=35",'Data Angt'!$H$5:$H$5809,$C69)-COUNTIFS('Data Angt'!$C$5:$C$5809,L$46,'Data Angt'!$F$5:$F$5809,"<24",'Data Angt'!$H$5:$H$5809,$C69) -> 0
C70: Petani/Pekebun/Nelayan | D70: =COUNTIFS('Data Angt'!$F$5:$F$5809,"<=35",'Data Angt'!$H$5:$H$5809,C70)-COUNTIFS('Data Angt'!$F$5:$F$5809,"<24",'Data Angt'!$H$5:$H$5809,C70) -> 2 | E70: =D70/$C$42 -> 0.00034453058 | F70: =COUNTIFS('Data Angt'!$C$5:$C$5809,F$46,'Data Angt'!$F$5:$F$5809,"<=35",'Data Angt'!$H$5:$H$5809,$C70)-COUNTIFS('Data Angt'!$C$5:$C$5809,F$46,'Data Angt'!$F$5:$F$5809,"<24",'Data Angt'!$H$5:$H$5809,$C70) -> 1 | G70: =COUNTIFS('Data Angt'!$C$5:$C$5809,G$46,'Data Angt'!$F$5:$F$5809,"<=35",'Data Angt'!$H$5:$H$5809,$C70)-COUNTIFS('Data Angt'!$C$5:$C$5809,G$46,'Data Angt'!$F$5:$F$5809,"<24",'Data Angt'!$H$5:$H$5809,$C70) -> 0 | H70: =COUNTIFS('Data Angt'!$C$5:$C$5809,H$46,'Data Angt'!$F$5:$F$5809,"<=35",'Data Angt'!$H$5:$H$5809,$C70)-COUNTIFS('Data Angt'!$C$5:$C$5809,H$46,'Data Angt'!$F$5:$F$5809,"<24",'Data Angt'!$H$5:$H$5809,$C70) -> 0 | I70: =COUNTIFS('Data Angt'!$C$5:$C$5809,I$46,'Data Angt'!$F$5:$F$5809,"<=35",'Data Angt'!$H$5:$H$5809,$C70)-COUNTIFS('Data Angt'!$C$5:$C$5809,I$46,'Data Angt'!$F$5:$F$5809,"<24",'Data Angt'!$H$5:$H$5809,$C70) -> 1 | J70: =COUNTIFS('Data Angt'!$C$5:$C$5809,J$46,'Data Angt'!$F$5:$F$5809,"<=35",'Data Angt'!$H$5:$H$5809,$C70)-COUNTIFS('Data Angt'!$C$5:$C$5809,J$46,'Data Angt'!$F$5:$F$5809,"<24",'Data Angt'!$H$5:$H$5809,$C70) -> 0 | K70: =COUNTIFS('Data Angt'!$C$5:$C$5809,K$46,'Data Angt'!$F$5:$F$5809,"<=35",'Data Angt'!$H$5:$H$5809,$C70)-COUNTIFS('Data Angt'!$C$5:$C$5809,K$46,'Data Angt'!$F$5:$F$5809,"<24",'Data Angt'!$H$5:$H$5809,$C70) -> 0 | L70: =COUNTIFS('Data Angt'!$C$5:$C$5809,L$46,'Data Angt'!$F$5:$F$5809,"<=35",'Data Angt'!$H$5:$H$5809,$C70)-COUNTIFS('Data Angt'!$C$5:$C$5809,L$46,'Data Angt'!$F$5:$F$5809,"<24",'Data Angt'!$H$5:$H$5809,$C70) -> 0
C71: Pensiunan | D71: =COUNTIFS('Data Angt'!$F$5:$F$5809,"<=35",'Data Angt'!$H$5:$H$5809,C71)-COUNTIFS('Data Angt'!$F$5:$F$5809,"<24",'Data Angt'!$H$5:$H$5809,C71) -> 0 | E71: =D71/$C$42 -> 0 | F71: =COUNTIFS('Data Angt'!$C$5:$C$5809,F$46,'Data Angt'!$F$5:$F$5809,"<=35",'Data Angt'!$H$5:$H$5809,$C71)-COUNTIFS('Data Angt'!$C$5:$C$5809,F$46,'Data Angt'!$F$5:$F$5809,"<24",'Data Angt'!$H$5:$H$5809,$C71) -> 0 | G71: =COUNTIFS('Data Angt'!$C$5:$C$5809,G$46,'Data Angt'!$F$5:$F$5809,"<=35",'Data Angt'!$H$5:$H$5809,$C71)-COUNTIFS('Data Angt'!$C$5:$C$5809,G$46,'Data Angt'!$F$5:$F$5809,"<24",'Data Angt'!$H$5:$H$5809,$C71) -> 0 | H71: =COUNTIFS('Data Angt'!$C$5:$C$5809,H$46,'Data Angt'!$F$5:$F$5809,"<=35",'Data Angt'!$H$5:$H$5809,$C71)-COUNTIFS('Data Angt'!$C$5:$C$5809,H$46,'Data Angt'!$F$5:$F$5809,"<24",'Data Angt'!$H$5:$H$5809,$C71) -> 0 | I71: =COUNTIFS('Data Angt'!$C$5:$C$5809,I$46,'Data Angt'!$F$5:$F$5809,"<=35",'Data Angt'!$H$5:$H$5809,$C71)-COUNTIFS('Data Angt'!$C$5:$C$5809,I$46,'Data Angt'!$F$5:$F$5809,"<24",'Data Angt'!$H$5:$H$5809,$C71) -> 0 | J71: =COUNTIFS('Data Angt'!$C$5:$C$5809,J$46,'Data Angt'!$F$5:$F$5809,"<=35",'Data Angt'!$H$5:$H$5809,$C71)-COUNTIFS('Data Angt'!$C$5:$C$5809,J$46,'Data Angt'!$F$5:$F$5809,"<24",'Data Angt'!$H$5:$H$5809,$C71) -> 0 | K71: =COUNTIFS('Data Angt'!$C$5:$C$5809,K$46,'Data Angt'!$F$5:$F$5809,"<=35",'Data Angt'!$H$5:$H$5809,$C71)-COUNTIFS('Data Angt'!$C$5:$C$5809,K$46,'Data Angt'!$F$5:$F$5809,"<24",'Data Angt'!$H$5:$H$5809,$C71) -> 0 | L71: =COUNTIFS('Data Angt'!$C$5:$C$5809,L$46,'Data Angt'!$F$5:$F$5809,"<=35",'Data Angt'!$H$5:$H$5809,$C71)-COUNTIFS('Data Angt'!$C$5:$C$5809,L$46,'Data Angt'!$F$5:$F$5809,"<24",'Data Angt'!$H$5:$H$5809,$C71) -> 0
C72: Belum/Tidak Bekerja | D72: =COUNTIFS('Data Angt'!$F$5:$F$5809,"<=35",'Data Angt'!$H$5:$H$5809,C72)-COUNTIFS('Data Angt'!$F$5:$F$5809,"<24",'Data Angt'!$H$5:$H$5809,C72) -> 15 | E72: =D72/$C$42 -> 0.0025839793 | F72: =COUNTIFS('Data Angt'!$C$5:$C$5809,F$46,'Data Angt'!$F$5:$F$5809,"<=35",'Data Angt'!$H$5:$H$5809,$C72)-COUNTIFS('Data Angt'!$C$5:$C$5809,F$46,'Data Angt'!$F$5:$F$5809,"<24",'Data Angt'!$H$5:$H$5809,$C72) -> 11 | G72: =COUNTIFS('Data Angt'!$C$5:$C$5809,G$46,'Data Angt'!$F$5:$F$5809,"<=35",'Data Angt'!$H$5:$H$5809,$C72)-COUNTIFS('Data Angt'!$C$5:$C$5809,G$46,'Data Angt'!$F$5:$F$5809,"<24",'Data Angt'!$H$5:$H$5809,$C72) -> 1 | H72: =COUNTIFS('Data Angt'!$C$5:$C$5809,H$46,'Data Angt'!$F$5:$F$5809,"<=35",'Data Angt'!$H$5:$H$5809,$C72)-COUNTIFS('Data Angt'!$C$5:$C$5809,H$46,'Data Angt'!$F$5:$F$5809,"<24",'Data Angt'!$H$5:$H$5809,$C72) -> 0 | I72: =COUNTIFS('Data Angt'!$C$5:$C$5809,I$46,'Data Angt'!$F$5:$F$5809,"<=35",'Data Angt'!$H$5:$H$5809,$C72)-COUNTIFS('Data Angt'!$C$5:$C$5809,I$46,'Data Angt'!$F$5:$F$5809,"<24",'Data Angt'!$H$5:$H$5809,$C72) -> 1 | J72: =COUNTIFS('Data Angt'!$C$5:$C$5809,J$46,'Data Angt'!$F$5:$F$5809,"<=35",'Data Angt'!$H$5:$H$5809,$C72)-COUNTIFS('Data Angt'!$C$5:$C$5809,J$46,'Data Angt'!$F$5:$F$5809,"<24",'Data Angt'!$H$5:$H$5809,$C72) -> 2 | K72: =COUNTIFS('Data Angt'!$C$5:$C$5809,K$46,'Data Angt'!$F$5:$F$5809,"<=35",'Data Angt'!$H$5:$H$5809,$C72)-COUNTIFS('Data Angt'!$C$5:$C$5809,K$46,'Data Angt'!$F$5:$F$5809,"<24",'Data Angt'!$H$5:$H$5809,$C72) -> 0 | L72: =COUNTIFS('Data Angt'!$C$5:$C$5809,L$46,'Data Angt'!$F$5:$F$5809,"<=35",'Data Angt'!$H$5:$H$5809,$C72)-COUNTIFS('Data Angt'!$C$5:$C$5809,L$46,'Data Angt'!$F$5:$F$5809,"<24",'Data Angt'!$H$5:$H$5809,$C72) -> 0
C73: Lain-lain | D73: =COUNTIFS('Data Angt'!$F$5:$F$5809,"<=35",'Data Angt'!$H$5:$H$5809,C73)-COUNTIFS('Data Angt'!$F$5:$F$5809,"<24",'Data Angt'!$H$5:$H$5809,C73) -> 35 | E73: =D73/$C$42 -> 0.0060292851 | F73: =COUNTIFS('Data Angt'!$C$5:$C$5809,F$46,'Data Angt'!$F$5:$F$5809,"<=35",'Data Angt'!$H$5:$H$5809,$C73)-COUNTIFS('Data Angt'!$C$5:$C$5809,F$46,'Data Angt'!$F$5:$F$5809,"<24",'Data Angt'!$H$5:$H$5809,$C73) -> 19 | G73: =COUNTIFS('Data Angt'!$C$5:$C$5809,G$46,'Data Angt'!$F$5:$F$5809,"<=35",'Data Angt'!$H$5:$H$5809,$C73)-COUNTIFS('Data Angt'!$C$5:$C$5809,G$46,'Data Angt'!$F$5:$F$5809,"<24",'Data Angt'!$H$5:$H$5809,$C73) -> 4 | H73: =COUNTIFS('Data Angt'!$C$5:$C$5809,H$46,'Data Angt'!$F$5:$F$5809,"<=35",'Data Angt'!$H$5:$H$5809,$C73)-COUNTIFS('Data Angt'!$C$5:$C$5809,H$46,'Data Angt'!$F$5:$F$5809,"<24",'Data Angt'!$H$5:$H$5809,$C73) -> 2 | I73: =COUNTIFS('Data Angt'!$C$5:$C$5809,I$46,'Data Angt'!$F$5:$F$5809,"<=35",'Data Angt'!$H$5:$H$5809,$C73)-COUNTIFS('Data Angt'!$C$5:$C$5809,I$46,'Data Angt'!$F$5:$F$5809,"<24",'Data Angt'!$H$5:$H$5809,$C73) -> 2 | J73: =COUNTIFS('Data Angt'!$C$5:$C$5809,J$46,'Data Angt'!$F$5:$F$5809,"<=35",'Data Angt'!$H$5:$H$5809,$C73)-COUNTIFS('Data Angt'!$C$5:$C$5809,J$46,'Data Angt'!$F$5:$F$5809,"<24",'Data Angt'!$H$5:$H$5809,$C73) -> 2 | K73: =COUNTIFS('Data Angt'!$C$5:$C$5809,K$46,'Data Angt'!$F$5:$F$5809,"<=35",'Data Angt'!$H$5:$H$5809,$C73)-COUNTIFS('Data Angt'!$C$5:$C$5809,K$46,'Data Angt'!$F$5:$F$5809,"<24",'Data Angt'!$H$5:$H$5809,$C73) -> 6 | L73: =COUNTIFS('Data Angt'!$C$5:$C$5809,L$46,'Data Angt'!$F$5:$F$5809,"<=35",'Data Angt'!$H$5:$H$5809,$C73)-COUNTIFS('Data Angt'!$C$5:$C$5809,L$46,'Data Angt'!$F$5:$F$5809,"<24",'Data Angt'!$H$5:$H$5809,$C73) -> 0
C74: Kosong | D74: =COUNTIFS('Data Angt'!$F$5:$F$5809,"<=35",'Data Angt'!$H$5:$H$5809,"")-COUNTIFS('Data Angt'!$F$5:$F$5809,"<24",'Data Angt'!$H$5:$H$5809,"") -> 54 | E74: =D74/$C$42 -> 0.0093023256 | F74: =COUNTIFS('Data Angt'!$C$5:$C$5809,F$46,'Data Angt'!$F$5:$F$5809,"<=35",'Data Angt'!$H$5:$H$5809,"")-COUNTIFS('Data Angt'!$C$5:$C$5809,F$46,'Data Angt'!$F$5:$F$5809,"<24",'Data Angt'!$H$5:$H$5809,"") -> 36 | G74: =COUNTIFS('Data Angt'!$C$5:$C$5809,G$46,'Data Angt'!$F$5:$F$5809,"<=35",'Data Angt'!$H$5:$H$5809,"")-COUNTIFS('Data Angt'!$C$5:$C$5809,G$46,'Data Angt'!$F$5:$F$5809,"<24",'Data Angt'!$H$5:$H$5809,"") -> 12 | H74: =COUNTIFS('Data Angt'!$C$5:$C$5809,H$46,'Data Angt'!$F$5:$F$5809,"<=35",'Data Angt'!$H$5:$H$5809,"")-COUNTIFS('Data Angt'!$C$5:$C$5809,H$46,'Data Angt'!$F$5:$F$5809,"<24",'Data Angt'!$H$5:$H$5809,"") -> 1 | I74: =COUNTIFS('Data Angt'!$C$5:$C$5809,I$46,'Data Angt'!$F$5:$F$5809,"<=35",'Data Angt'!$H$5:$H$5809,"")-COUNTIFS('Data Angt'!$C$5:$C$5809,I$46,'Data Angt'!$F$5:$F$5809,"<24",'Data Angt'!$H$5:$H$5809,"") -> 1 | J74: =COUNTIFS('Data Angt'!$C$5:$C$5809,J$46,'Data Angt'!$F$5:$F$5809,"<=35",'Data Angt'!$H$5:$H$5809,"")-COUNTIFS('Data Angt'!$C$5:$C$5809,J$46,'Data Angt'!$F$5:$F$5809,"<24",'Data Angt'!$H$5:$H$5809,"") -> 1 | K74: =COUNTIFS('Data Angt'!$C$5:$C$5809,K$46,'Data Angt'!$F$5:$F$5809,"<=35",'Data Angt'!$H$5:$H$5809,"")-COUNTIFS('Data Angt'!$C$5:$C$5809,K$46,'Data Angt'!$F$5:$F$5809,"<24",'Data Angt'!$H$5:$H$5809,"") -> 3 | L74: =COUNTIFS('Data Angt'!$C$5:$C$5809,L$46,'Data Angt'!$F$5:$F$5809,"<=35",'Data Angt'!$H$5:$H$5809,"")-COUNTIFS('Data Angt'!$C$5:$C$5809,L$46,'Data Angt'!$F$5:$F$5809,"<24",'Data Angt'!$H$5:$H$5809,"") -> 0
B75: 36 - 45 Th | C75: Wiraswasta | D75: =COUNTIFS('Data Angt'!$F$5:$F$5809,"<=45",'Data Angt'!$H$5:$H$5809,C75)-COUNTIFS('Data Angt'!$F$5:$F$5809,"<36",'Data Angt'!$H$5:$H$5809,C75) -> 342 | E75: =D75/$C$42 -> 0.058914729 | F75: =COUNTIFS('Data Angt'!$C$5:$C$5809,F$46,'Data Angt'!$F$5:$F$5809,"<=45",'Data Angt'!$H$5:$H$5809,$C75)-COUNTIFS('Data Angt'!$C$5:$C$5809,F$46,'Data Angt'!$F$5:$F$5809,"<36",'Data Angt'!$H$5:$H$5809,$C75) -> 131 | G75: =COUNTIFS('Data Angt'!$C$5:$C$5809,G$46,'Data Angt'!$F$5:$F$5809,"<=45",'Data Angt'!$H$5:$H$5809,$C75)-COUNTIFS('Data Angt'!$C$5:$C$5809,G$46,'Data Angt'!$F$5:$F$5809,"<36",'Data Angt'!$H$5:$H$5809,$C75) -> 49 | H75: =COUNTIFS('Data Angt'!$C$5:$C$5809,H$46,'Data Angt'!$F$5:$F$5809,"<=45",'Data Angt'!$H$5:$H$5809,$C75)-COUNTIFS('Data Angt'!$C$5:$C$5809,H$46,'Data Angt'!$F$5:$F$5809,"<36",'Data Angt'!$H$5:$H$5809,$C75) -> 51 | I75: =COUNTIFS('Data Angt'!$C$5:$C$5809,I$46,'Data Angt'!$F$5:$F$5809,"<=45",'Data Angt'!$H$5:$H$5809,$C75)-COUNTIFS('Data Angt'!$C$5:$C$5809,I$46,'Data Angt'!$F$5:$F$5809,"<36",'Data Angt'!$H$5:$H$5809,$C75) -> 44 | J75: =COUNTIFS('Data Angt'!$C$5:$C$5809,J$46,'Data Angt'!$F$5:$F$5809,"<=45",'Data Angt'!$H$5:$H$5809,$C75)-COUNTIFS('Data Angt'!$C$5:$C$5809,J$46,'Data Angt'!$F$5:$F$5809,"<36",'Data Angt'!$H$5:$H$5809,$C75) -> 25 | K75: =COUNTIFS('Data Angt'!$C$5:$C$5809,K$46,'Data Angt'!$F$5:$F$5809,"<=45",'Data Angt'!$H$5:$H$5809,$C75)-COUNTIFS('Data Angt'!$C$5:$C$5809,K$46,'Data Angt'!$F$5:$F$5809,"<36",'Data Angt'!$H$5:$H$5809,$C75) -> 36 | L75: =COUNTIFS('Data Angt'!$C$5:$C$5809,L$46,'Data Angt'!$F$5:$F$5809,"<=45",'Data Angt'!$H$5:$H$5809,$C75)-COUNTIFS('Data Angt'!$C$5:$C$5809,L$46,'Data Angt'!$F$5:$F$5809,"<36",'Data Angt'!$H$5:$H$5809,$C75) -> 6
C76: Karyawan | D76: =COUNTIFS('Data Angt'!$F$5:$F$5809,"<=45",'Data Angt'!$H$5:$H$5809,C76)-COUNTIFS('Data Angt'!$F$5:$F$5809,"<36",'Data Angt'!$H$5:$H$5809,C76) -> 488 | E76: =D76/$C$42 -> 0.084065461 | F76: =COUNTIFS('Data Angt'!$C$5:$C$5809,F$46,'Data Angt'!$F$5:$F$5809,"<=45",'Data Angt'!$H$5:$H$5809,$C76)-COUNTIFS('Data Angt'!$C$5:$C$5809,F$46,'Data Angt'!$F$5:$F$5809,"<36",'Data Angt'!$H$5:$H$5809,$C76) -> 207 | G76: =COUNTIFS('Data Angt'!$C$5:$C$5809,G$46,'Data Angt'!$F$5:$F$5809,"<=45",'Data Angt'!$H$5:$H$5809,$C76)-COUNTIFS('Data Angt'!$C$5:$C$5809,G$46,'Data Angt'!$F$5:$F$5809,"<36",'Data Angt'!$H$5:$H$5809,$C76) -> 54 | H76: =COUNTIFS('Data Angt'!$C$5:$C$5809,H$46,'Data Angt'!$F$5:$F$5809,"<=45",'Data Angt'!$H$5:$H$5809,$C76)-COUNTIFS('Data Angt'!$C$5:$C$5809,H$46,'Data Angt'!$F$5:$F$5809,"<36",'Data Angt'!$H$5:$H$5809,$C76) -> 83 | I76: =COUNTIFS('Data Angt'!$C$5:$C$5809,I$46,'Data Angt'!$F$5:$F$5809,"<=45",'Data Angt'!$H$5:$H$5809,$C76)-COUNTIFS('Data Angt'!$C$5:$C$5809,I$46,'Data Angt'!$F$5:$F$5809,"<36",'Data Angt'!$H$5:$H$5809,$C76) -> 42 | J76: =COUNTIFS('Data Angt'!$C$5:$C$5809,J$46,'Data Angt'!$F$5:$F$5809,"<=45",'Data Angt'!$H$5:$H$5809,$C76)-COUNTIFS('Data Angt'!$C$5:$C$5809,J$46,'Data Angt'!$F$5:$F$5809,"<36",'Data Angt'!$H$5:$H$5809,$C76) -> 24 | K76: =COUNTIFS('Data Angt'!$C$5:$C$5809,K$46,'Data Angt'!$F$5:$F$5809,"<=45",'Data Angt'!$H$5:$H$5809,$C76)-COUNTIFS('Data Angt'!$C$5:$C$5809,K$46,'Data Angt'!$F$5:$F$5809,"<36",'Data Angt'!$H$5:$H$5809,$C76) -> 34 | L76: =COUNTIFS('Data Angt'!$C$5:$C$5809,L$46,'Data Angt'!$F$5:$F$5809,"<=45",'Data Angt'!$H$5:$H$5809,$C76)-COUNTIFS('Data Angt'!$C$5:$C$5809,L$46,'Data Angt'!$F$5:$F$5809,"<36",'Data Angt'!$H$5:$H$5809,$C76) -> 44
C77: Tenaga Pengajar | D77: =COUNTIFS('Data Angt'!$F$5:$F$5809,"<=45",'Data Angt'!$H$5:$H$5809,C77)-COUNTIFS('Data Angt'!$F$5:$F$5809,"<36",'Data Angt'!$H$5:$H$5809,C77) -> 132 | E77: =D77/$C$42 -> 0.022739018 | F77: =COUNTIFS('Data Angt'!$C$5:$C$5809,F$46,'Data Angt'!$F$5:$F$5809,"<=45",'Data Angt'!$H$5:$H$5809,$C77)-COUNTIFS('Data Angt'!$C$5:$C$5809,F$46,'Data Angt'!$F$5:$F$5809,"<36",'Data Angt'!$H$5:$H$5809,$C77) -> 51 | G77: =COUNTIFS('Data Angt'!$C$5:$C$5809,G$46,'Data Angt'!$F$5:$F$5809,"<=45",'Data Angt'!$H$5:$H$5809,$C77)-COUNTIFS('Data Angt'!$C$5:$C$5809,G$46,'Data Angt'!$F$5:$F$5809,"<36",'Data Angt'!$H$5:$H$5809,$C77) -> 35 | H77: =COUNTIFS('Data Angt'!$C$5:$C$5809,H$46,'Data Angt'!$F$5:$F$5809,"<=45",'Data Angt'!$H$5:$H$5809,$C77)-COUNTIFS('Data Angt'!$C$5:$C$5809,H$46,'Data Angt'!$F$5:$F$5809,"<36",'Data Angt'!$H$5:$H$5809,$C77) -> 22 | I77: =COUNTIFS('Data Angt'!$C$5:$C$5809,I$46,'Data Angt'!$F$5:$F$5809,"<=45",'Data Angt'!$H$5:$H$5809,$C77)-COUNTIFS('Data Angt'!$C$5:$C$5809,I$46,'Data Angt'!$F$5:$F$5809,"<36",'Data Angt'!$H$5:$H$5809,$C77) -> 6 | J77: =COUNTIFS('Data Angt'!$C$5:$C$5809,J$46,'Data Angt'!$F$5:$F$5809,"<=45",'Data Angt'!$H$5:$H$5809,$C77)-COUNTIFS('Data Angt'!$C$5:$C$5809,J$46,'Data Angt'!$F$5:$F$5809,"<36",'Data Angt'!$H$5:$H$5809,$C77) -> 10 | K77: =COUNTIFS('Data Angt'!$C$5:$C$5809,K$46,'Data Angt'!$F$5:$F$5809,"<=45",'Data Angt'!$H$5:$H$5809,$C77)-COUNTIFS('Data Angt'!$C$5:$C$5809,K$46,'Data Angt'!$F$5:$F$5809,"<36",'Data Angt'!$H$5:$H$5809,$C77) -> 5 | L77: =COUNTIFS('Data Angt'!$C$5:$C$5809,L$46,'Data Angt'!$F$5:$F$5809,"<=45",'Data Angt'!$H$5:$H$5809,$C77)-COUNTIFS('Data Angt'!$C$5:$C$5809,L$46,'Data Angt'!$F$5:$F$5809,"<36",'Data Angt'!$H$5:$H$5809,$C77) -> 3
C78: Aparatur/Pejabat Negara | D78: =COUNTIFS('Data Angt'!$F$5:$F$5809,"<=45",'Data Angt'!$H$5:$H$5809,C78)-COUNTIFS('Data Angt'!$F$5:$F$5809,"<36",'Data Angt'!$H$5:$H$5809,C78) -> 71 | E78: =D78/$C$42 -> 0.012230835 | F78: =COUNTIFS('Data Angt'!$C$5:$C$5809,F$46,'Data Angt'!$F$5:$F$5809,"<=45",'Data Angt'!$H$5:$H$5809,$C78)-COUNTIFS('Data Angt'!$C$5:$C$5809,F$46,'Data Angt'!$F$5:$F$5809,"<36",'Data Angt'!$H$5:$H$5809,$C78) -> 51 | G78: =COUNTIFS('Data Angt'!$C$5:$C$5809,G$46,'Data Angt'!$F$5:$F$5809,"<=45",'Data Angt'!$H$5:$H$5809,$C78)-COUNTIFS('Data Angt'!$C$5:$C$5809,G$46,'Data Angt'!$F$5:$F$5809,"<36",'Data Angt'!$H$5:$H$5809,$C78) -> 8 | H78: =COUNTIFS('Data Angt'!$C$5:$C$5809,H$46,'Data Angt'!$F$5:$F$5809,"<=45",'Data Angt'!$H$5:$H$5809,$C78)-COUNTIFS('Data Angt'!$C$5:$C$5809,H$46,'Data Angt'!$F$5:$F$5809,"<36",'Data Angt'!$H$5:$H$5809,$C78) -> 4 | I78: =COUNTIFS('Data Angt'!$C$5:$C$5809,I$46,'Data Angt'!$F$5:$F$5809,"<=45",'Data Angt'!$H$5:$H$5809,$C78)-COUNTIFS('Data Angt'!$C$5:$C$5809,I$46,'Data Angt'!$F$5:$F$5809,"<36",'Data Angt'!$H$5:$H$5809,$C78) -> 4 | J78: =COUNTIFS('Data Angt'!$C$5:$C$5809,J$46,'Data Angt'!$F$5:$F$5809,"<=45",'Data Angt'!$H$5:$H$5809,$C78)-COUNTIFS('Data Angt'!$C$5:$C$5809,J$46,'Data Angt'!$F$5:$F$5809,"<36",'Data Angt'!$H$5:$H$5809,$C78) -> 0 | K78: =COUNTIFS('Data Angt'!$C$5:$C$5809,K$46,'Data Angt'!$F$5:$F$5809,"<=45",'Data Angt'!$H$5:$H$5809,$C78)-COUNTIFS('Data Angt'!$C$5:$C$5809,K$46,'Data Angt'!$F$5:$F$5809,"<36",'Data Angt'!$H$5:$H$5809,$C78) -> 1 | L78: =COUNTIFS('Data Angt'!$C$5:$C$5809,L$46,'Data Angt'!$F$5:$F$5809,"<=45",'Data Angt'!$H$5:$H$5809,$C78)-COUNTIFS('Data Angt'!$C$5:$C$5809,L$46,'Data Angt'!$F$5:$F$5809,"<36",'Data Angt'!$H$5:$H$5809,$C78) -> 3
C79: Pelajar/Mahasiswa | D79: =COUNTIFS('Data Angt'!$F$5:$F$5809,"<=45",'Data Angt'!$H$5:$H$5809,C79)-COUNTIFS('Data Angt'!$F$5:$F$5809,"<36",'Data Angt'!$H$5:$H$5809,C79) -> 2 | E79: =D79/$C$42 -> 0.00034453058 | F79: =COUNTIFS('Data Angt'!$C$5:$C$5809,F$46,'Data Angt'!$F$5:$F$5809,"<=45",'Data Angt'!$H$5:$H$5809,$C79)-COUNTIFS('Data Angt'!$C$5:$C$5809,F$46,'Data Angt'!$F$5:$F$5809,"<36",'Data Angt'!$H$5:$H$5809,$C79) -> 1 | G79: =COUNTIFS('Data Angt'!$C$5:$C$5809,G$46,'Data Angt'!$F$5:$F$5809,"<=45",'Data Angt'!$H$5:$H$5809,$C79)-COUNTIFS('Data Angt'!$C$5:$C$5809,G$46,'Data Angt'!$F$5:$F$5809,"<36",'Data Angt'!$H$5:$H$5809,$C79) -> 0 | H79: =COUNTIFS('Data Angt'!$C$5:$C$5809,H$46,'Data Angt'!$F$5:$F$5809,"<=45",'Data Angt'!$H$5:$H$5809,$C79)-COUNTIFS('Data Angt'!$C$5:$C$5809,H$46,'Data Angt'!$F$5:$F$5809,"<36",'Data Angt'!$H$5:$H$5809,$C79) -> 0 | I79: =COUNTIFS('Data Angt'!$C$5:$C$5809,I$46,'Data Angt'!$F$5:$F$5809,"<=45",'Data Angt'!$H$5:$H$5809,$C79)-COUNTIFS('Data Angt'!$C$5:$C$5809,I$46,'Data Angt'!$F$5:$F$5809,"<36",'Data Angt'!$H$5:$H$5809,$C79) -> 0 | J79: =COUNTIFS('Data Angt'!$C$5:$C$5809,J$46,'Data Angt'!$F$5:$F$5809,"<=45",'Data Angt'!$H$5:$H$5809,$C79)-COUNTIFS('Data Angt'!$C$5:$C$5809,J$46,'Data Angt'!$F$5:$F$5809,"<36",'Data Angt'!$H$5:$H$5809,$C79) -> 1 | K79: =COUNTIFS('Data Angt'!$C$5:$C$5809,K$46,'Data Angt'!$F$5:$F$5809,"<=45",'Data Angt'!$H$5:$H$5809,$C79)-COUNTIFS('Data Angt'!$C$5:$C$5809,K$46,'Data Angt'!$F$5:$F$5809,"<36",'Data Angt'!$H$5:$H$5809,$C79) -> 0 | L79: =COUNTIFS('Data Angt'!$C$5:$C$5809,L$46,'Data Angt'!$F$5:$F$5809,"<=45",'Data Angt'!$H$5:$H$5809,$C79)-COUNTIFS('Data Angt'!$C$5:$C$5809,L$46,'Data Angt'!$F$5:$F$5809,"<36",'Data Angt'!$H$5:$H$5809,$C79) -> 0
C80: Pemuka Agama | D80: =COUNTIFS('Data Angt'!$F$5:$F$5809,"<=45",'Data Angt'!$H$5:$H$5809,C80)-COUNTIFS('Data Angt'!$F$5:$F$5809,"<36",'Data Angt'!$H$5:$H$5809,C80) -> 6 | E80: =D80/$C$42 -> 0.0010335917 | F80: =COUNTIFS('Data Angt'!$C$5:$C$5809,F$46,'Data Angt'!$F$5:$F$5809,"<=45",'Data Angt'!$H$5:$H$5809,$C80)-COUNTIFS('Data Angt'!$C$5:$C$5809,F$46,'Data Angt'!$F$5:$F$5809,"<36",'Data Angt'!$H$5:$H$5809,$C80) -> 4 | G80: =COUNTIFS('Data Angt'!$C$5:$C$5809,G$46,'Data Angt'!$F$5:$F$5809,"<=45",'Data Angt'!$H$5:$H$5809,$C80)-COUNTIFS('Data Angt'!$C$5:$C$5809,G$46,'Data Angt'!$F$5:$F$5809,"<36",'Data Angt'!$H$5:$H$5809,$C80) -> 0 | H80: =COUNTIFS('Data Angt'!$C$5:$C$5809,H$46,'Data Angt'!$F$5:$F$5809,"<=45",'Data Angt'!$H$5:$H$5809,$C80)-COUNTIFS('Data Angt'!$C$5:$C$5809,H$46,'Data Angt'!$F$5:$F$5809,"<36",'Data Angt'!$H$5:$H$5809,$C80) -> 1 | I80: =COUNTIFS('Data Angt'!$C$5:$C$5809,I$46,'Data Angt'!$F$5:$F$5809,"<=45",'Data Angt'!$H$5:$H$5809,$C80)-COUNTIFS('Data Angt'!$C$5:$C$5809,I$46,'Data Angt'!$F$5:$F$5809,"<36",'Data Angt'!$H$5:$H$5809,$C80) -> 1 | J80: =COUNTIFS('Data Angt'!$C$5:$C$5809,J$46,'Data Angt'!$F$5:$F$5809,"<=45",'Data Angt'!$H$5:$H$5809,$C80)-COUNTIFS('Data Angt'!$C$5:$C$5809,J$46,'Data Angt'!$F$5:$F$5809,"<36",'Data Angt'!$H$5:$H$5809,$C80) -> 0 | K80: =COUNTIFS('Data Angt'!$C$5:$C$5809,K$46,'Data Angt'!$F$5:$F$5809,"<=45",'Data Angt'!$H$5:$H$5809,$C80)-COUNTIFS('Data Angt'!$C$5:$C$5809,K$46,'Data Angt'!$F$5:$F$5809,"<36",'Data Angt'!$H$5:$H$5809,$C80) -> 0 | L80: =COUNTIFS('Data Angt'!$C$5:$C$5809,L$46,'Data Angt'!$F$5:$F$5809,"<=45",'Data Angt'!$H$5:$H$5809,$C80)-COUNTIFS('Data Angt'!$C$5:$C$5809,L$46,'Data Angt'!$F$5:$F$5809,"<36",'Data Angt'!$H$5:$H$5809,$C80) -> 0
C81: Mengurus Rumah Tangga | D81: =COUNTIFS('Data Angt'!$F$5:$F$5809,"<=45",'Data Angt'!$H$5:$H$5809,C81)-COUNTIFS('Data Angt'!$F$5:$F$5809,"<36",'Data Angt'!$H$5:$H$5809,C81) -> 236 | E81: =D81/$C$42 -> 0.040654608 | F81: =COUNTIFS('Data Angt'!$C$5:$C$5809,F$46,'Data Angt'!$F$5:$F$5809,"<=45",'Data Angt'!$H$5:$H$5809,$C81)-COUNTIFS('Data Angt'!$C$5:$C$5809,F$46,'Data Angt'!$F$5:$F$5809,"<36",'Data Angt'!$H$5:$H$5809,$C81) -> 108 | G81: =COUNTIFS('Data Angt'!$C$5:$C$5809,G$46,'Data Angt'!$F$5:$F$5809,"<=45",'Data Angt'!$H$5:$H$5809,$C81)-COUNTIFS('Data Angt'!$C$5:$C$5809,G$46,'Data Angt'!$F$5:$F$5809,"<36",'Data Angt'!$H$5:$H$5809,$C81) -> 22 | H81: =COUNTIFS('Data Angt'!$C$5:$C$5809,H$46,'Data Angt'!$F$5:$F$5809,"<=45",'Data Angt'!$H$5:$H$5809,$C81)-COUNTIFS('Data Angt'!$C$5:$C$5809,H$46,'Data Angt'!$F$5:$F$5809,"<36",'Data Angt'!$H$5:$H$5809,$C81) -> 41 | I81: =COUNTIFS('Data Angt'!$C$5:$C$5809,I$46,'Data Angt'!$F$5:$F$5809,"<=45",'Data Angt'!$H$5:$H$5809,$C81)-COUNTIFS('Data Angt'!$C$5:$C$5809,I$46,'Data Angt'!$F$5:$F$5809,"<36",'Data Angt'!$H$5:$H$5809,$C81) -> 10 | J81: =COUNTIFS('Data Angt'!$C$5:$C$5809,J$46,'Data Angt'!$F$5:$F$5809,"<=45",'Data Angt'!$H$5:$H$5809,$C81)-COUNTIFS('Data Angt'!$C$5:$C$5809,J$46,'Data Angt'!$F$5:$F$5809,"<36",'Data Angt'!$H$5:$H$5809,$C81) -> 15 | K81: =COUNTIFS('Data Angt'!$C$5:$C$5809,K$46,'Data Angt'!$F$5:$F$5809,"<=45",'Data Angt'!$H$5:$H$5809,$C81)-COUNTIFS('Data Angt'!$C$5:$C$5809,K$46,'Data Angt'!$F$5:$F$5809,"<36",'Data Angt'!$H$5:$H$5809,$C81) -> 9 | L81: =COUNTIFS('Data Angt'!$C$5:$C$5809,L$46,'Data Angt'!$F$5:$F$5809,"<=45",'Data Angt'!$H$5:$H$5809,$C81)-COUNTIFS('Data Angt'!$C$5:$C$5809,L$46,'Data Angt'!$F$5:$F$5809,"<36",'Data Angt'!$H$5:$H$5809,$C81) -> 31
C82: Tenaga Ahli | D82: =COUNTIFS('Data Angt'!$F$5:$F$5809,"<=45",'Data Angt'!$H$5:$H$5809,C82)-COUNTIFS('Data Angt'!$F$5:$F$5809,"<36",'Data Angt'!$H$5:$H$5809,C82) -> 4 | E82: =D82/$C$42 -> 0.00068906115 | F82: =COUNTIFS('Data Angt'!$C$5:$C$5809,F$46,'Data Angt'!$F$5:$F$5809,"<=45",'Data Angt'!$H$5:$H$5809,$C82)-COUNTIFS('Data Angt'!$C$5:$C$5809,F$46,'Data Angt'!$F$5:$F$5809,"<36",'Data Angt'!$H$5:$H$5809,$C82) -> 2 | G82: =COUNTIFS('Data Angt'!$C$5:$C$5809,G$46,'Data Angt'!$F$5:$F$5809,"<=45",'Data Angt'!$H$5:$H$5809,$C82)-COUNTIFS('Data Angt'!$C$5:$C$5809,G$46,'Data Angt'!$F$5:$F$5809,"<36",'Data Angt'!$H$5:$H$5809,$C82) -> 1 | H82: =COUNTIFS('Data Angt'!$C$5:$C$5809,H$46,'Data Angt'!$F$5:$F$5809,"<=45",'Data Angt'!$H$5:$H$5809,$C82)-COUNTIFS('Data Angt'!$C$5:$C$5809,H$46,'Data Angt'!$F$5:$F$5809,"<36",'Data Angt'!$H$5:$H$5809,$C82) -> 1 | I82: =COUNTIFS('Data Angt'!$C$5:$C$5809,I$46,'Data Angt'!$F$5:$F$5809,"<=45",'Data Angt'!$H$5:$H$5809,$C82)-COUNTIFS('Data Angt'!$C$5:$C$5809,I$46,'Data Angt'!$F$5:$F$5809,"<36",'Data Angt'!$H$5:$H$5809,$C82) -> 0 | J82: =COUNTIFS('Data Angt'!$C$5:$C$5809,J$46,'Data Angt'!$F$5:$F$5809,"<=45",'Data Angt'!$H$5:$H$5809,$C82)-COUNTIFS('Data Angt'!$C$5:$C$5809,J$46,'Data Angt'!$F$5:$F$5809,"<36",'Data Angt'!$H$5:$H$5809,$C82) -> 0 | K82: =COUNTIFS('Data Angt'!$C$5:$C$5809,K$46,'Data Angt'!$F$5:$F$5809,"<=45",'Data Angt'!$H$5:$H$5809,$C82)-COUNTIFS('Data Angt'!$C$5:$C$5809,K$46,'Data Angt'!$F$5:$F$5809,"<36",'Data Angt'!$H$5:$H$5809,$C82) -> 0 | L82: =COUNTIFS('Data Angt'!$C$5:$C$5809,L$46,'Data Angt'!$F$5:$F$5809,"<=45",'Data Angt'!$H$5:$H$5809,$C82)-COUNTIFS('Data Angt'!$C$5:$C$5809,L$46,'Data Angt'!$F$5:$F$5809,"<36",'Data Angt'!$H$5:$H$5809,$C82) -> 0
C83: Tenaga Medis | D83: =COUNTIFS('Data Angt'!$F$5:$F$5809,"<=45",'Data Angt'!$H$5:$H$5809,C83)-COUNTIFS('Data Angt'!$F$5:$F$5809,"<36",'Data Angt'!$H$5:$H$5809,C83) -> 14 | E83: =D83/$C$42 -> 0.002411714 | F83: =COUNTIFS('Data Angt'!$C$5:$C$5809,F$46,'Data Angt'!$F$5:$F$5809,"<=45",'Data Angt'!$H$5:$H$5809,$C83)-COUNTIFS('Data Angt'!$C$5:$C$5809,F$46,'Data Angt'!$F$5:$F$5809,"<36",'Data Angt'!$H$5:$H$5809,$C83) -> 3 | G83: =COUNTIFS('Data Angt'!$C$5:$C$5809,G$46,'Data Angt'!$F$5:$F$5809,"<=45",'Data Angt'!$H$5:$H$5809,$C83)-COUNTIFS('Data Angt'!$C$5:$C$5809,G$46,'Data Angt'!$F$5:$F$5809,"<36",'Data Angt'!$H$5:$H$5809,$C83) -> 4 | H83: =COUNTIFS('Data Angt'!$C$5:$C$5809,H$46,'Data Angt'!$F$5:$F$5809,"<=45",'Data Angt'!$H$5:$H$5809,$C83)-COUNTIFS('Data Angt'!$C$5:$C$5809,H$46,'Data Angt'!$F$5:$F$5809,"<36",'Data Angt'!$H$5:$H$5809,$C83) -> 3 | I83: =COUNTIFS('Data Angt'!$C$5:$C$5809,I$46,'Data Angt'!$F$5:$F$5809,"<=45",'Data Angt'!$H$5:$H$5809,$C83)-COUNTIFS('Data Angt'!$C$5:$C$5809,I$46,'Data Angt'!$F$5:$F$5809,"<36",'Data Angt'!$H$5:$H$5809,$C83) -> 1 | J83: =COUNTIFS('Data Angt'!$C$5:$C$5809,J$46,'Data Angt'!$F$5:$F$5809,"<=45",'Data Angt'!$H$5:$H$5809,$C83)-COUNTIFS('Data Angt'!$C$5:$C$5809,J$46,'Data Angt'!$F$5:$F$5809,"<36",'Data Angt'!$H$5:$H$5809,$C83) -> 2 | K83: =COUNTIFS('Data Angt'!$C$5:$C$5809,K$46,'Data Angt'!$F$5:$F$5809,"<=45",'Data Angt'!$H$5:$H$5809,$C83)-COUNTIFS('Data Angt'!$C$5:$C$5809,K$46,'Data Angt'!$F$5:$F$5809,"<36",'Data Angt'!$H$5:$H$5809,$C83) -> 1 | L83: =COUNTIFS('Data Angt'!$C$5:$C$5809,L$46,'Data Angt'!$F$5:$F$5809,"<=45",'Data Angt'!$H$5:$H$5809,$C83)-COUNTIFS('Data Angt'!$C$5:$C$5809,L$46,'Data Angt'!$F$5:$F$5809,"<36",'Data Angt'!$H$5:$H$5809,$C83) -> 0
C84: Petani/Pekebun/Nelayan | D84: =COUNTIFS('Data Angt'!$F$5:$F$5809,"<=45",'Data Angt'!$H$5:$H$5809,C84)-COUNTIFS('Data Angt'!$F$5:$F$5809,"<36",'Data Angt'!$H$5:$H$5809,C84) -> 6 | E84: =D84/$C$42 -> 0.0010335917 | F84: =COUNTIFS('Data Angt'!$C$5:$C$5809,F$46,'Data Angt'!$F$5:$F$5809,"<=45",'Data Angt'!$H$5:$H$5809,$C84)-COUNTIFS('Data Angt'!$C$5:$C$5809,F$46,'Data Angt'!$F$5:$F$5809,"<36",'Data Angt'!$H$5:$H$5809,$C84) -> 0 | G84: =COUNTIFS('Data Angt'!$C$5:$C$5809,G$46,'Data Angt'!$F$5:$F$5809,"<=45",'Data Angt'!$H$5:$H$5809,$C84)-COUNTIFS('Data Angt'!$C$5:$C$5809,G$46,'Data Angt'!$F$5:$F$5809,"<36",'Data Angt'!$H$5:$H$5809,$C84) -> 5 | H84: =COUNTIFS('Data Angt'!$C$5:$C$5809,H$46,'Data Angt'!$F$5:$F$5809,"<=45",'Data Angt'!$H$5:$H$5809,$C84)-COUNTIFS('Data Angt'!$C$5:$C$5809,H$46,'Data Angt'!$F$5:$F$5809,"<36",'Data Angt'!$H$5:$H$5809,$C84) -> 0 | I84: =COUNTIFS('Data Angt'!$C$5:$C$5809,I$46,'Data Angt'!$F$5:$F$5809,"<=45",'Data Angt'!$H$5:$H$5809,$C84)-COUNTIFS('Data Angt'!$C$5:$C$5809,I$46,'Data Angt'!$F$5:$F$5809,"<36",'Data Angt'!$H$5:$H$5809,$C84) -> 0 | J84: =COUNTIFS('Data Angt'!$C$5:$C$5809,J$46,'Data Angt'!$F$5:$F$5809,"<=45",'Data Angt'!$H$5:$H$5809,$C84)-COUNTIFS('Data Angt'!$C$5:$C$5809,J$46,'Data Angt'!$F$5:$F$5809,"<36",'Data Angt'!$H$5:$H$5809,$C84) -> 0 | K84: =COUNTIFS('Data Angt'!$C$5:$C$5809,K$46,'Data Angt'!$F$5:$F$5809,"<=45",'Data Angt'!$H$5:$H$5809,$C84)-COUNTIFS('Data Angt'!$C$5:$C$5809,K$46,'Data Angt'!$F$5:$F$5809,"<36",'Data Angt'!$H$5:$H$5809,$C84) -> 1 | L84: =COUNTIFS('Data Angt'!$C$5:$C$5809,L$46,'Data Angt'!$F$5:$F$5809,"<=45",'Data Angt'!$H$5:$H$5809,$C84)-COUNTIFS('Data Angt'!$C$5:$C$5809,L$46,'Data Angt'!$F$5:$F$5809,"<36",'Data Angt'!$H$5:$H$5809,$C84) -> 0
C85: Pensiunan | D85: =COUNTIFS('Data Angt'!$F$5:$F$5809,"<=45",'Data Angt'!$H$5:$H$5809,C85)-COUNTIFS('Data Angt'!$F$5:$F$5809,"<36",'Data Angt'!$H$5:$H$5809,C85) -> 0 | E85: =D85/$C$42 -> 0 | F85: =COUNTIFS('Data Angt'!$C$5:$C$5809,F$46,'Data Angt'!$F$5:$F$5809,"<=45",'Data Angt'!$H$5:$H$5809,$C85)-COUNTIFS('Data Angt'!$C$5:$C$5809,F$46,'Data Angt'!$F$5:$F$5809,"<36",'Data Angt'!$H$5:$H$5809,$C85) -> 0 | G85: =COUNTIFS('Data Angt'!$C$5:$C$5809,G$46,'Data Angt'!$F$5:$F$5809,"<=45",'Data Angt'!$H$5:$H$5809,$C85)-COUNTIFS('Data Angt'!$C$5:$C$5809,G$46,'Data Angt'!$F$5:$F$5809,"<36",'Data Angt'!$H$5:$H$5809,$C85) -> 0 | H85: =COUNTIFS('Data Angt'!$C$5:$C$5809,H$46,'Data Angt'!$F$5:$F$5809,"<=45",'Data Angt'!$H$5:$H$5809,$C85)-COUNTIFS('Data Angt'!$C$5:$C$5809,H$46,'Data Angt'!$F$5:$F$5809,"<36",'Data Angt'!$H$5:$H$5809,$C85) -> 0 | I85: =COUNTIFS('Data Angt'!$C$5:$C$5809,I$46,'Data Angt'!$F$5:$F$5809,"<=45",'Data Angt'!$H$5:$H$5809,$C85)-COUNTIFS('Data Angt'!$C$5:$C$5809,I$46,'Data Angt'!$F$5:$F$5809,"<36",'Data Angt'!$H$5:$H$5809,$C85) -> 0 | J85: =COUNTIFS('Data Angt'!$C$5:$C$5809,J$46,'Data Angt'!$F$5:$F$5809,"<=45",'Data Angt'!$H$5:$H$5809,$C85)-COUNTIFS('Data Angt'!$C$5:$C$5809,J$46,'Data Angt'!$F$5:$F$5809,"<36",'Data Angt'!$H$5:$H$5809,$C85) -> 0 | K85: =COUNTIFS('Data Angt'!$C$5:$C$5809,K$46,'Data Angt'!$F$5:$F$5809,"<=45",'Data Angt'!$H$5:$H$5809,$C85)-COUNTIFS('Data Angt'!$C$5:$C$5809,K$46,'Data Angt'!$F$5:$F$5809,"<36",'Data Angt'!$H$5:$H$5809,$C85) -> 0 | L85: =COUNTIFS('Data Angt'!$C$5:$C$5809,L$46,'Data Angt'!$F$5:$F$5809,"<=45",'Data Angt'!$H$5:$H$5809,$C85)-COUNTIFS('Data Angt'!$C$5:$C$5809,L$46,'Data Angt'!$F$5:$F$5809,"<36",'Data Angt'!$H$5:$H$5809,$C85) -> 0
C86: Belum/Tidak Bekerja | D86: =COUNTIFS('Data Angt'!$F$5:$F$5809,"<=45",'Data Angt'!$H$5:$H$5809,C86)-COUNTIFS('Data Angt'!$F$5:$F$5809,"<36",'Data Angt'!$H$5:$H$5809,C86) -> 12 | E86: =D86/$C$42 -> 0.0020671835 | F86: =COUNTIFS('Data Angt'!$C$5:$C$5809,F$46,'Data Angt'!$F$5:$F$5809,"<=45",'Data Angt'!$H$5:$H$5809,$C86)-COUNTIFS('Data Angt'!$C$5:$C$5809,F$46,'Data Angt'!$F$5:$F$5809,"<36",'Data Angt'!$H$5:$H$5809,$C86) -> 4 | G86: =COUNTIFS('Data Angt'!$C$5:$C$5809,G$46,'Data Angt'!$F$5:$F$5809,"<=45",'Data Angt'!$H$5:$H$5809,$C86)-COUNTIFS('Data Angt'!$C$5:$C$5809,G$46,'Data Angt'!$F$5:$F$5809,"<36",'Data Angt'!$H$5:$H$5809,$C86) -> 1 | H86: =COUNTIFS('Data Angt'!$C$5:$C$5809,H$46,'Data Angt'!$F$5:$F$5809,"<=45",'Data Angt'!$H$5:$H$5809,$C86)-COUNTIFS('Data Angt'!$C$5:$C$5809,H$46,'Data Angt'!$F$5:$F$5809,"<36",'Data Angt'!$H$5:$H$5809,$C86) -> 1 | I86: =COUNTIFS('Data Angt'!$C$5:$C$5809,I$46,'Data Angt'!$F$5:$F$5809,"<=45",'Data Angt'!$H$5:$H$5809,$C86)-COUNTIFS('Data Angt'!$C$5:$C$5809,I$46,'Data Angt'!$F$5:$F$5809,"<36",'Data Angt'!$H$5:$H$5809,$C86) -> 0 | J86: =COUNTIFS('Data Angt'!$C$5:$C$5809,J$46,'Data Angt'!$F$5:$F$5809,"<=45",'Data Angt'!$H$5:$H$5809,$C86)-COUNTIFS('Data Angt'!$C$5:$C$5809,J$46,'Data Angt'!$F$5:$F$5809,"<36",'Data Angt'!$H$5:$H$5809,$C86) -> 3 | K86: =COUNTIFS('Data Angt'!$C$5:$C$5809,K$46,'Data Angt'!$F$5:$F$5809,"<=45",'Data Angt'!$H$5:$H$5809,$C86)-COUNTIFS('Data Angt'!$C$5:$C$5809,K$46,'Data Angt'!$F$5:$F$5809,"<36",'Data Angt'!$H$5:$H$5809,$C86) -> 3 | L86: =COUNTIFS('Data Angt'!$C$5:$C$5809,L$46,'Data Angt'!$F$5:$F$5809,"<=45",'Data Angt'!$H$5:$H$5809,$C86)-COUNTIFS('Data Angt'!$C$5:$C$5809,L$46,'Data Angt'!$F$5:$F$5809,"<36",'Data Angt'!$H$5:$H$5809,$C86) -> 0
C87: Lain-lain | D87: =COUNTIFS('Data Angt'!$F$5:$F$5809,"<=45",'Data Angt'!$H$5:$H$5809,C87)-COUNTIFS('Data Angt'!$F$5:$F$5809,"<36",'Data Angt'!$H$5:$H$5809,C87) -> 68 | E87: =D87/$C$42 -> 0.01171404 | F87: =COUNTIFS('Data Angt'!$C$5:$C$5809,F$46,'Data Angt'!$F$5:$F$5809,"<=45",'Data Angt'!$H$5:$H$5809,$C87)-COUNTIFS('Data Angt'!$C$5:$C$5809,F$46,'Data Angt'!$F$5:$F$5809,"<36",'Data Angt'!$H$5:$H$5809,$C87) -> 41 | G87: =COUNTIFS('Data Angt'!$C$5:$C$5809,G$46,'Data Angt'!$F$5:$F$5809,"<=45",'Data Angt'!$H$5:$H$5809,$C87)-COUNTIFS('Data Angt'!$C$5:$C$5809,G$46,'Data Angt'!$F$5:$F$5809,"<36",'Data Angt'!$H$5:$H$5809,$C87) -> 8 | H87: =COUNTIFS('Data Angt'!$C$5:$C$5809,H$46,'Data Angt'!$F$5:$F$5809,"<=45",'Data Angt'!$H$5:$H$5809,$C87)-COUNTIFS('Data Angt'!$C$5:$C$5809,H$46,'Data Angt'!$F$5:$F$5809,"<36",'Data Angt'!$H$5:$H$5809,$C87) -> 4 | I87: =COUNTIFS('Data Angt'!$C$5:$C$5809,I$46,'Data Angt'!$F$5:$F$5809,"<=45",'Data Angt'!$H$5:$H$5809,$C87)-COUNTIFS('Data Angt'!$C$5:$C$5809,I$46,'Data Angt'!$F$5:$F$5809,"<36",'Data Angt'!$H$5:$H$5809,$C87) -> 5 | J87: =COUNTIFS('Data Angt'!$C$5:$C$5809,J$46,'Data Angt'!$F$5:$F$5809,"<=45",'Data Angt'!$H$5:$H$5809,$C87)-COUNTIFS('Data Angt'!$C$5:$C$5809,J$46,'Data Angt'!$F$5:$F$5809,"<36",'Data Angt'!$H$5:$H$5809,$C87) -> 2 | K87: =COUNTIFS('Data Angt'!$C$5:$C$5809,K$46,'Data Angt'!$F$5:$F$5809,"<=45",'Data Angt'!$H$5:$H$5809,$C87)-COUNTIFS('Data Angt'!$C$5:$C$5809,K$46,'Data Angt'!$F$5:$F$5809,"<36",'Data Angt'!$H$5:$H$5809,$C87) -> 8 | L87: =COUNTIFS('Data Angt'!$C$5:$C$5809,L$46,'Data Angt'!$F$5:$F$5809,"<=45",'Data Angt'!$H$5:$H$5809,$C87)-COUNTIFS('Data Angt'!$C$5:$C$5809,L$46,'Data Angt'!$F$5:$F$5809,"<36",'Data Angt'!$H$5:$H$5809,$C87) -> 0
C88: Kosong | D88: =COUNTIFS('Data Angt'!$F$5:$F$5809,"<=45",'Data Angt'!$H$5:$H$5809,"")-COUNTIFS('Data Angt'!$F$5:$F$5809,"<36",'Data Angt'!$H$5:$H$5809,"") -> 67 | E88: =D88/$C$42 -> 0.011541774 | F88: =COUNTIFS('Data Angt'!$C$5:$C$5809,F$46,'Data Angt'!$F$5:$F$5809,"<=45",'Data Angt'!$H$5:$H$5809,"")-COUNTIFS('Data Angt'!$C$5:$C$5809,F$46,'Data Angt'!$F$5:$F$5809,"<36",'Data Angt'!$H$5:$H$5809,"") -> 50 | G88: =COUNTIFS('Data Angt'!$C$5:$C$5809,G$46,'Data Angt'!$F$5:$F$5809,"<=45",'Data Angt'!$H$5:$H$5809,"")-COUNTIFS('Data Angt'!$C$5:$C$5809,G$46,'Data Angt'!$F$5:$F$5809,"<36",'Data Angt'!$H$5:$H$5809,"") -> 11 | H88: =COUNTIFS('Data Angt'!$C$5:$C$5809,H$46,'Data Angt'!$F$5:$F$5809,"<=45",'Data Angt'!$H$5:$H$5809,"")-COUNTIFS('Data Angt'!$C$5:$C$5809,H$46,'Data Angt'!$F$5:$F$5809,"<36",'Data Angt'!$H$5:$H$5809,"") -> 0 | I88: =COUNTIFS('Data Angt'!$C$5:$C$5809,I$46,'Data Angt'!$F$5:$F$5809,"<=45",'Data Angt'!$H$5:$H$5809,"")-COUNTIFS('Data Angt'!$C$5:$C$5809,I$46,'Data Angt'!$F$5:$F$5809,"<36",'Data Angt'!$H$5:$H$5809,"") -> 0 | J88: =COUNTIFS('Data Angt'!$C$5:$C$5809,J$46,'Data Angt'!$F$5:$F$5809,"<=45",'Data Angt'!$H$5:$H$5809,"")-COUNTIFS('Data Angt'!$C$5:$C$5809,J$46,'Data Angt'!$F$5:$F$5809,"<36",'Data Angt'!$H$5:$H$5809,"") -> 0 | K88: =COUNTIFS('Data Angt'!$C$5:$C$5809,K$46,'Data Angt'!$F$5:$F$5809,"<=45",'Data Angt'!$H$5:$H$5809,"")-COUNTIFS('Data Angt'!$C$5:$C$5809,K$46,'Data Angt'!$F$5:$F$5809,"<36",'Data Angt'!$H$5:$H$5809,"") -> 2 | L88: =COUNTIFS('Data Angt'!$C$5:$C$5809,L$46,'Data Angt'!$F$5:$F$5809,"<=45",'Data Angt'!$H$5:$H$5809,"")-COUNTIFS('Data Angt'!$C$5:$C$5809,L$46,'Data Angt'!$F$5:$F$5809,"<36",'Data Angt'!$H$5:$H$5809,"") -> 4
B89: 46 - 60 Th | C89: Wiraswasta | D89: =COUNTIFS('Data Angt'!$F$5:$F$5809,"<=60",'Data Angt'!$H$5:$H$5809,C89)-COUNTIFS('Data Angt'!$F$5:$F$5809,"<46",'Data Angt'!$H$5:$H$5809,C89) -> 626 | E89: =D89/$C$42 -> 0.10783807 | F89: =COUNTIFS('Data Angt'!$C$5:$C$5809,F$46,'Data Angt'!$F$5:$F$5809,"<=60",'Data Angt'!$H$5:$H$5809,$C89)-COUNTIFS('Data Angt'!$C$5:$C$5809,F$46,'Data Angt'!$F$5:$F$5809,"<46",'Data Angt'!$H$5:$H$5809,$C89) -> 235 | G89: =COUNTIFS('Data Angt'!$C$5:$C$5809,G$46,'Data Angt'!$F$5:$F$5809,"<=60",'Data Angt'!$H$5:$H$5809,$C89)-COUNTIFS('Data Angt'!$C$5:$C$5809,G$46,'Data Angt'!$F$5:$F$5809,"<46",'Data Angt'!$H$5:$H$5809,$C89) -> 84 | H89: =COUNTIFS('Data Angt'!$C$5:$C$5809,H$46,'Data Angt'!$F$5:$F$5809,"<=60",'Data Angt'!$H$5:$H$5809,$C89)-COUNTIFS('Data Angt'!$C$5:$C$5809,H$46,'Data Angt'!$F$5:$F$5809,"<46",'Data Angt'!$H$5:$H$5809,$C89) -> 94 | I89: =COUNTIFS('Data Angt'!$C$5:$C$5809,I$46,'Data Angt'!$F$5:$F$5809,"<=60",'Data Angt'!$H$5:$H$5809,$C89)-COUNTIFS('Data Angt'!$C$5:$C$5809,I$46,'Data Angt'!$F$5:$F$5809,"<46",'Data Angt'!$H$5:$H$5809,$C89) -> 69 | J89: =COUNTIFS('Data Angt'!$C$5:$C$5809,J$46,'Data Angt'!$F$5:$F$5809,"<=60",'Data Angt'!$H$5:$H$5809,$C89)-COUNTIFS('Data Angt'!$C$5:$C$5809,J$46,'Data Angt'!$F$5:$F$5809,"<46",'Data Angt'!$H$5:$H$5809,$C89) -> 66 | K89: =COUNTIFS('Data Angt'!$C$5:$C$5809,K$46,'Data Angt'!$F$5:$F$5809,"<=60",'Data Angt'!$H$5:$H$5809,$C89)-COUNTIFS('Data Angt'!$C$5:$C$5809,K$46,'Data Angt'!$F$5:$F$5809,"<46",'Data Angt'!$H$5:$H$5809,$C89) -> 77 | L89: =COUNTIFS('Data Angt'!$C$5:$C$5809,L$46,'Data Angt'!$F$5:$F$5809,"<=60",'Data Angt'!$H$5:$H$5809,$C89)-COUNTIFS('Data Angt'!$C$5:$C$5809,L$46,'Data Angt'!$F$5:$F$5809,"<46",'Data Angt'!$H$5:$H$5809,$C89) -> 1
C90: Karyawan | D90: =COUNTIFS('Data Angt'!$F$5:$F$5809,"<=60",'Data Angt'!$H$5:$H$5809,C90)-COUNTIFS('Data Angt'!$F$5:$F$5809,"<46",'Data Angt'!$H$5:$H$5809,C90) -> 488 | E90: =D90/$C$42 -> 0.084065461 | F90: =COUNTIFS('Data Angt'!$C$5:$C$5809,F$46,'Data Angt'!$F$5:$F$5809,"<=60",'Data Angt'!$H$5:$H$5809,$C90)-COUNTIFS('Data Angt'!$C$5:$C$5809,F$46,'Data Angt'!$F$5:$F$5809,"<46",'Data Angt'!$H$5:$H$5809,$C90) -> 181 | G90: =COUNTIFS('Data Angt'!$C$5:$C$5809,G$46,'Data Angt'!$F$5:$F$5809,"<=60",'Data Angt'!$H$5:$H$5809,$C90)-COUNTIFS('Data Angt'!$C$5:$C$5809,G$46,'Data Angt'!$F$5:$F$5809,"<46",'Data Angt'!$H$5:$H$5809,$C90) -> 62 | H90: =COUNTIFS('Data Angt'!$C$5:$C$5809,H$46,'Data Angt'!$F$5:$F$5809,"<=60",'Data Angt'!$H$5:$H$5809,$C90)-COUNTIFS('Data Angt'!$C$5:$C$5809,H$46,'Data Angt'!$F$5:$F$5809,"<46",'Data Angt'!$H$5:$H$5809,$C90) -> 84 | I90: =COUNTIFS('Data Angt'!$C$5:$C$5809,I$46,'Data Angt'!$F$5:$F$5809,"<=60",'Data Angt'!$H$5:$H$5809,$C90)-COUNTIFS('Data Angt'!$C$5:$C$5809,I$46,'Data Angt'!$F$5:$F$5809,"<46",'Data Angt'!$H$5:$H$5809,$C90) -> 25 | J90: =COUNTIFS('Data Angt'!$C$5:$C$5809,J$46,'Data Angt'!$F$5:$F$5809,"<=60",'Data Angt'!$H$5:$H$5809,$C90)-COUNTIFS('Data Angt'!$C$5:$C$5809,J$46,'Data Angt'!$F$5:$F$5809,"<46",'Data Angt'!$H$5:$H$5809,$C90) -> 35 | K90: =COUNTIFS('Data Angt'!$C$5:$C$5809,K$46,'Data Angt'!$F$5:$F$5809,"<=60",'Data Angt'!$H$5:$H$5809,$C90)-COUNTIFS('Data Angt'!$C$5:$C$5809,K$46,'Data Angt'!$F$5:$F$5809,"<46",'Data Angt'!$H$5:$H$5809,$C90) -> 73 | L90: =COUNTIFS('Data Angt'!$C$5:$C$5809,L$46,'Data Angt'!$F$5:$F$5809,"<=60",'Data Angt'!$H$5:$H$5809,$C90)-COUNTIFS('Data Angt'!$C$5:$C$5809,L$46,'Data Angt'!$F$5:$F$5809,"<46",'Data Angt'!$H$5:$H$5809,$C90) -> 28
C91: Tenaga Pengajar | D91: =COUNTIFS('Data Angt'!$F$5:$F$5809,"<=60",'Data Angt'!$H$5:$H$5809,C91)-COUNTIFS('Data Angt'!$F$5:$F$5809,"<46",'Data Angt'!$H$5:$H$5809,C91) -> 218 | E91: =D91/$C$42 -> 0.037553833 | F91: =COUNTIFS('Data Angt'!$C$5:$C$5809,F$46,'Data Angt'!$F$5:$F$5809,"<=60",'Data Angt'!$H$5:$H$5809,$C91)-COUNTIFS('Data Angt'!$C$5:$C$5809,F$46,'Data Angt'!$F$5:$F$5809,"<46",'Data Angt'!$H$5:$H$5809,$C91) -> 78 | G91: =COUNTIFS('Data Angt'!$C$5:$C$5809,G$46,'Data Angt'!$F$5:$F$5809,"<=60",'Data Angt'!$H$5:$H$5809,$C91)-COUNTIFS('Data Angt'!$C$5:$C$5809,G$46,'Data Angt'!$F$5:$F$5809,"<46",'Data Angt'!$H$5:$H$5809,$C91) -> 30 | H91: =COUNTIFS('Data Angt'!$C$5:$C$5809,H$46,'Data Angt'!$F$5:$F$5809,"<=60",'Data Angt'!$H$5:$H$5809,$C91)-COUNTIFS('Data Angt'!$C$5:$C$5809,H$46,'Data Angt'!$F$5:$F$5809,"<46",'Data Angt'!$H$5:$H$5809,$C91) -> 61 | I91: =COUNTIFS('Data Angt'!$C$5:$C$5809,I$46,'Data Angt'!$F$5:$F$5809,"<=60",'Data Angt'!$H$5:$H$5809,$C91)-COUNTIFS('Data Angt'!$C$5:$C$5809,I$46,'Data Angt'!$F$5:$F$5809,"<46",'Data Angt'!$H$5:$H$5809,$C91) -> 21 | J91: =COUNTIFS('Data Angt'!$C$5:$C$5809,J$46,'Data Angt'!$F$5:$F$5809,"<=60",'Data Angt'!$H$5:$H$5809,$C91)-COUNTIFS('Data Angt'!$C$5:$C$5809,J$46,'Data Angt'!$F$5:$F$5809,"<46",'Data Angt'!$H$5:$H$5809,$C91) -> 12 | K91: =COUNTIFS('Data Angt'!$C$5:$C$5809,K$46,'Data Angt'!$F$5:$F$5809,"<=60",'Data Angt'!$H$5:$H$5809,$C91)-COUNTIFS('Data Angt'!$C$5:$C$5809,K$46,'Data Angt'!$F$5:$F$5809,"<46",'Data Angt'!$H$5:$H$5809,$C91) -> 15 | L91: =COUNTIFS('Data Angt'!$C$5:$C$5809,L$46,'Data Angt'!$F$5:$F$5809,"<=60",'Data Angt'!$H$5:$H$5809,$C91)-COUNTIFS('Data Angt'!$C$5:$C$5809,L$46,'Data Angt'!$F$5:$F$5809,"<46",'Data Angt'!$H$5:$H$5809,$C91) -> 1
C92: Aparatur/Pejabat Negara | D92: =COUNTIFS('Data Angt'!$F$5:$F$5809,"<=60",'Data Angt'!$H$5:$H$5809,C92)-COUNTIFS('Data Angt'!$F$5:$F$5809,"<46",'Data Angt'!$H$5:$H$5809,C92) -> 107 | E92: =D92/$C$42 -> 0.018432386 | F92: =COUNTIFS('Data Angt'!$C$5:$C$5809,F$46,'Data Angt'!$F$5:$F$5809,"<=60",'Data Angt'!$H$5:$H$5809,$C92)-COUNTIFS('Data Angt'!$C$5:$C$5809,F$46,'Data Angt'!$F$5:$F$5809,"<46",'Data Angt'!$H$5:$H$5809,$C92) -> 65 | G92: =COUNTIFS('Data Angt'!$C$5:$C$5809,G$46,'Data Angt'!$F$5:$F$5809,"<=60",'Data Angt'!$H$5:$H$5809,$C92)-COUNTIFS('Data Angt'!$C$5:$C$5809,G$46,'Data Angt'!$F$5:$F$5809,"<46",'Data Angt'!$H$5:$H$5809,$C92) -> 14 | H92: =COUNTIFS('Data Angt'!$C$5:$C$5809,H$46,'Data Angt'!$F$5:$F$5809,"<=60",'Data Angt'!$H$5:$H$5809,$C92)-COUNTIFS('Data Angt'!$C$5:$C$5809,H$46,'Data Angt'!$F$5:$F$5809,"<46",'Data Angt'!$H$5:$H$5809,$C92) -> 6 | I92: =COUNTIFS('Data Angt'!$C$5:$C$5809,I$46,'Data Angt'!$F$5:$F$5809,"<=60",'Data Angt'!$H$5:$H$5809,$C92)-COUNTIFS('Data Angt'!$C$5:$C$5809,I$46,'Data Angt'!$F$5:$F$5809,"<46",'Data Angt'!$H$5:$H$5809,$C92) -> 9 | J92: =COUNTIFS('Data Angt'!$C$5:$C$5809,J$46,'Data Angt'!$F$5:$F$5809,"<=60",'Data Angt'!$H$5:$H$5809,$C92)-COUNTIFS('Data Angt'!$C$5:$C$5809,J$46,'Data Angt'!$F$5:$F$5809,"<46",'Data Angt'!$H$5:$H$5809,$C92) -> 6 | K92: =COUNTIFS('Data Angt'!$C$5:$C$5809,K$46,'Data Angt'!$F$5:$F$5809,"<=60",'Data Angt'!$H$5:$H$5809,$C92)-COUNTIFS('Data Angt'!$C$5:$C$5809,K$46,'Data Angt'!$F$5:$F$5809,"<46",'Data Angt'!$H$5:$H$5809,$C92) -> 4 | L92: =COUNTIFS('Data Angt'!$C$5:$C$5809,L$46,'Data Angt'!$F$5:$F$5809,"<=60",'Data Angt'!$H$5:$H$5809,$C92)-COUNTIFS('Data Angt'!$C$5:$C$5809,L$46,'Data Angt'!$F$5:$F$5809,"<46",'Data Angt'!$H$5:$H$5809,$C92) -> 3
C93: Pelajar/Mahasiswa | D93: =COUNTIFS('Data Angt'!$F$5:$F$5809,"<=60",'Data Angt'!$H$5:$H$5809,C93)-COUNTIFS('Data Angt'!$F$5:$F$5809,"<46",'Data Angt'!$H$5:$H$5809,C93) -> 1 | E93: =D93/$C$42 -> 0.00017226529 | F93: =COUNTIFS('Data Angt'!$C$5:$C$5809,F$46,'Data Angt'!$F$5:$F$5809,"<=60",'Data Angt'!$H$5:$H$5809,$C93)-COUNTIFS('Data Angt'!$C$5:$C$5809,F$46,'Data Angt'!$F$5:$F$5809,"<46",'Data Angt'!$H$5:$H$5809,$C93) -> 0 | G93: =COUNTIFS('Data Angt'!$C$5:$C$5809,G$46,'Data Angt'!$F$5:$F$5809,"<=60",'Data Angt'!$H$5:$H$5809,$C93)-COUNTIFS('Data Angt'!$C$5:$C$5809,G$46,'Data Angt'!$F$5:$F$5809,"<46",'Data Angt'!$H$5:$H$5809,$C93) -> 0 | H93: =COUNTIFS('Data Angt'!$C$5:$C$5809,H$46,'Data Angt'!$F$5:$F$5809,"<=60",'Data Angt'!$H$5:$H$5809,$C93)-COUNTIFS('Data Angt'!$C$5:$C$5809,H$46,'Data Angt'!$F$5:$F$5809,"<46",'Data Angt'!$H$5:$H$5809,$C93) -> 0 | I93: =COUNTIFS('Data Angt'!$C$5:$C$5809,I$46,'Data Angt'!$F$5:$F$5809,"<=60",'Data Angt'!$H$5:$H$5809,$C93)-COUNTIFS('Data Angt'!$C$5:$C$5809,I$46,'Data Angt'!$F$5:$F$5809,"<46",'Data Angt'!$H$5:$H$5809,$C93) -> 0 | J93: =COUNTIFS('Data Angt'!$C$5:$C$5809,J$46,'Data Angt'!$F$5:$F$5809,"<=60",'Data Angt'!$H$5:$H$5809,$C93)-COUNTIFS('Data Angt'!$C$5:$C$5809,J$46,'Data Angt'!$F$5:$F$5809,"<46",'Data Angt'!$H$5:$H$5809,$C93) -> 0 | K93: =COUNTIFS('Data Angt'!$C$5:$C$5809,K$46,'Data Angt'!$F$5:$F$5809,"<=60",'Data Angt'!$H$5:$H$5809,$C93)-COUNTIFS('Data Angt'!$C$5:$C$5809,K$46,'Data Angt'!$F$5:$F$5809,"<46",'Data Angt'!$H$5:$H$5809,$C93) -> 1 | L93: =COUNTIFS('Data Angt'!$C$5:$C$5809,L$46,'Data Angt'!$F$5:$F$5809,"<=60",'Data Angt'!$H$5:$H$5809,$C93)-COUNTIFS('Data Angt'!$C$5:$C$5809,L$46,'Data Angt'!$F$5:$F$5809,"<46",'Data Angt'!$H$5:$H$5809,$C93) -> 0
C94: Pemuka Agama | D94: =COUNTIFS('Data Angt'!$F$5:$F$5809,"<=60",'Data Angt'!$H$5:$H$5809,C94)-COUNTIFS('Data Angt'!$F$5:$F$5809,"<46",'Data Angt'!$H$5:$H$5809,C94) -> 31 | E94: =D94/$C$42 -> 0.0053402239 | F94: =COUNTIFS('Data Angt'!$C$5:$C$5809,F$46,'Data Angt'!$F$5:$F$5809,"<=60",'Data Angt'!$H$5:$H$5809,$C94)-COUNTIFS('Data Angt'!$C$5:$C$5809,F$46,'Data Angt'!$F$5:$F$5809,"<46",'Data Angt'!$H$5:$H$5809,$C94) -> 20 | G94: =COUNTIFS('Data Angt'!$C$5:$C$5809,G$46,'Data Angt'!$F$5:$F$5809,"<=60",'Data Angt'!$H$5:$H$5809,$C94)-COUNTIFS('Data Angt'!$C$5:$C$5809,G$46,'Data Angt'!$F$5:$F$5809,"<46",'Data Angt'!$H$5:$H$5809,$C94) -> 0 | H94: =COUNTIFS('Data Angt'!$C$5:$C$5809,H$46,'Data Angt'!$F$5:$F$5809,"<=60",'Data Angt'!$H$5:$H$5809,$C94)-COUNTIFS('Data Angt'!$C$5:$C$5809,H$46,'Data Angt'!$F$5:$F$5809,"<46",'Data Angt'!$H$5:$H$5809,$C94) -> 6 | I94: =COUNTIFS('Data Angt'!$C$5:$C$5809,I$46,'Data Angt'!$F$5:$F$5809,"<=60",'Data Angt'!$H$5:$H$5809,$C94)-COUNTIFS('Data Angt'!$C$5:$C$5809,I$46,'Data Angt'!$F$5:$F$5809,"<46",'Data Angt'!$H$5:$H$5809,$C94) -> 1 | J94: =COUNTIFS('Data Angt'!$C$5:$C$5809,J$46,'Data Angt'!$F$5:$F$5809,"<=60",'Data Angt'!$H$5:$H$5809,$C94)-COUNTIFS('Data Angt'!$C$5:$C$5809,J$46,'Data Angt'!$F$5:$F$5809,"<46",'Data Angt'!$H$5:$H$5809,$C94) -> 0 | K94: =COUNTIFS('Data Angt'!$C$5:$C$5809,K$46,'Data Angt'!$F$5:$F$5809,"<=60",'Data Angt'!$H$5:$H$5809,$C94)-COUNTIFS('Data Angt'!$C$5:$C$5809,K$46,'Data Angt'!$F$5:$F$5809,"<46",'Data Angt'!$H$5:$H$5809,$C94) -> 3 | L94: =COUNTIFS('Data Angt'!$C$5:$C$5809,L$46,'Data Angt'!$F$5:$F$5809,"<=60",'Data Angt'!$H$5:$H$5809,$C94)-COUNTIFS('Data Angt'!$C$5:$C$5809,L$46,'Data Angt'!$F$5:$F$5809,"<46",'Data Angt'!$H$5:$H$5809,$C94) -> 1
C95: Mengurus Rumah Tangga | D95: =COUNTIFS('Data Angt'!$F$5:$F$5809,"<=60",'Data Angt'!$H$5:$H$5809,C95)-COUNTIFS('Data Angt'!$F$5:$F$5809,"<46",'Data Angt'!$H$5:$H$5809,C95) -> 339 | E95: =D95/$C$42 -> 0.058397933 | F95: =COUNTIFS('Data Angt'!$C$5:$C$5809,F$46,'Data Angt'!$F$5:$F$5809,"<=60",'Data Angt'!$H$5:$H$5809,$C95)-COUNTIFS('Data Angt'!$C$5:$C$5809,F$46,'Data Angt'!$F$5:$F$5809,"<46",'Data Angt'!$H$5:$H$5809,$C95) -> 143 | G95: =COUNTIFS('Data Angt'!$C$5:$C$5809,G$46,'Data Angt'!$F$5:$F$5809,"<=60",'Data Angt'!$H$5:$H$5809,$C95)-COUNTIFS('Data Angt'!$C$5:$C$5809,G$46,'Data Angt'!$F$5:$F$5809,"<46",'Data Angt'!$H$5:$H$5809,$C95) -> 28 | H95: =COUNTIFS('Data Angt'!$C$5:$C$5809,H$46,'Data Angt'!$F$5:$F$5809,"<=60",'Data Angt'!$H$5:$H$5809,$C95)-COUNTIFS('Data Angt'!$C$5:$C$5809,H$46,'Data Angt'!$F$5:$F$5809,"<46",'Data Angt'!$H$5:$H$5809,$C95) -> 96 | I95: =COUNTIFS('Data Angt'!$C$5:$C$5809,I$46,'Data Angt'!$F$5:$F$5809,"<=60",'Data Angt'!$H$5:$H$5809,$C95)-COUNTIFS('Data Angt'!$C$5:$C$5809,I$46,'Data Angt'!$F$5:$F$5809,"<46",'Data Angt'!$H$5:$H$5809,$C95) -> 21 | J95: =COUNTIFS('Data Angt'!$C$5:$C$5809,J$46,'Data Angt'!$F$5:$F$5809,"<=60",'Data Angt'!$H$5:$H$5809,$C95)-COUNTIFS('Data Angt'!$C$5:$C$5809,J$46,'Data Angt'!$F$5:$F$5809,"<46",'Data Angt'!$H$5:$H$5809,$C95) -> 16 | K95: =COUNTIFS('Data Angt'!$C$5:$C$5809,K$46,'Data Angt'!$F$5:$F$5809,"<=60",'Data Angt'!$H$5:$H$5809,$C95)-COUNTIFS('Data Angt'!$C$5:$C$5809,K$46,'Data Angt'!$F$5:$F$5809,"<46",'Data Angt'!$H$5:$H$5809,$C95) -> 20 | L95: =COUNTIFS('Data Angt'!$C$5:$C$5809,L$46,'Data Angt'!$F$5:$F$5809,"<=60",'Data Angt'!$H$5:$H$5809,$C95)-COUNTIFS('Data Angt'!$C$5:$C$5809,L$46,'Data Angt'!$F$5:$F$5809,"<46",'Data Angt'!$H$5:$H$5809,$C95) -> 15
C96: Tenaga Ahli | D96: =COUNTIFS('Data Angt'!$F$5:$F$5809,"<=60",'Data Angt'!$H$5:$H$5809,C96)-COUNTIFS('Data Angt'!$F$5:$F$5809,"<46",'Data Angt'!$H$5:$H$5809,C96) -> 11 | E96: =D96/$C$42 -> 0.0018949182 | F96: =COUNTIFS('Data Angt'!$C$5:$C$5809,F$46,'Data Angt'!$F$5:$F$5809,"<=60",'Data Angt'!$H$5:$H$5809,$C96)-COUNTIFS('Data Angt'!$C$5:$C$5809,F$46,'Data Angt'!$F$5:$F$5809,"<46",'Data Angt'!$H$5:$H$5809,$C96) -> 6 | G96: =COUNTIFS('Data Angt'!$C$5:$C$5809,G$46,'Data Angt'!$F$5:$F$5809,"<=60",'Data Angt'!$H$5:$H$5809,$C96)-COUNTIFS('Data Angt'!$C$5:$C$5809,G$46,'Data Angt'!$F$5:$F$5809,"<46",'Data Angt'!$H$5:$H$5809,$C96) -> 2 | H96: =COUNTIFS('Data Angt'!$C$5:$C$5809,H$46,'Data Angt'!$F$5:$F$5809,"<=60",'Data Angt'!$H$5:$H$5809,$C96)-COUNTIFS('Data Angt'!$C$5:$C$5809,H$46,'Data Angt'!$F$5:$F$5809,"<46",'Data Angt'!$H$5:$H$5809,$C96) -> 2 | I96: =COUNTIFS('Data Angt'!$C$5:$C$5809,I$46,'Data Angt'!$F$5:$F$5809,"<=60",'Data Angt'!$H$5:$H$5809,$C96)-COUNTIFS('Data Angt'!$C$5:$C$5809,I$46,'Data Angt'!$F$5:$F$5809,"<46",'Data Angt'!$H$5:$H$5809,$C96) -> 1 | J96: =COUNTIFS('Data Angt'!$C$5:$C$5809,J$46,'Data Angt'!$F$5:$F$5809,"<=60",'Data Angt'!$H$5:$H$5809,$C96)-COUNTIFS('Data Angt'!$C$5:$C$5809,J$46,'Data Angt'!$F$5:$F$5809,"<46",'Data Angt'!$H$5:$H$5809,$C96) -> 0 | K96: =COUNTIFS('Data Angt'!$C$5:$C$5809,K$46,'Data Angt'!$F$5:$F$5809,"<=60",'Data Angt'!$H$5:$H$5809,$C96)-COUNTIFS('Data Angt'!$C$5:$C$5809,K$46,'Data Angt'!$F$5:$F$5809,"<46",'Data Angt'!$H$5:$H$5809,$C96) -> 0 | L96: =COUNTIFS('Data Angt'!$C$5:$C$5809,L$46,'Data Angt'!$F$5:$F$5809,"<=60",'Data Angt'!$H$5:$H$5809,$C96)-COUNTIFS('Data Angt'!$C$5:$C$5809,L$46,'Data Angt'!$F$5:$F$5809,"<46",'Data Angt'!$H$5:$H$5809,$C96) -> 0
C97: Tenaga Medis | D97: =COUNTIFS('Data Angt'!$F$5:$F$5809,"<=60",'Data Angt'!$H$5:$H$5809,C97)-COUNTIFS('Data Angt'!$F$5:$F$5809,"<46",'Data Angt'!$H$5:$H$5809,C97) -> 20 | E97: =D97/$C$42 -> 0.0034453058 | F97: =COUNTIFS('Data Angt'!$C$5:$C$5809,F$46,'Data Angt'!$F$5:$F$5809,"<=60",'Data Angt'!$H$5:$H$5809,$C97)-COUNTIFS('Data Angt'!$C$5:$C$5809,F$46,'Data Angt'!$F$5:$F$5809,"<46",'Data Angt'!$H$5:$H$5809,$C97) -> 7 | G97: =COUNTIFS('Data Angt'!$C$5:$C$5809,G$46,'Data Angt'!$F$5:$F$5809,"<=60",'Data Angt'!$H$5:$H$5809,$C97)-COUNTIFS('Data Angt'!$C$5:$C$5809,G$46,'Data Angt'!$F$5:$F$5809,"<46",'Data Angt'!$H$5:$H$5809,$C97) -> 1 | H97: =COUNTIFS('Data Angt'!$C$5:$C$5809,H$46,'Data Angt'!$F$5:$F$5809,"<=60",'Data Angt'!$H$5:$H$5809,$C97)-COUNTIFS('Data Angt'!$C$5:$C$5809,H$46,'Data Angt'!$F$5:$F$5809,"<46",'Data Angt'!$H$5:$H$5809,$C97) -> 7 | I97: =COUNTIFS('Data Angt'!$C$5:$C$5809,I$46,'Data Angt'!$F$5:$F$5809,"<=60",'Data Angt'!$H$5:$H$5809,$C97)-COUNTIFS('Data Angt'!$C$5:$C$5809,I$46,'Data Angt'!$F$5:$F$5809,"<46",'Data Angt'!$H$5:$H$5809,$C97) -> 0 | J97: =COUNTIFS('Data Angt'!$C$5:$C$5809,J$46,'Data Angt'!$F$5:$F$5809,"<=60",'Data Angt'!$H$5:$H$5809,$C97)-COUNTIFS('Data Angt'!$C$5:$C$5809,J$46,'Data Angt'!$F$5:$F$5809,"<46",'Data Angt'!$H$5:$H$5809,$C97) -> 3 | K97: =COUNTIFS('Data Angt'!$C$5:$C$5809,K$46,'Data Angt'!$F$5:$F$5809,"<=60",'Data Angt'!$H$5:$H$5809,$C97)-COUNTIFS('Data Angt'!$C$5:$C$5809,K$46,'Data Angt'!$F$5:$F$5809,"<46",'Data Angt'!$H$5:$H$5809,$C97) -> 1 | L97: =COUNTIFS('Data Angt'!$C$5:$C$5809,L$46,'Data Angt'!$F$5:$F$5809,"<=60",'Data Angt'!$H$5:$H$5809,$C97)-COUNTIFS('Data Angt'!$C$5:$C$5809,L$46,'Data Angt'!$F$5:$F$5809,"<46",'Data Angt'!$H$5:$H$5809,$C97) -> 1
C98: Petani/Pekebun/Nelayan | D98: =COUNTIFS('Data Angt'!$F$5:$F$5809,"<=60",'Data Angt'!$H$5:$H$5809,C98)-COUNTIFS('Data Angt'!$F$5:$F$5809,"<46",'Data Angt'!$H$5:$H$5809,C98) -> 33 | E98: =D98/$C$42 -> 0.0056847545 | F98: =COUNTIFS('Data Angt'!$C$5:$C$5809,F$46,'Data Angt'!$F$5:$F$5809,"<=60",'Data Angt'!$H$5:$H$5809,$C98)-COUNTIFS('Data Angt'!$C$5:$C$5809,F$46,'Data Angt'!$F$5:$F$5809,"<46",'Data Angt'!$H$5:$H$5809,$C98) -> 5 | G98: =COUNTIFS('Data Angt'!$C$5:$C$5809,G$46,'Data Angt'!$F$5:$F$5809,"<=60",'Data Angt'!$H$5:$H$5809,$C98)-COUNTIFS('Data Angt'!$C$5:$C$5809,G$46,'Data Angt'!$F$5:$F$5809,"<46",'Data Angt'!$H$5:$H$5809,$C98) -> 13 | H98: =COUNTIFS('Data Angt'!$C$5:$C$5809,H$46,'Data Angt'!$F$5:$F$5809,"<=60",'Data Angt'!$H$5:$H$5809,$C98)-COUNTIFS('Data Angt'!$C$5:$C$5809,H$46,'Data Angt'!$F$5:$F$5809,"<46",'Data Angt'!$H$5:$H$5809,$C98) -> 5 | I98: =COUNTIFS('Data Angt'!$C$5:$C$5809,I$46,'Data Angt'!$F$5:$F$5809,"<=60",'Data Angt'!$H$5:$H$5809,$C98)-COUNTIFS('Data Angt'!$C$5:$C$5809,I$46,'Data Angt'!$F$5:$F$5809,"<46",'Data Angt'!$H$5:$H$5809,$C98) -> 3 | J98: =COUNTIFS('Data Angt'!$C$5:$C$5809,J$46,'Data Angt'!$F$5:$F$5809,"<=60",'Data Angt'!$H$5:$H$5809,$C98)-COUNTIFS('Data Angt'!$C$5:$C$5809,J$46,'Data Angt'!$F$5:$F$5809,"<46",'Data Angt'!$H$5:$H$5809,$C98) -> 0 | K98: =COUNTIFS('Data Angt'!$C$5:$C$5809,K$46,'Data Angt'!$F$5:$F$5809,"<=60",'Data Angt'!$H$5:$H$5809,$C98)-COUNTIFS('Data Angt'!$C$5:$C$5809,K$46,'Data Angt'!$F$5:$F$5809,"<46",'Data Angt'!$H$5:$H$5809,$C98) -> 7 | L98: =COUNTIFS('Data Angt'!$C$5:$C$5809,L$46,'Data Angt'!$F$5:$F$5809,"<=60",'Data Angt'!$H$5:$H$5809,$C98)-COUNTIFS('Data Angt'!$C$5:$C$5809,L$46,'Data Angt'!$F$5:$F$5809,"<46",'Data Angt'!$H$5:$H$5809,$C98) -> 0
C99: Pensiunan | D99: =COUNTIFS('Data Angt'!$F$5:$F$5809,"<=60",'Data Angt'!$H$5:$H$5809,C99)-COUNTIFS('Data Angt'!$F$5:$F$5809,"<46",'Data Angt'!$H$5:$H$5809,C99) -> 21 | E99: =D99/$C$42 -> 0.0036175711 | F99: =COUNTIFS('Data Angt'!$C$5:$C$5809,F$46,'Data Angt'!$F$5:$F$5809,"<=60",'Data Angt'!$H$5:$H$5809,$C99)-COUNTIFS('Data Angt'!$C$5:$C$5809,F$46,'Data Angt'!$F$5:$F$5809,"<46",'Data Angt'!$H$5:$H$5809,$C99) -> 11 | G99: =COUNTIFS('Data Angt'!$C$5:$C$5809,G$46,'Data Angt'!$F$5:$F$5809,"<=60",'Data Angt'!$H$5:$H$5809,$C99)-COUNTIFS('Data Angt'!$C$5:$C$5809,G$46,'Data Angt'!$F$5:$F$5809,"<46",'Data Angt'!$H$5:$H$5809,$C99) -> 1 | H99: =COUNTIFS('Data Angt'!$C$5:$C$5809,H$46,'Data Angt'!$F$5:$F$5809,"<=60",'Data Angt'!$H$5:$H$5809,$C99)-COUNTIFS('Data Angt'!$C$5:$C$5809,H$46,'Data Angt'!$F$5:$F$5809,"<46",'Data Angt'!$H$5:$H$5809,$C99) -> 4 | I99: =COUNTIFS('Data Angt'!$C$5:$C$5809,I$46,'Data Angt'!$F$5:$F$5809,"<=60",'Data Angt'!$H$5:$H$5809,$C99)-COUNTIFS('Data Angt'!$C$5:$C$5809,I$46,'Data Angt'!$F$5:$F$5809,"<46",'Data Angt'!$H$5:$H$5809,$C99) -> 1 | J99: =COUNTIFS('Data Angt'!$C$5:$C$5809,J$46,'Data Angt'!$F$5:$F$5809,"<=60",'Data Angt'!$H$5:$H$5809,$C99)-COUNTIFS('Data Angt'!$C$5:$C$5809,J$46,'Data Angt'!$F$5:$F$5809,"<46",'Data Angt'!$H$5:$H$5809,$C99) -> 2 | K99: =COUNTIFS('Data Angt'!$C$5:$C$5809,K$46,'Data Angt'!$F$5:$F$5809,"<=60",'Data Angt'!$H$5:$H$5809,$C99)-COUNTIFS('Data Angt'!$C$5:$C$5809,K$46,'Data Angt'!$F$5:$F$5809,"<46",'Data Angt'!$H$5:$H$5809,$C99) -> 2 | L99: =COUNTIFS('Data Angt'!$C$5:$C$5809,L$46,'Data Angt'!$F$5:$F$5809,"<=60",'Data Angt'!$H$5:$H$5809,$C99)-COUNTIFS('Data Angt'!$C$5:$C$5809,L$46,'Data Angt'!$F$5:$F$5809,"<46",'Data Angt'!$H$5:$H$5809,$C99) -> 0
C100: Belum/Tidak Bekerja | D100: =COUNTIFS('Data Angt'!$F$5:$F$5809,"<=60",'Data Angt'!$H$5:$H$5809,C100)-COUNTIFS('Data Angt'!$F$5:$F$5809,"<46",'Data Angt'!$H$5:$H$5809,C100) -> 30 | E100: =D100/$C$42 -> 0.0051679587 | F100: =COUNTIFS('Data Angt'!$C$5:$C$5809,F$46,'Data Angt'!$F$5:$F$5809,"<=60",'Data Angt'!$H$5:$H$5809,$C100)-COUNTIFS('Data Angt'!$C$5:$C$5809,F$46,'Data Angt'!$F$5:$F$5809,"<46",'Data Angt'!$H$5:$H$5809,$C100) -> 9 | G100: =COUNTIFS('Data Angt'!$C$5:$C$5809,G$46,'Data Angt'!$F$5:$F$5809,"<=60",'Data Angt'!$H$5:$H$5809,$C100)-COUNTIFS('Data Angt'!$C$5:$C$5809,G$46,'Data Angt'!$F$5:$F$5809,"<46",'Data Angt'!$H$5:$H$5809,$C100) -> 5 | H100: =COUNTIFS('Data Angt'!$C$5:$C$5809,H$46,'Data Angt'!$F$5:$F$5809,"<=60",'Data Angt'!$H$5:$H$5809,$C100)-COUNTIFS('Data Angt'!$C$5:$C$5809,H$46,'Data Angt'!$F$5:$F$5809,"<46",'Data Angt'!$H$5:$H$5809,$C100) -> 0 | I100: =COUNTIFS('Data Angt'!$C$5:$C$5809,I$46,'Data Angt'!$F$5:$F$5809,"<=60",'Data Angt'!$H$5:$H$5809,$C100)-COUNTIFS('Data Angt'!$C$5:$C$5809,I$46,'Data Angt'!$F$5:$F$5809,"<46",'Data Angt'!$H$5:$H$5809,$C100) -> 0 | J100: =COUNTIFS('Data Angt'!$C$5:$C$5809,J$46,'Data Angt'!$F$5:$F$5809,"<=60",'Data Angt'!$H$5:$H$5809,$C100)-COUNTIFS('Data Angt'!$C$5:$C$5809,J$46,'Data Angt'!$F$5:$F$5809,"<46",'Data Angt'!$H$5:$H$5809,$C100) -> 9 | K100: =COUNTIFS('Data Angt'!$C$5:$C$5809,K$46,'Data Angt'!$F$5:$F$5809,"<=60",'Data Angt'!$H$5:$H$5809,$C100)-COUNTIFS('Data Angt'!$C$5:$C$5809,K$46,'Data Angt'!$F$5:$F$5809,"<46",'Data Angt'!$H$5:$H$5809,$C100) -> 7 | L100: =COUNTIFS('Data Angt'!$C$5:$C$5809,L$46,'Data Angt'!$F$5:$F$5809,"<=60",'Data Angt'!$H$5:$H$5809,$C100)-COUNTIFS('Data Angt'!$C$5:$C$5809,L$46,'Data Angt'!$F$5:$F$5809,"<46",'Data Angt'!$H$5:$H$5809,$C100) -> 0
